Workbook
Name Slicer_Category: #N/A
Name Slicer_Region: #N/A

Sheet New Dashboard
A1: E -Commerce Sales DataSet
K3: How they like to buy

Sheet PIVOTS
A3: Sum of Total_Amount | B3: Column Labels
A4: Row Labels | B4: East | C4: North | D4: South | E4: West | F4: Grand Total
A5: Beauty | B5: 93738.074 | C5: 90887.545 | D5: 101876.16 | E5: 35059.548 | F5: 321561.33 | O5: Sum of Total_Amount | P5: . | U5: =P6 -> Female | V5: =Q6 -> Male
A6: Clothing | B6: 105166.69 | C6: 111832.22 | D6: 113264.13 | E6: 48953.004 | F6: 379216.04 | O6: Row Labels | P6: Female | Q6: Male | R6: Grand Total | T6: =O7 -> Flagship | U6: =P7 -> 0.21581193 | V6: =Q7 -> 0.17444687
A7: Electronics | B7: 133221.68 | C7: 147510.96 | D7: 147714.64 | E7: 75864.076 | F7: 504311.35 | O7: Flagship | P7: 0.21581193 | Q7: 0.17444687 | R7: 0.3902588 | T7: =O8 -> Online | U7: =P8 -> 0.24160718 | V7: =Q8 -> 0.17885628
A8: Home | B8: 120153.86 | C8: 129789.2 | D8: 117057.06 | E8: 60295.68 | F8: 427295.8 | O8: Online | P8: 0.24160718 | Q8: 0.17885628 | R8: 0.42046346 | T8: =O9 -> Outlet | U8: =P9 -> 0.10891976 | V8: =Q9 -> 0.080357978
A9: Sports | B9: 170124.02 | C9: 166080.96 | D9: 155301.1 | E9: 50504.098 | F9: 542010.17 | O9: Outlet | P9: 0.10891976 | Q9: 0.080357978 | R9: 0.18927774
A10: Grand Total | B10: 622404.32 | C10: 646100.88 | D10: 635213.1 | E10: 270676.41 | F10: 2174394.7 | O10: Grand Total | P10: 0.56633887 | Q10: 0.43366113 | R10: 1
B15: Count of Sales_ID | C15: Column Labels | O15: Row Labels | P15: Sum of Quantity
B16: Row Labels | C16: Flagship | D16: Online | E16: Outlet | F16: Grand Total | O16: CUST1054 | P16: 30
B17: COD | C17: 288 | D17: 254 | E17: 118 | F17: 660 | O17: CUST1219 | P17: 29
B18: Credit Card | C18: 243 | D18: 269 | E18: 133 | F18: 645 | O18: CUST1108 | P18: 27
B19: PayPal | C19: 263 | D19: 299 | E19: 133 | F19: 695 | I19: Row Labels | J19: Sum of Total_Amount | O19: CUST1084 | P19: 27
B20: Grand Total | C20: 794 | D20: 822 | E20: 384 | F20: 2000 | I20: 2023 | J20: 223812.72 | O20: CUST1470 | P20: 25 | W20: Sum of Quantity | X20: Column Labels | AC20: Row Labels | AD20: Sum of Quantity | AE20: Sum of Total_Amount
I21: Qtr4 | J21: 223812.72 | L21: Row Labels | M21: Sum of Total_Amount | O21: CUST1051 | P21: 25 | W21: Row Labels | X21: Female | Y21: Male | Z21: Grand Total | AC21: Alabama | AD21: 105 | AE21: 49377.684 | AH21: USA | AI21: =AC21 -> Alabama | AJ21: =AD21 -> 105
I22: 2024 | J22: 1093911.8 | L22: 2023 | M22: 223812.72 | O22: CUST1168 | P22: 25 | W22: Sports | X22: 714 | Y22: 527 | Z22: 1241 | AC22: Alaska | AD22: 103 | AE22: 49032.414 | AH22: USA | AI22: =AC22 -> Alaska | AJ22: =AD22 -> 103
C23: Column Labels | I23: Qtr1 | J23: 268596.98 | L23: 2024 | M23: 1093911.8 | O23: CUST1007 | P23: 25 | W23: Electronics | X23: 657 | Y23: 508 | Z23: 1165 | AC23: Arizona | AD23: 101 | AE23: 46317.776 | AH23: USA | AI23: =AC23 -> Arizona | AJ23: =AD23 -> 101
C24: East | D24: North | E24: South | F24: West | G24: Grand Total | I24: Qtr2 | J24: 245299.96 | L24: 2025 | M24: 856670.18 | O24: CUST1013 | P24: 24 | W24: Home | X24: 514 | Y24: 460 | Z24: 974 | AC24: Arkansas | AD24: 61 | AE24: 24828.745 | AH24: USA | AI24: =AC24 -> Arkansas | AJ24: =AD24 -> 61
B25: Sum of Total_Amount | C25: 622404.32 | D25: 646100.88 | E25: 635213.1 | F25: 270676.41 | G25: 2174394.7 | I25: Qtr3 | J25: 285586.04 | L25: Grand Total | M25: 2174394.7 | O25: CUST1371 | P25: 24 | W25: Clothing | X25: 483 | Y25: 363 | Z25: 846 | AC25: California | AD25: 124 | AE25: 47072.305 | AH25: USA | AI25: =AC25 -> California | AJ25: =AD25 -> 124
I26: Qtr4 | J26: 294428.82 | O26: CUST1057 | P26: 24 | W26: Beauty | X26: 404 | Y26: 334 | Z26: 738 | AC26: Colorado | AD26: 21 | AE26: 9312.2465 | AH26: USA | AI26: =AC26 -> Colorado | AJ26: =AD26 -> 21
I27: 2025 | J27: 856670.18 | O27: CUST1067 | P27: 23 | W27: Grand Total | X27: 2772 | Y27: 2192 | Z27: 4964 | AC27: Connecticut | AD27: 142 | AE27: 56723.038 | AH27: USA | AI27: =AC27 -> Connecticut | AJ27: =AD27 -> 142
I28: Qtr1 | J28: 271630.62 | O28: CUST1373 | P28: 22 | AC28: Delaware | AD28: 84 | AE28: 29967.98 | AH28: USA | AI28: =AC28 -> Delaware | AJ28: =AD28 -> 84
I29: Qtr2 | J29: 256716.06 | O29: CUST1348 | P29: 22 | AC29: Florida | AD29: 127 | AE29: 60406.676 | AH29: USA | AI29: =AC29 -> Florida | AJ29: =AD29 -> 127
I30: Qtr3 | J30: 289855.68 | O30: CUST1485 | P30: 22 | AC30: Georgia | AD30: 123 | AE30: 47224.799 | AH30: USA | AI30: =AC30 -> Georgia | AJ30: =AD30 -> 123
I31: Qtr4 | J31: 38467.816 | O31: CUST1147 | P31: 21 | AC31: Hawaii | AD31: 75 | AE31: 34436.901 | AH31: USA | AI31: =AC31 -> Hawaii | AJ31: =AD31 -> 75
I32: Grand Total | J32: 2174394.7 | O32: CUST1466 | P32: 21 | AC32: Idaho | AD32: 25 | AE32: 12801.172 | AH32: USA | AI32: =AC32 -> Idaho | AJ32: =AD32 -> 25
O33: CUST1052 | P33: 20 | AC33: Illinois | AD33: 74 | AE33: 32348.639 | AH33: USA | AI33: =AC33 -> Illinois | AJ33: =AD33 -> 74
O34: CUST1101 | P34: 20 | AC34: Indiana | AD34: 108 | AE34: 51827.029 | AH34: USA | AI34: =AC34 -> Indiana | AJ34: =AD34 -> 108
O35: CUST1478 | P35: 19 | AC35: Iowa | AD35: 126 | AE35: 51613.308 | AH35: USA | AI35: =AC35 -> Iowa | AJ35: =AD35 -> 126
O36: CUST1251 | P36: 19 | AC36: Kansas | AD36: 124 | AE36: 58787.176 | AH36: USA | AI36: =AC36 -> Kansas | AJ36: =AD36 -> 124
O37: CUST1156 | P37: 19 | AC37: Kentucky | AD37: 60 | AE37: 23445.226 | AH37: USA | AI37: =AC37 -> Kentucky | AJ37: =AD37 -> 60
O38: CUST1462 | P38: 19 | AC38: Louisiana | AD38: 97 | AE38: 41264.121 | AH38: USA | AI38: =AC38 -> Louisiana | AJ38: =AD38 -> 97
O39: CUST1104 | P39: 19 | AC39: Maine | AD39: 92 | AE39: 43827.302 | AH39: USA | AI39: =AC39 -> Maine | AJ39: =AD39 -> 92
O40: CUST1039 | P40: 19 | AC40: Maryland | AD40: 75 | AE40: 27871.036 | AH40: USA | AI40: =AC40 -> Maryland | AJ40: =AD40 -> 75
O41: CUST1209 | P41: 19 | AC41: Massachusetts | AD41: 55 | AE41: 26107.866 | AH41: USA | AI41: =AC41 -> Massachusetts | AJ41: =AD41 -> 55
O42: CUST1248 | P42: 19 | AC42: Michigan | AD42: 109 | AE42: 44872.697 | AH42: USA | AI42: =AC42 -> Michigan | AJ42: =AD42 -> 109
O43: CUST1384 | P43: 18 | AC43: Minnesota | AD43: 106 | AE43: 47628.872 | AH43: USA | AI43: =AC43 -> Minnesota | AJ43: =AD43 -> 106
O44: CUST1072 | P44: 18 | AC44: Mississippi | AD44: 51 | AE44: 30570.603 | AH44: USA | AI44: =AC44 -> Mississippi | AJ44: =AD44 -> 51
... O70: CUST1164 | P70: 17 | AC70: Wyoming | AD70: 47 | AE70: 17815.739 | AH70: USA | AI70: =AC70 -> Wyoming | AJ70: =AD70 -> 47
O71: CUST1343 | P71: 17 | AC71: Grand Total | AD71: 4964 | AE71: 2174394.7
O72: CUST1492 | P72: 17
O73: CUST1388 | P73: 17
O74: CUST1221 | P74: 17
O75: CUST1420 | P75: 17
O76: CUST1257 | P76: 17
O77: CUST1453 | P77: 17
O78: CUST1277 | P78: 17
O79: CUST1012 | P79: 17
O80: CUST1381 | P80: 16
O81: CUST1056 | P81: 16
O82: CUST1443 | P82: 16
O83: CUST1148 | P83: 16
... O508: Grand Total | P508: 4964

Sheet Summary
A1: INSIGHTS
A3: 1 | B3: This assignment focuses on analyzing an Ecommerce dataset using Microsoft Excel. The dataset was imported into Excel and organized into structured tables for efficient analysis. Multiple sheets were used to clearly separate raw data, cleaned data, pivot tables, and dashboard elements.
A7: 2 | B7: Data cleaning was performed to ensure accuracy and consistency
A8: 3 | B8: Duplicate records were identified and removed, missing values were handled appropriately, and formatting issues such as date and numeric inconsistencies were corrected. Data validation techniques were applied to maintain data quality.
A9: 4 | B9: Excel formulas such as SUM, SUMIF, COUNTIF, AVERAGE, TEXT, and
A10: 5 | B10: VLOOKUP were used to combine data from multiple tables. VLOOKUP was used to link related datasets
A11: 6 | B11: Descriptive statistics including mean, median, and standard deviation were calculated using Analysis ToolPak,
A12: 7 | B12: Pivot Tables were created to summarize data across multiple dimensions such as category, product and region
A13: 8 | B13: Pivot Tables formed the foundation for analysis and dashboard visuals.
A14: 9 | B14: An interactive dashboard was built using Column, Bar, and Pie charts along with PivotCharts and slicers. Key Performance Indicators (KPIs) such as Total Sales, Total Orders, Average Order Value, highlighted at the side of the dashboard for quick insights
A15: 10 | B15: Key findings show that certain product categories contribute significantly more to overall revenue, while a few top products drive the majority of sales. Monthly sales trends reveal seasonal patterns, and regional analysis highlights high-performing locations. Overall, this analysis provides meaningful insights into sales performance, customer behavior, and product contribution using Excel tools.

Sheet Sales_Fact (3)
A1: Sales_ID | B1: Customer Name | C1: City | D1: Age | E1: Sex | F1: State | G1: Loyalty_level | H1: Customer_ID | I1: Order date | J1: Product_ID | K1: Category | L1: Sub_Category | M1: Product Cost | N1: Stock | O1: Store_ID | P1: StoreName | Q1: Region | R1: Store city | S1: Store Type | T1: Quantity | U1: Unit_Price | V1: Discount | W1: Payment_Type | X1: Total_Amount
A2: SALE0 | B2: =VLOOKUP(Table6[[#This Row],[Customer_ID]],Table1[[Customer_ID]:[Name]],2,FALSE) -> Sarah Smith | C2: =VLOOKUP(Table6[[#This Row],[Customer_ID]],Table1[[Customer_ID]:[City]],5,FALSE) -> Kathleenport | D2: =VLOOKUP(Table6[[#This Row],[Customer_ID]],Table1[],3,FALSE) -> 55 | E2: =VLOOKUP(Table6[[#This Row],[Customer_ID]],Table1[],4,FALSE) -> Male | F2: =VLOOKUP(Table6[[#This Row],[Customer_ID]],Table1[],6,FALSE) -> Wyoming | G2: =VLOOKUP(Table6[[#This Row],[Customer_ID]],Table1[],8,FALSE) -> Gold | H2: CUST1409 | I2: 45480 | J2: PROD97 | K2: =VLOOKUP($J2,'Product_Dim (2)'!$A$2:$G$101,{3,4,5,6},FALSE) -> Sports | L2: =VLOOKUP($J2,'Product_Dim (2)'!$A$2:$G$101,{4,5,6},FALSE) -> Team Sports | M2: {=VLOOKUP($J2,'Product_Dim (2)'!$A$2:$G$101,{6},FALSE)} -> 245.98 | N2: =VLOOKUP($J2,'Product_Dim (2)'!$A$2:$G$101,7,FALSE) -> 471 | O2: STORE3 | P2: =VLOOKUP($O2,'Store_Dim (2)'!$A$2:$E$21,2,FALSE) -> Johnson-Wright | Q2: =VLOOKUP(Table6[[#This Row],[Store_ID]],Table4[],3,FALSE) -> North | R2: =VLOOKUP(Table6[[#This Row],[Store_ID]],Table4[],4,FALSE) -> Hoodberg | S2: =VLOOKUP(Table6[[#This Row],[Store_ID]],Table4[],5,FALSE) -> Outlet | T2: 1 | U2: 218.04 | V2: 0.09 | W2: Credit Card | X2: 198.4164
A3: SALE1 | B3: =VLOOKUP(Table6[[#This Row],[Customer_ID]],Table1[[Customer_ID]:[Name]],2,FALSE) -> Michael Foley | C3: =VLOOKUP(Table6[[#This Row],[Customer_ID]],Table1[[Customer_ID]:[City]],5,FALSE) -> Oneillfurt | D3: =VLOOKUP(Table6[[#This Row],[Customer_ID]],Table1[],3,FALSE) -> 63 | E3: =VLOOKUP(Table6[[#This Row],[Customer_ID]],Table1[],4,FALSE) -> Female | F3: =VLOOKUP(Table6[[#This Row],[Customer_ID]],Table1[],6,FALSE) -> Vermont | G3: =VLOOKUP(Table6[[#This Row],[Customer_ID]],Table1[],8,FALSE) -> Gold | H3: CUST1467 | I3: 45285 | J3: PROD74 | K3: =VLOOKUP($J3,'Product_Dim (2)'!$A$2:$G$101,{3,4,5,6},FALSE) -> Electronics | L3: =VLOOKUP($J3,'Product_Dim (2)'!$A$2:$G$101,{4,5,6},FALSE) -> Audio | M3: {=VLOOKUP($J3,'Product_Dim (2)'!$A$2:$G$101,{6},FALSE)} -> 403.71 | N3: =VLOOKUP($J3,'Product_Dim (2)'!$A$2:$G$101,7,FALSE) -> 159 | O3: STORE17 | P3: =VLOOKUP($O3,'Store_Dim (2)'!$A$2:$E$21,2,FALSE) -> Holloway Ltd | Q3: =VLOOKUP(Table6[[#This Row],[Store_ID]],Table4[],3,FALSE) -> North | R3: =VLOOKUP(Table6[[#This Row],[Store_ID]],Table4[],4,FALSE) -> Bensonhaven | S3: =VLOOKUP(Table6[[#This Row],[Store_ID]],Table4[],5,FALSE) -> Flagship | T3: 3 | U3: 104.47 | V3: 0.27 | W3: PayPal | X3: 228.7893
A4: SALE2 | B4: =VLOOKUP(Table6[[#This Row],[Customer_ID]],Table1[[Customer_ID]:[Name]],2,FALSE) -> Christopher Sutton | C4: =VLOOKUP(Table6[[#This Row],[Customer_ID]],Table1[[Customer_ID]:[City]],5,FALSE) -> Deborahberg | D4: =VLOOKUP(Table6[[#This Row],[Customer_ID]],Table1[],3,FALSE) -> 49 | E4: =VLOOKUP(Table6[[#This Row],[Customer_ID]],Table1[],4,FALSE) -> Female | F4: =VLOOKUP(Table6[[#This Row],[Customer_ID]],Table1[],6,FALSE) -> Pennsylvania | G4: =VLOOKUP(Table6[[#This Row],[Customer_ID]],Table1[],8,FALSE) -> Gold | H4: CUST1056 | I4: 45446 | J4: PROD49 | K4: =VLOOKUP($J4,'Product_Dim (2)'!$A$2:$G$101,{3,4,5,6},FALSE) -> Beauty | L4: =VLOOKUP($J4,'Product_Dim (2)'!$A$2:$G$101,{4,5,6},FALSE) -> Fragrance | M4: {=VLOOKUP($J4,'Product_Dim (2)'!$A$2:$G$101,{6},FALSE)} -> 43.29 | N4: =VLOOKUP($J4,'Product_Dim (2)'!$A$2:$G$101,7,FALSE) -> 267 | O4: STORE8 | P4: =VLOOKUP($O4,'Store_Dim (2)'!$A$2:$E$21,2,FALSE) -> Bean, Jones and Park | Q4: =VLOOKUP(Table6[[#This Row],[Store_ID]],Table4[],3,FALSE) -> West | R4: =VLOOKUP(Table6[[#This Row],[Store_ID]],Table4[],4,FALSE) -> Thompsonborough | S4: =VLOOKUP(Table6[[#This Row],[Store_ID]],Table4[],5,FALSE) -> Online | T4: 4 | U4: 914.05 | V4: 0.25 | W4: Credit Card | X4: 2742.15
A5: SALE3 | B5: =VLOOKUP(Table6[[#This Row],[Customer_ID]],Table1[[Customer_ID]:[Name]],2,FALSE) -> John Jordan | C5: =VLOOKUP(Table6[[#This Row],[Customer_ID]],Table1[[Customer_ID]:[City]],5,FALSE) -> Port Crystalberg | D5: =VLOOKUP(Table6[[#This Row],[Customer_ID]],Table1[],3,FALSE) -> 58 | E5: =VLOOKUP(Table6[[#This Row],[Customer_ID]],Table1[],4,FALSE) -> Female | F5: =VLOOKUP(Table6[[#This Row],[Customer_ID]],Table1[],6,FALSE) -> Tennessee | G5: =VLOOKUP(Table6[[#This Row],[Customer_ID]],Table1[],8,FALSE) -> Platinum | H5: CUST1346 | I5: 45259 | J5: PROD76 | K5: =VLOOKUP($J5,'Product_Dim (2)'!$A$2:$G$101,{3,4,5,6},FALSE) -> Electronics | L5: =VLOOKUP($J5,'Product_Dim (2)'!$A$2:$G$101,{4,5,6},FALSE) -> Computer | M5: {=VLOOKUP($J5,'Product_Dim (2)'!$A$2:$G$101,{6},FALSE)} -> 392.89 | N5: =VLOOKUP($J5,'Product_Dim (2)'!$A$2:$G$101,7,FALSE) -> 320 | O5: STORE8 | P5: =VLOOKUP($O5,'Store_Dim (2)'!$A$2:$E$21,2,FALSE) -> Bean, Jones and Park | Q5: =VLOOKUP(Table6[[#This Row],[Store_ID]],Table4[],3,FALSE) -> West | R5: =VLOOKUP(Table6[[#This Row],[Store_ID]],Table4[],4,FALSE) -> Thompsonborough | S5: =VLOOKUP(Table6[[#This Row],[Store_ID]],Table4[],5,FALSE) -> Online | T5: 1 | U5: 921.51 | V5: 0.16 | W5: COD | X5: 774.0684
A6: SALE4 | B6: =VLOOKUP(Table6[[#This Row],[Customer_ID]],Table1[[Customer_ID]:[Name]],2,FALSE) -> Amanda Powell | C6: =VLOOKUP(Table6[[#This Row],[Customer_ID]],Table1[[Customer_ID]:[City]],5,FALSE) -> South William | D6: =VLOOKUP(Table6[[#This Row],[Customer_ID]],Table1[],3,FALSE) -> 28 | E6: =VLOOKUP(Table6[[#This Row],[Customer_ID]],Table1[],4,FALSE) -> Male | F6: =VLOOKUP(Table6[[#This Row],[Customer_ID]],Table1[],6,FALSE) -> Alabama | G6: =VLOOKUP(Table6[[#This Row],[Customer_ID]],Table1[],8,FALSE) -> Silver | H6: CUST1493 | I6: 45297 | J6: PROD59 | K6: =VLOOKUP($J6,'Product_Dim (2)'!$A$2:$G$101,{3,4,5,6},FALSE) -> Beauty | L6: =VLOOKUP($J6,'Product_Dim (2)'!$A$2:$G$101,{4,5,6},FALSE) -> Haircare | M6: {=VLOOKUP($J6,'Product_Dim (2)'!$A$2:$G$101,{6},FALSE)} -> 17.31 | N6: =VLOOKUP($J6,'Product_Dim (2)'!$A$2:$G$101,7,FALSE) -> 399 | O6: STORE5 | P6: =VLOOKUP($O6,'Store_Dim (2)'!$A$2:$E$21,2,FALSE) -> Gray Ltd | Q6: =VLOOKUP(Table6[[#This Row],[Store_ID]],Table4[],3,FALSE) -> North | R6: =VLOOKUP(Table6[[#This Row],[Store_ID]],Table4[],4,FALSE) -> New Michaelchester | S6: =VLOOKUP(Table6[[#This Row],[Store_ID]],Table4[],5,FALSE) -> Outlet | T6: 3 | U6: 745.3 | V6: 0.18 | W6: Credit Card | X6: 1833.438
A7: SALE5 | B7: =VLOOKUP(Table6[[#This Row],[Customer_ID]],Table1[[Customer_ID]:[Name]],2,FALSE) -> Anthony Phillips | C7: =VLOOKUP(Table6[[#This Row],[Customer_ID]],Table1[[Customer_ID]:[City]],5,FALSE) -> North Davidport | D7: =VLOOKUP(Table6[[#This Row],[Customer_ID]],Table1[],3,FALSE) -> 18 | E7: =VLOOKUP(Table6[[#This Row],[Customer_ID]],Table1[],4,FALSE) -> Female | F7: =VLOOKUP(Table6[[#This Row],[Customer_ID]],Table1[],6,FALSE) -> Rhode Island | G7: =VLOOKUP(Table6[[#This Row],[Customer_ID]],Table1[],8,FALSE) -> Platinum | H7: CUST1116 | I7: 45499 | J7: PROD15 | K7: =VLOOKUP($J7,'Product_Dim (2)'!$A$2:$G$101,{3,4,5,6},FALSE) -> Electronics | L7: =VLOOKUP($J7,'Product_Dim (2)'!$A$2:$G$101,{4,5,6},FALSE) -> Appliances | M7: {=VLOOKUP($J7,'Product_Dim (2)'!$A$2:$G$101,{6},FALSE)} -> 465.34 | N7: =VLOOKUP($J7,'Product_Dim (2)'!$A$2:$G$101,7,FALSE) -> 301 | O7: STORE7 | P7: =VLOOKUP($O7,'Store_Dim (2)'!$A$2:$E$21,2,FALSE) -> Martinez-Mullins | Q7: =VLOOKUP(Table6[[#This Row],[Store_ID]],Table4[],3,FALSE) -> South | R7: =VLOOKUP(Table6[[#This Row],[Store_ID]],Table4[],4,FALSE) -> Williamsfurt | S7: =VLOOKUP(Table6[[#This Row],[Store_ID]],Table4[],5,FALSE) -> Online | T7: 3 | U7: 147.01 | V7: 0.19 | W7: COD | X7: 357.2343
A8: SALE6 | B8: =VLOOKUP(Table6[[#This Row],[Customer_ID]],Table1[[Customer_ID]:[Name]],2,FALSE) -> John Scott | C8: =VLOOKUP(Table6[[#This Row],[Customer_ID]],Table1[[Customer_ID]:[City]],5,FALSE) -> South Christopher | D8: =VLOOKUP(Table6[[#This Row],[Customer_ID]],Table1[],3,FALSE) -> 24 | E8: =VLOOKUP(Table6[[#This Row],[Customer_ID]],Table1[],4,FALSE) -> Female | F8: =VLOOKUP(Table6[[#This Row],[Customer_ID]],Table1[],6,FALSE) -> Pennsylvania | G8: =VLOOKUP(Table6[[#This Row],[Customer_ID]],Table1[],8,FALSE) -> Bronze | H8: CUST1016 | I8: 45850 | J8: PROD56 | K8: =VLOOKUP($J8,'Product_Dim (2)'!$A$2:$G$101,{3,4,5,6},FALSE) -> Home | L8: =VLOOKUP($J8,'Product_Dim (2)'!$A$2:$G$101,{4,5,6},FALSE) -> Decor | M8: {=VLOOKUP($J8,'Product_Dim (2)'!$A$2:$G$101,{6},FALSE)} -> 461.47 | N8: =VLOOKUP($J8,'Product_Dim (2)'!$A$2:$G$101,7,FALSE) -> 190 | O8: STORE4 | P8: =VLOOKUP($O8,'Store_Dim (2)'!$A$2:$E$21,2,FALSE) -> Alexander Group | Q8: =VLOOKUP(Table6[[#This Row],[Store_ID]],Table4[],3,FALSE) -> South | R8: =VLOOKUP(Table6[[#This Row],[Store_ID]],Table4[],4,FALSE) -> Port Sharon | S8: =VLOOKUP(Table6[[#This Row],[Store_ID]],Table4[],5,FALSE) -> Online | T8: 2 | U8: 785.31 | V8: 0.15 | W8: PayPal | X8: 1335.027
A9: SALE7 | B9: =VLOOKUP(Table6[[#This Row],[Customer_ID]],Table1[[Customer_ID]:[Name]],2,FALSE) -> Patrick Roberts | C9: =VLOOKUP(Table6[[#This Row],[Customer_ID]],Table1[[Customer_ID]:[City]],5,FALSE) -> Jaredville | D9: =VLOOKUP(Table6[[#This Row],[Customer_ID]],Table1[],3,FALSE) -> 41 | E9: =VLOOKUP(Table6[[#This Row],[Customer_ID]],Table1[],4,FALSE) -> Female | F9: =VLOOKUP(Table6[[#This Row],[Customer_ID]],Table1[],6,FALSE) -> Missouri | G9: =VLOOKUP(Table6[[#This Row],[Customer_ID]],Table1[],8,FALSE) -> Platinum | H9: CUST1152 | I9: 45248 | J9: PROD70 | K9: =VLOOKUP($J9,'Product_Dim (2)'!$A$2:$G$101,{3,4,5,6},FALSE) -> Home | L9: =VLOOKUP($J9,'Product_Dim (2)'!$A$2:$G$101,{4,5,6},FALSE) -> Storage | M9: {=VLOOKUP($J9,'Product_Dim (2)'!$A$2:$G$101,{6},FALSE)} -> 138.05 | N9: =VLOOKUP($J9,'Product_Dim (2)'!$A$2:$G$101,7,FALSE) -> 89 | O9: STORE8 | P9: =VLOOKUP($O9,'Store_Dim (2)'!$A$2:$E$21,2,FALSE) -> Bean, Jones and Park | Q9: =VLOOKUP(Table6[[#This Row],[Store_ID]],Table4[],3,FALSE) -> West | R9: =VLOOKUP(Table6[[#This Row],[Store_ID]],Table4[],4,FALSE) -> Thompsonborough | S9: =VLOOKUP(Table6[[#This Row],[Store_ID]],Table4[],5,FALSE) -> Online | T9: 4 | U9: 342.39 | V9: 0.23 | W9: PayPal | X9: 1054.5612
A10: SALE8 | B10: =VLOOKUP(Table6[[#This Row],[Customer_ID]],Table1[[Customer_ID]:[Name]],2,FALSE) -> Dr. Suzanne Bullock | C10: =VLOOKUP(Table6[[#This Row],[Customer_ID]],Table1[[Customer_ID]:[City]],5,FALSE) -> Lake Blaketon | D10: =VLOOKUP(Table6[[#This Row],[Customer_ID]],Table1[],3,FALSE) -> 60 | E10: =VLOOKUP(Table6[[#This Row],[Customer_ID]],Table1[],4,FALSE) -> Female | F10: =VLOOKUP(Table6[[#This Row],[Customer_ID]],Table1[],6,FALSE) -> Alabama | G10: =VLOOKUP(Table6[[#This Row],[Customer_ID]],Table1[],8,FALSE) -> Platinum | H10: CUST1187 | I10: 45781 | J10: PROD99 | K10: =VLOOKUP($J10,'Product_Dim (2)'!$A$2:$G$101,{3,4,5,6},FALSE) -> Home | L10: =VLOOKUP($J10,'Product_Dim (2)'!$A$2:$G$101,{4,5,6},FALSE) -> Kitchen | M10: {=VLOOKUP($J10,'Product_Dim (2)'!$A$2:$G$101,{6},FALSE)} -> 201.41 | N10: =VLOOKUP($J10,'Product_Dim (2)'!$A$2:$G$101,7,FALSE) -> 146 | O10: STORE5 | P10: =VLOOKUP($O10,'Store_Dim (2)'!$A$2:$E$21,2,FALSE) -> Gray Ltd | Q10: =VLOOKUP(Table6[[#This Row],[Store_ID]],Table4[],3,FALSE) -> North | R10: =VLOOKUP(Table6[[#This Row],[Store_ID]],Table4[],4,FALSE) -> New Michaelchester | S10: =VLOOKUP(Table6[[#This Row],[Store_ID]],Table4[],5,FALSE) -> Outlet | T10: =X10/(U10*(1-V10)) -> 3 | U10: 448.25 | V10: 0.07 | W10: PayPal | X10: 1250.6175
A11: SALE9 | B11: =VLOOKUP(Table6[[#This Row],[Customer_ID]],Table1[[Customer_ID]:[Name]],2,FALSE) -> David Pierce | C11: =VLOOKUP(Table6[[#This Row],[Customer_ID]],Table1[[Customer_ID]:[City]],5,FALSE) -> Grayland | D11: =VLOOKUP(Table6[[#This Row],[Customer_ID]],Table1[],3,FALSE) -> 45 | E11: =VLOOKUP(Table6[[#This Row],[Customer_ID]],Table1[],4,FALSE) -> Female | F11: =VLOOKUP(Table6[[#This Row],[Customer_ID]],Table1[],6,FALSE) -> Washington | G11: =VLOOKUP(Table6[[#This Row],[Customer_ID]],Table1[],8,FALSE) -> Platinum | H11: CUST1464 | I11: 45869 | J11: PROD33 | K11: =VLOOKUP($J11,'Product_Dim (2)'!$A$2:$G$101,{3,4,5,6},FALSE) -> Home | L11: =VLOOKUP($J11,'Product_Dim (2)'!$A$2:$G$101,{4,5,6},FALSE) -> Decor | M11: {=VLOOKUP($J11,'Product_Dim (2)'!$A$2:$G$101,{6},FALSE)} -> 179.77 | N11: =VLOOKUP($J11,'Product_Dim (2)'!$A$2:$G$101,7,FALSE) -> 305 | O11: STORE0 | P11: =VLOOKUP($O11,'Store_Dim (2)'!$A$2:$E$21,2,FALSE) -> Rivera-Warner | Q11: =VLOOKUP(Table6[[#This Row],[Store_ID]],Table4[],3,FALSE) -> East | R11: =VLOOKUP(Table6[[#This Row],[Store_ID]],Table4[],4,FALSE) -> Washingtonfurt | S11: =VLOOKUP(Table6[[#This Row],[Store_ID]],Table4[],5,FALSE) -> Flagship | T11: 2 | U11: 873.17 | V11: 0.23 | W11: PayPal | X11: 1344.6818
A12: SALE10 | B12: =VLOOKUP(Table6[[#This Row],[Customer_ID]],Table1[[Customer_ID]:[Name]],2,FALSE) -> Michael Thomas | C12: =VLOOKUP(Table6[[#This Row],[Customer_ID]],Table1[[Customer_ID]:[City]],5,FALSE) -> Woodmouth | D12: =VLOOKUP(Table6[[#This Row],[Customer_ID]],Table1[],3,FALSE) -> 21 | E12: =VLOOKUP(Table6[[#This Row],[Customer_ID]],Table1[],4,FALSE) -> Female | F12: =VLOOKUP(Table6[[#This Row],[Customer_ID]],Table1[],6,FALSE) -> Nevada | G12: =VLOOKUP(Table6[[#This Row],[Customer_ID]],Table1[],8,FALSE) -> Silver | H12: CUST1065 | I12: 45335 | J12: PROD24 | K12: =VLOOKUP($J12,'Product_Dim (2)'!$A$2:$G$101,{3,4,5,6},FALSE) -> Sports | L12: =VLOOKUP($J12,'Product_Dim (2)'!$A$2:$G$101,{4,5,6},FALSE) -> Outdoor | M12: {=VLOOKUP($J12,'Product_Dim (2)'!$A$2:$G$101,{6},FALSE)} -> 166.06 | N12: =VLOOKUP($J12,'Product_Dim (2)'!$A$2:$G$101,7,FALSE) -> 340 | O12: STORE14 | P12: =VLOOKUP($O12,'Store_Dim (2)'!$A$2:$E$21,2,FALSE) -> Mcdonald Inc | Q12: =VLOOKUP(Table6[[#This Row],[Store_ID]],Table4[],3,FALSE) -> South | R12: =VLOOKUP(Table6[[#This Row],[Store_ID]],Table4[],4,FALSE) -> Christopherland | S12: =VLOOKUP(Table6[[#This Row],[Store_ID]],Table4[],5,FALSE) -> Outlet | T12: 1 | U12: 278.63 | V12: 0.07 | W12: Credit Card | X12: 259.1259
A13: SALE11 | B13: =VLOOKUP(Table6[[#This Row],[Customer_ID]],Table1[[Customer_ID]:[Name]],2,FALSE) -> Jessica Gonzalez | C13: =VLOOKUP(Table6[[#This Row],[Customer_ID]],Table1[[Customer_ID]:[City]],5,FALSE) -> South Darrenland | D13: =VLOOKUP(Table6[[#This Row],[Customer_ID]],Table1[],3,FALSE) -> 34 | E13: =VLOOKUP(Table6[[#This Row],[Customer_ID]],Table1[],4,FALSE) -> Female | F13: =VLOOKUP(Table6[[#This Row],[Customer_ID]],Table1[],6,FALSE) -> Iowa | G13: =VLOOKUP(Table6[[#This Row],[Customer_ID]],Table1[],8,FALSE) -> Bronze | H13: CUST1320 | I13: 45801 | J13: PROD39 | K13: =VLOOKUP($J13,'Product_Dim (2)'!$A$2:$G$101,{3,4,5,6},FALSE) -> Electronics | L13: =VLOOKUP($J13,'Product_Dim (2)'!$A$2:$G$101,{4,5,6},FALSE) -> Mobile | M13: {=VLOOKUP($J13,'Product_Dim (2)'!$A$2:$G$101,{6},FALSE)} -> 326.06 | N13: =VLOOKUP($J13,'Product_Dim (2)'!$A$2:$G$101,7,FALSE) -> 301 | O13: STORE1 | P13: =VLOOKUP($O13,'Store_Dim (2)'!$A$2:$E$21,2,FALSE) -> Martinez, Adkins and Johnson | Q13: =VLOOKUP(Table6[[#This Row],[Store_ID]],Table4[],3,FALSE) -> North | R13: =VLOOKUP(Table6[[#This Row],[Store_ID]],Table4[],4,FALSE) -> Danielmouth | S13: =VLOOKUP(Table6[[#This Row],[Store_ID]],Table4[],5,FALSE) -> Flagship | T13: 4 | U13: 286.92 | V13: 0.17 | W13: Credit Card | X13: 952.5744
A14: SALE12 | B14: =VLOOKUP(Table6[[#This Row],[Customer_ID]],Table1[[Customer_ID]:[Name]],2,FALSE) -> Wesley Short | C14: =VLOOKUP(Table6[[#This Row],[Customer_ID]],Table1[[Customer_ID]:[City]],5,FALSE) -> Susanstad | D14: =VLOOKUP(Table6[[#This Row],[Customer_ID]],Table1[],3,FALSE) -> 41 | E14: =VLOOKUP(Table6[[#This Row],[Customer_ID]],Table1[],4,FALSE) -> Female | F14: =VLOOKUP(Table6[[#This Row],[Customer_ID]],Table1[],6,FALSE) -> Montana | G14: =VLOOKUP(Table6[[#This Row],[Customer_ID]],Table1[],8,FALSE) -> Gold | H14: CUST1237 | I14: 45528 | J14: PROD88 | K14: =VLOOKUP($J14,'Product_Dim (2)'!$A$2:$G$101,{3,4,5,6},FALSE) -> Sports | L14: =VLOOKUP($J14,'Product_Dim (2)'!$A$2:$G$101,{4,5,6},FALSE) -> Accessories | M14: {=VLOOKUP($J14,'Product_Dim (2)'!$A$2:$G$101,{6},FALSE)} -> 131.24 | N14: =VLOOKUP($J14,'Product_Dim (2)'!$A$2:$G$101,7,FALSE) -> 232 | O14: STORE4 | P14: =VLOOKUP($O14,'Store_Dim (2)'!$A$2:$E$21,2,FALSE) -> Alexander Group | Q14: =VLOOKUP(Table6[[#This Row],[Store_ID]],Table4[],3,FALSE) -> South | R14: =VLOOKUP(Table6[[#This Row],[Store_ID]],Table4[],4,FALSE) -> Port Sharon | S14: =VLOOKUP(Table6[[#This Row],[Store_ID]],Table4[],5,FALSE) -> Online | T14: 4 | U14: 644.58 | V14: 0.01 | W14: Credit Card | X14: 2552.5368
A15: SALE13 | B15: =VLOOKUP(Table6[[#This Row],[Customer_ID]],Table1[[Customer_ID]:[Name]],2,FALSE) -> Adam Castro | C15: =VLOOKUP(Table6[[#This Row],[Customer_ID]],Table1[[Customer_ID]:[City]],5,FALSE) -> New Donnabury | D15: =VLOOKUP(Table6[[#This Row],[Customer_ID]],Table1[],3,FALSE) -> 51 | E15: =VLOOKUP(Table6[[#This Row],[Customer_ID]],Table1[],4,FALSE) -> Male | F15: =VLOOKUP(Table6[[#This Row],[Customer_ID]],Table1[],6,FALSE) -> Texas | G15: =VLOOKUP(Table6[[#This Row],[Customer_ID]],Table1[],8,FALSE) -> Silver | H15: CUST1443 | I15: 45875 | J15: PROD34 | K15: =VLOOKUP($J15,'Product_Dim (2)'!$A$2:$G$101,{3,4,5,6},FALSE) -> Electronics | L15: =VLOOKUP($J15,'Product_Dim (2)'!$A$2:$G$101,{4,5,6},FALSE) -> Computer | M15: {=VLOOKUP($J15,'Product_Dim (2)'!$A$2:$G$101,{6},FALSE)} -> 419.28 | N15: =VLOOKUP($J15,'Product_Dim (2)'!$A$2:$G$101,7,FALSE) -> 86 | O15: STORE16 | P15: =VLOOKUP($O15,'Store_Dim (2)'!$A$2:$E$21,2,FALSE) -> Frederick-Wright | Q15: =VLOOKUP(Table6[[#This Row],[Store_ID]],Table4[],3,FALSE) -> West | R15: =VLOOKUP(Table6[[#This Row],[Store_ID]],Table4[],4,FALSE) -> New Jimmymouth | S15: =VLOOKUP(Table6[[#This Row],[Store_ID]],Table4[],5,FALSE) -> Flagship | T15: 2 | U15: 316.9 | V15: 0.3 | W15: PayPal | X15: 443.66
A16: SALE14 | B16: =VLOOKUP(Table6[[#This Row],[Customer_ID]],Table1[[Customer_ID]:[Name]],2,FALSE) -> Sherry Cabrera | C16: =VLOOKUP(Table6[[#This Row],[Customer_ID]],Table1[[Customer_ID]:[City]],5,FALSE) -> Shannonview | D16: =VLOOKUP(Table6[[#This Row],[Customer_ID]],Table1[],3,FALSE) -> 55 | E16: =VLOOKUP(Table6[[#This Row],[Customer_ID]],Table1[],4,FALSE) -> Male | F16: =VLOOKUP(Table6[[#This Row],[Customer_ID]],Table1[],6,FALSE) -> Pennsylvania | G16: =VLOOKUP(Table6[[#This Row],[Customer_ID]],Table1[],8,FALSE) -> Silver | H16: CUST1348 | I16: 45829 | J16: PROD24 | K16: =VLOOKUP($J16,'Product_Dim (2)'!$A$2:$G$101,{3,4,5,6},FALSE) -> Sports | L16: =VLOOKUP($J16,'Product_Dim (2)'!$A$2:$G$101,{4,5,6},FALSE) -> Outdoor | M16: {=VLOOKUP($J16,'Product_Dim (2)'!$A$2:$G$101,{6},FALSE)} -> 166.06 | N16: =VLOOKUP($J16,'Product_Dim (2)'!$A$2:$G$101,7,FALSE) -> 340 | O16: STORE15 | P16: =VLOOKUP($O16,'Store_Dim (2)'!$A$2:$E$21,2,FALSE) -> Shelton PLC | Q16: =VLOOKUP(Table6[[#This Row],[Store_ID]],Table4[],3,FALSE) -> North | R16: =VLOOKUP(Table6[[#This Row],[Store_ID]],Table4[],4,FALSE) -> East Jenniferstad | S16: =VLOOKUP(Table6[[#This Row],[Store_ID]],Table4[],5,FALSE) -> Flagship | T16: 4 | U16: 403.47 | V16: 0.29 | W16: PayPal | X16: 1145.8548
A17: SALE15 | B17: =VLOOKUP(Table6[[#This Row],[Customer_ID]],Table1[[Customer_ID]:[Name]],2,FALSE) -> Lindsay Beasley | C17: =VLOOKUP(Table6[[#This Row],[Customer_ID]],Table1[[Customer_ID]:[City]],5,FALSE) -> Wesleyhaven | D17: =VLOOKUP(Table6[[#This Row],[Customer_ID]],Table1[],3,FALSE) -> 37 | E17: =VLOOKUP(Table6[[#This Row],[Customer_ID]],Table1[],4,FALSE) -> Female | F17: =VLOOKUP(Table6[[#This Row],[Customer_ID]],Table1[],6,FALSE) -> Idaho | G17: =VLOOKUP(Table6[[#This Row],[Customer_ID]],Table1[],8,FALSE) -> Silver | H17: CUST1435 | I17: 45636 | J17: PROD36 | K17: =VLOOKUP($J17,'Product_Dim (2)'!$A$2:$G$101,{3,4,5,6},FALSE) -> Clothing | L17: =VLOOKUP($J17,'Product_Dim (2)'!$A$2:$G$101,{4,5,6},FALSE) -> Tops | M17: {=VLOOKUP($J17,'Product_Dim (2)'!$A$2:$G$101,{6},FALSE)} -> 223.43 | N17: =VLOOKUP($J17,'Product_Dim (2)'!$A$2:$G$101,7,FALSE) -> 154 | O17: STORE9 | P17: =VLOOKUP($O17,'Store_Dim (2)'!$A$2:$E$21,2,FALSE) -> Moore, Padilla and Butler | Q17: =VLOOKUP(Table6[[#This Row],[Store_ID]],Table4[],3,FALSE) -> South | R17: =VLOOKUP(Table6[[#This Row],[Store_ID]],Table4[],4,FALSE) -> East Johnstad | S17: =VLOOKUP(Table6[[#This Row],[Store_ID]],Table4[],5,FALSE) -> Flagship | T17: =X17/(U17*(1-V17)) -> 3 | U17: 871.34 | V17: 0.04 | W17: COD | X17: 2509.4592
A18: SALE16 | B18: =VLOOKUP(Table6[[#This Row],[Customer_ID]],Table1[[Customer_ID]:[Name]],2,FALSE) -> Arthur Warren | C18: =VLOOKUP(Table6[[#This Row],[Customer_ID]],Table1[[Customer_ID]:[City]],5,FALSE) -> Ericshire | D18: =VLOOKUP(Table6[[#This Row],[Customer_ID]],Table1[],3,FALSE) -> 38 | E18: =VLOOKUP(Table6[[#This Row],[Customer_ID]],Table1[],4,FALSE) -> Male | F18: =VLOOKUP(Table6[[#This Row],[Customer_ID]],Table1[],6,FALSE) -> Nevada | G18: =VLOOKUP(Table6[[#This Row],[Customer_ID]],Table1[],8,FALSE) -> Gold | H18: CUST1276 | I18: 45913 | J18: PROD65 | K18: =VLOOKUP($J18,'Product_Dim (2)'!$A$2:$G$101,{3,4,5,6},FALSE) -> Sports | L18: =VLOOKUP($J18,'Product_Dim (2)'!$A$2:$G$101,{4,5,6},FALSE) -> Fitness | M18: {=VLOOKUP($J18,'Product_Dim (2)'!$A$2:$G$101,{6},FALSE)} -> 240.63 | N18: =VLOOKUP($J18,'Product_Dim (2)'!$A$2:$G$101,7,FALSE) -> 423 | O18: STORE19 | P18: =VLOOKUP($O18,'Store_Dim (2)'!$A$2:$E$21,2,FALSE) -> Mann-Austin | Q18: =VLOOKUP(Table6[[#This Row],[Store_ID]],Table4[],3,FALSE) -> East | R18: =VLOOKUP(Table6[[#This Row],[Store_ID]],Table4[],4,FALSE) -> Vasquezborough | S18: =VLOOKUP(Table6[[#This Row],[Store_ID]],Table4[],5,FALSE) -> Online | T18: 2 | U18: 451.98 | V18: 0.25 | W18: Credit Card | X18: 677.97
A19: SALE17 | B19: =VLOOKUP(Table6[[#This Row],[Customer_ID]],Table1[[Customer_ID]:[Name]],2,FALSE) -> Molly Gardner | C19: =VLOOKUP(Table6[[#This Row],[Customer_ID]],Table1[[Customer_ID]:[City]],5,FALSE) -> Nicoleborough | D19: =VLOOKUP(Table6[[#This Row],[Customer_ID]],Table1[],3,FALSE) -> 22 | E19: =VLOOKUP(Table6[[#This Row],[Customer_ID]],Table1[],4,FALSE) -> Female | F19: =VLOOKUP(Table6[[#This Row],[Customer_ID]],Table1[],6,FALSE) -> Arkansas | G19: =VLOOKUP(Table6[[#This Row],[Customer_ID]],Table1[],8,FALSE) -> Platinum | H19: CUST1079 | I19: 45637 | J19: PROD27 | K19: =VLOOKUP($J19,'Product_Dim (2)'!$A$2:$G$101,{3,4,5,6},FALSE) -> Home | L19: =VLOOKUP($J19,'Product_Dim (2)'!$A$2:$G$101,{4,5,6},FALSE) -> Decor | M19: {=VLOOKUP($J19,'Product_Dim (2)'!$A$2:$G$101,{6},FALSE)} -> 234.806 | N19: =VLOOKUP($J19,'Product_Dim (2)'!$A$2:$G$101,7,FALSE) -> 378 | O19: STORE4 | P19: =VLOOKUP($O19,'Store_Dim (2)'!$A$2:$E$21,2,FALSE) -> Alexander Group | Q19: =VLOOKUP(Table6[[#This Row],[Store_ID]],Table4[],3,FALSE) -> South | R19: =VLOOKUP(Table6[[#This Row],[Store_ID]],Table4[],4,FALSE) -> Port Sharon | S19: =VLOOKUP(Table6[[#This Row],[Store_ID]],Table4[],5,FALSE) -> Online | T19: 2 | U19: 502.69 | V19: 0.23 | W19: Credit Card | X19: 774.1426
A20: SALE18 | B20: =VLOOKUP(Table6[[#This Row],[Customer_ID]],Table1[[Customer_ID]:[Name]],2,FALSE) -> David Patterson | C20: =VLOOKUP(Table6[[#This Row],[Customer_ID]],Table1[[Customer_ID]:[City]],5,FALSE) -> New Amyport | D20: =VLOOKUP(Table6[[#This Row],[Customer_ID]],Table1[],3,FALSE) -> 43 | E20: =VLOOKUP(Table6[[#This Row],[Customer_ID]],Table1[],4,FALSE) -> Female | F20: =VLOOKUP(Table6[[#This Row],[Customer_ID]],Table1[],6,FALSE) -> Nevada | G20: =VLOOKUP(Table6[[#This Row],[Customer_ID]],Table1[],8,FALSE) -> Gold | H20: CUST1094 | I20: 45517 | J20: PROD39 | K20: =VLOOKUP($J20,'Product_Dim (2)'!$A$2:$G$101,{3,4,5,6},FALSE) -> Electronics | L20: =VLOOKUP($J20,'Product_Dim (2)'!$A$2:$G$101,{4,5,6},FALSE) -> Mobile | M20: {=VLOOKUP($J20,'Product_Dim (2)'!$A$2:$G$101,{6},FALSE)} -> 326.06 | N20: =VLOOKUP($J20,'Product_Dim (2)'!$A$2:$G$101,7,FALSE) -> 301 | O20: STORE4 | P20: =VLOOKUP($O20,'Store_Dim (2)'!$A$2:$E$21,2,FALSE) -> Alexander Group | Q20: =VLOOKUP(Table6[[#This Row],[Store_ID]],Table4[],3,FALSE) -> South | R20: =VLOOKUP(Table6[[#This Row],[Store_ID]],Table4[],4,FALSE) -> Port Sharon | S20: =VLOOKUP(Table6[[#This Row],[Store_ID]],Table4[],5,FALSE) -> Online | T20: 2 | U20: 559.23 | V20: 0.25 | W20: COD | X20: 838.845
A21: SALE19 | B21: =VLOOKUP(Table6[[#This Row],[Customer_ID]],Table1[[Customer_ID]:[Name]],2,FALSE) -> Maria Hill | C21: =VLOOKUP(Table6[[#This Row],[Customer_ID]],Table1[[Customer_ID]:[City]],5,FALSE) -> Zamoraborough | D21: =VLOOKUP(Table6[[#This Row],[Customer_ID]],Table1[],3,FALSE) -> 58 | E21: =VLOOKUP(Table6[[#This Row],[Customer_ID]],Table1[],4,FALSE) -> Female | F21: =VLOOKUP(Table6[[#This Row],[Customer_ID]],Table1[],6,FALSE) -> Nevada | G21: =VLOOKUP(Table6[[#This Row],[Customer_ID]],Table1[],8,FALSE) -> Platinum | H21: CUST1239 | I21: 45369 | J21: PROD60 | K21: =VLOOKUP($J21,'Product_Dim (2)'!$A$2:$G$101,{3,4,5,6},FALSE) -> Beauty | L21: =VLOOKUP($J21,'Product_Dim (2)'!$A$2:$G$101,{4,5,6},FALSE) -> Fragrance | M21: {=VLOOKUP($J21,'Product_Dim (2)'!$A$2:$G$101,{6},FALSE)} -> 482.75 | N21: =VLOOKUP($J21,'Product_Dim (2)'!$A$2:$G$101,7,FALSE) -> 444 | O21: STORE13 | P21: =VLOOKUP($O21,'Store_Dim (2)'!$A$2:$E$21,2,FALSE) -> Gardner, Humphrey and Contreras | Q21: =VLOOKUP(Table6[[#This Row],[Store_ID]],Table4[],3,FALSE) -> East | R21: =VLOOKUP(Table6[[#This Row],[Store_ID]],Table4[],4,FALSE) -> Johnsonville | S21: =VLOOKUP(Table6[[#This Row],[Store_ID]],Table4[],5,FALSE) -> Flagship | T21: 4 | U21: =X21/(T21*(1-V21)) -> 464.18 | V21: 0.04 | W21: COD | X21: 1782.4512
A22: SALE20 | B22: =VLOOKUP(Table6[[#This Row],[Customer_ID]],Table1[[Customer_ID]:[Name]],2,FALSE) -> Justin Cross | C22: =VLOOKUP(Table6[[#This Row],[Customer_ID]],Table1[[Customer_ID]:[City]],5,FALSE) -> North Anthonychester | D22: =VLOOKUP(Table6[[#This Row],[Customer_ID]],Table1[],3,FALSE) -> 62 | E22: =VLOOKUP(Table6[[#This Row],[Customer_ID]],Table1[],4,FALSE) -> Female | F22: =VLOOKUP(Table6[[#This Row],[Customer_ID]],Table1[],6,FALSE) -> Nevada | G22: =VLOOKUP(Table6[[#This Row],[Customer_ID]],Table1[],8,FALSE) -> Bronze | H22: CUST1144 | I22: 45843 | J22: PROD72 | K22: =VLOOKUP($J22,'Product_Dim (2)'!$A$2:$G$101,{3,4,5,6},FALSE) -> Sports | L22: =VLOOKUP($J22,'Product_Dim (2)'!$A$2:$G$101,{4,5,6},FALSE) -> Fitness | M22: {=VLOOKUP($J22,'Product_Dim (2)'!$A$2:$G$101,{6},FALSE)} -> 477.61 | N22: =VLOOKUP($J22,'Product_Dim (2)'!$A$2:$G$101,7,FALSE) -> 300 | O22: STORE17 | P22: =VLOOKUP($O22,'Store_Dim (2)'!$A$2:$E$21,2,FALSE) -> Holloway Ltd | Q22: =VLOOKUP(Table6[[#This Row],[Store_ID]],Table4[],3,FALSE) -> North | R22: =VLOOKUP(Table6[[#This Row],[Store_ID]],Table4[],4,FALSE) -> Bensonhaven | S22: =VLOOKUP(Table6[[#This Row],[Store_ID]],Table4[],5,FALSE) -> Flagship | T22: 3 | U22: 986.04 | V22: 0.27 | W22: COD | X22: 2159.4276
A23: SALE21 | B23: =VLOOKUP(Table6[[#This Row],[Customer_ID]],Table1[[Customer_ID]:[Name]],2,FALSE) -> Alexander Byrd | C23: =VLOOKUP(Table6[[#This Row],[Customer_ID]],Table1[[Customer_ID]:[City]],5,FALSE) -> Parkerview | D23: =VLOOKUP(Table6[[#This Row],[Customer_ID]],Table1[],3,FALSE) -> 25 | E23: =VLOOKUP(Table6[[#This Row],[Customer_ID]],Table1[],4,FALSE) -> Female | F23: =VLOOKUP(Table6[[#This Row],[Customer_ID]],Table1[],6,FALSE) -> New York | G23: =VLOOKUP(Table6[[#This Row],[Customer_ID]],Table1[],8,FALSE) -> Silver | H23: CUST1396 | I23: 45447 | J23: PROD43 | K23: =VLOOKUP($J23,'Product_Dim (2)'!$A$2:$G$101,{3,4,5,6},FALSE) -> Electronics | L23: =VLOOKUP($J23,'Product_Dim (2)'!$A$2:$G$101,{4,5,6},FALSE) -> Computer | M23: {=VLOOKUP($J23,'Product_Dim (2)'!$A$2:$G$101,{6},FALSE)} -> 253.33 | N23: =VLOOKUP($J23,'Product_Dim (2)'!$A$2:$G$101,7,FALSE) -> 266 | O23: STORE18 | P23: =VLOOKUP($O23,'Store_Dim (2)'!$A$2:$E$21,2,FALSE) -> Guerrero-Schmitt | Q23: =VLOOKUP(Table6[[#This Row],[Store_ID]],Table4[],3,FALSE) -> East | R23: =VLOOKUP(Table6[[#This Row],[Store_ID]],Table4[],4,FALSE) -> East Stevechester | S23: =VLOOKUP(Table6[[#This Row],[Store_ID]],Table4[],5,FALSE) -> Flagship | T23: 1 | U23: 589.56 | V23: 0.22 | W23: Credit Card | X23: 459.8568
A24: SALE22 | B24: =VLOOKUP(Table6[[#This Row],[Customer_ID]],Table1[[Customer_ID]:[Name]],2,FALSE) -> Elizabeth Foster | C24: =VLOOKUP(Table6[[#This Row],[Customer_ID]],Table1[[Customer_ID]:[City]],5,FALSE) -> Anthonymouth | D24: =VLOOKUP(Table6[[#This Row],[Customer_ID]],Table1[],3,FALSE) -> 33 | E24: =VLOOKUP(Table6[[#This Row],[Customer_ID]],Table1[],4,FALSE) -> Female | F24: =VLOOKUP(Table6[[#This Row],[Customer_ID]],Table1[],6,FALSE) -> Oklahoma | G24: =VLOOKUP(Table6[[#This Row],[Customer_ID]],Table1[],8,FALSE) -> Gold | H24: CUST1476 | I24: 45394 | J24: PROD69 | K24: =VLOOKUP($J24,'Product_Dim (2)'!$A$2:$G$101,{3,4,5,6},FALSE) -> Clothing | L24: =VLOOKUP($J24,'Product_Dim (2)'!$A$2:$G$101,{4,5,6},FALSE) -> Bottoms | M24: {=VLOOKUP($J24,'Product_Dim (2)'!$A$2:$G$101,{6},FALSE)} -> 218.22 | N24: =VLOOKUP($J24,'Product_Dim (2)'!$A$2:$G$101,7,FALSE) -> 224 | O24: STORE10 | P24: =VLOOKUP($O24,'Store_Dim (2)'!$A$2:$E$21,2,FALSE) -> Hill, Wagner and Ballard | Q24: =VLOOKUP(Table6[[#This Row],[Store_ID]],Table4[],3,FALSE) -> East | R24: =VLOOKUP(Table6[[#This Row],[Store_ID]],Table4[],4,FALSE) -> East Davidville | S24: =VLOOKUP(Table6[[#This Row],[Store_ID]],Table4[],5,FALSE) -> Online | T24: 3 | U24: 979.42 | V24: 0.03 | W24: PayPal | X24: 2850.1122
A25: SALE23 | B25: =VLOOKUP(Table6[[#This Row],[Customer_ID]],Table1[[Customer_ID]:[Name]],2,FALSE) -> Miranda King | C25: =VLOOKUP(Table6[[#This Row],[Customer_ID]],Table1[[Customer_ID]:[City]],5,FALSE) -> West Mathew | D25: =VLOOKUP(Table6[[#This Row],[Customer_ID]],Table1[],3,FALSE) -> 34 | E25: =VLOOKUP(Table6[[#This Row],[Customer_ID]],Table1[],4,FALSE) -> Female | F25: =VLOOKUP(Table6[[#This Row],[Customer_ID]],Table1[],6,FALSE) -> New York | G25: =VLOOKUP(Table6[[#This Row],[Customer_ID]],Table1[],8,FALSE) -> Platinum | H25: CUST1368 | I25: 45466 | J25: PROD12 | K25: =VLOOKUP($J25,'Product_Dim (2)'!$A$2:$G$101,{3,4,5,6},FALSE) -> Beauty | L25: =VLOOKUP($J25,'Product_Dim (2)'!$A$2:$G$101,{4,5,6},FALSE) -> Haircare | M25: {=VLOOKUP($J25,'Product_Dim (2)'!$A$2:$G$101,{6},FALSE)} -> 115.82 | N25: =VLOOKUP($J25,'Product_Dim (2)'!$A$2:$G$101,7,FALSE) -> 460 | O25: STORE8 | P25: =VLOOKUP($O25,'Store_Dim (2)'!$A$2:$E$21,2,FALSE) -> Bean, Jones and Park | Q25: =VLOOKUP(Table6[[#This Row],[Store_ID]],Table4[],3,FALSE) -> West | R25: =VLOOKUP(Table6[[#This Row],[Store_ID]],Table4[],4,FALSE) -> Thompsonborough | S25: =VLOOKUP(Table6[[#This Row],[Store_ID]],Table4[],5,FALSE) -> Online | T25: 1 | U25: 719.28 | V25: 0.08 | W25: Credit Card | X25: 661.7376
A26: SALE24 | B26: =VLOOKUP(Table6[[#This Row],[Customer_ID]],Table1[[Customer_ID]:[Name]],2,FALSE) -> Jennifer Pruitt | C26: =VLOOKUP(Table6[[#This Row],[Customer_ID]],Table1[[Customer_ID]:[City]],5,FALSE) -> East Justin | D26: =VLOOKUP(Table6[[#This Row],[Customer_ID]],Table1[],3,FALSE) -> 53 | E26: =VLOOKUP(Table6[[#This Row],[Customer_ID]],Table1[],4,FALSE) -> Male | F26: =VLOOKUP(Table6[[#This Row],[Customer_ID]],Table1[],6,FALSE) -> Missouri | G26: =VLOOKUP(Table6[[#This Row],[Customer_ID]],Table1[],8,FALSE) -> Silver | H26: CUST1186 | I26: 45908 | J26: PROD67 | K26: =VLOOKUP($J26,'Product_Dim (2)'!$A$2:$G$101,{3,4,5,6},FALSE) -> Electronics | L26: =VLOOKUP($J26,'Product_Dim (2)'!$A$2:$G$101,{4,5,6},FALSE) -> Accessories | M26: {=VLOOKUP($J26,'Product_Dim (2)'!$A$2:$G$101,{6},FALSE)} -> 349.17 | N26: =VLOOKUP($J26,'Product_Dim (2)'!$A$2:$G$101,7,FALSE) -> 476 | O26: STORE6 | P26: =VLOOKUP($O26,'Store_Dim (2)'!$A$2:$E$21,2,FALSE) -> Benson-Elliott | Q26: =VLOOKUP(Table6[[#This Row],[Store_ID]],Table4[],3,FALSE) -> East | R26: =VLOOKUP(Table6[[#This Row],[Store_ID]],Table4[],4,FALSE) -> Port Josephberg | S26: =VLOOKUP(Table6[[#This Row],[Store_ID]],Table4[],5,FALSE) -> Online | T26: 3 | U26: 77.6 | V26: 0.07 | W26: Credit Card | X26: 216.504
A27: SALE25 | B27: =VLOOKUP(Table6[[#This Row],[Customer_ID]],Table1[[Customer_ID]:[Name]],2,FALSE) -> Erika Padilla | C27: =VLOOKUP(Table6[[#This Row],[Customer_ID]],Table1[[Customer_ID]:[City]],5,FALSE) -> Andrewsland | D27: =VLOOKUP(Table6[[#This Row],[Customer_ID]],Table1[],3,FALSE) -> 50 | E27: =VLOOKUP(Table6[[#This Row],[Customer_ID]],Table1[],4,FALSE) -> Male | F27: =VLOOKUP(Table6[[#This Row],[Customer_ID]],Table1[],6,FALSE) -> Alabama | G27: =VLOOKUP(Table6[[#This Row],[Customer_ID]],Table1[],8,FALSE) -> Silver | H27: CUST1381 | I27: 45552 | J27: PROD5 | K27: =VLOOKUP($J27,'Product_Dim (2)'!$A$2:$G$101,{3,4,5,6},FALSE) -> Clothing | L27: =VLOOKUP($J27,'Product_Dim (2)'!$A$2:$G$101,{4,5,6},FALSE) -> Accessories | M27: {=VLOOKUP($J27,'Product_Dim (2)'!$A$2:$G$101,{6},FALSE)} -> 261 | N27: =VLOOKUP($J27,'Product_Dim (2)'!$A$2:$G$101,7,FALSE) -> 59 | O27: STORE3 | P27: =VLOOKUP($O27,'Store_Dim (2)'!$A$2:$E$21,2,FALSE) -> Johnson-Wright | Q27: =VLOOKUP(Table6[[#This Row],[Store_ID]],Table4[],3,FALSE) -> North | R27: =VLOOKUP(Table6[[#This Row],[Store_ID]],Table4[],4,FALSE) -> Hoodberg | S27: =VLOOKUP(Table6[[#This Row],[Store_ID]],Table4[],5,FALSE) -> Outlet | T27: 4 | U27: 852.71 | V27: 0.14 | W27: PayPal | X27: 2933.3224
A28: SALE26 | B28: =VLOOKUP(Table6[[#This Row],[Customer_ID]],Table1[[Customer_ID]:[Name]],2,FALSE) -> Stuart Johnson | C28: =VLOOKUP(Table6[[#This Row],[Customer_ID]],Table1[[Customer_ID]:[City]],5,FALSE) -> West Markport | D28: =VLOOKUP(Table6[[#This Row],[Customer_ID]],Table1[],3,FALSE) -> 42 | E28: =VLOOKUP(Table6[[#This Row],[Customer_ID]],Table1[],4,FALSE) -> Female | F28: =VLOOKUP(Table6[[#This Row],[Customer_ID]],Table1[],6,FALSE) -> North Dakota | G28: =VLOOKUP(Table6[[#This Row],[Customer_ID]],Table1[],8,FALSE) -> Platinum | H28: CUST1213 | I28: 45294 | J28: PROD98 | K28: =VLOOKUP($J28,'Product_Dim (2)'!$A$2:$G$101,{3,4,5,6},FALSE) -> Electronics | L28: =VLOOKUP($J28,'Product_Dim (2)'!$A$2:$G$101,{4,5,6},FALSE) -> Audio | M28: {=VLOOKUP($J28,'Product_Dim (2)'!$A$2:$G$101,{6},FALSE)} -> 431.67 | N28: =VLOOKUP($J28,'Product_Dim (2)'!$A$2:$G$101,7,FALSE) -> 73 | O28: STORE8 | P28: =VLOOKUP($O28,'Store_Dim (2)'!$A$2:$E$21,2,FALSE) -> Bean, Jones and Park | Q28: =VLOOKUP(Table6[[#This Row],[Store_ID]],Table4[],3,FALSE) -> West | R28: =VLOOKUP(Table6[[#This Row],[Store_ID]],Table4[],4,FALSE) -> Thompsonborough | S28: =VLOOKUP(Table6[[#This Row],[Store_ID]],Table4[],5,FALSE) -> Online | T28: 4 | U28: 156.16 | V28: =1-(X28/(T28*U28)) -> 0.04 | W28: Credit Card | X28: 599.6544
A29: SALE27 | B29: =VLOOKUP(Table6[[#This Row],[Customer_ID]],Table1[[Customer_ID]:[Name]],2,FALSE) -> Anna Perez | C29: =VLOOKUP(Table6[[#This Row],[Customer_ID]],Table1[[Customer_ID]:[City]],5,FALSE) -> South Jerry | D29: =VLOOKUP(Table6[[#This Row],[Customer_ID]],Table1[],3,FALSE) -> 30 | E29: =VLOOKUP(Table6[[#This Row],[Customer_ID]],Table1[],4,FALSE) -> Male | F29: =VLOOKUP(Table6[[#This Row],[Customer_ID]],Table1[],6,FALSE) -> Maine | G29: =VLOOKUP(Table6[[#This Row],[Customer_ID]],Table1[],8,FALSE) -> Platinum | H29: CUST1200 | I29: 45710 | J29: PROD77 | K29: =VLOOKUP($J29,'Product_Dim (2)'!$A$2:$G$101,{3,4,5,6},FALSE) -> Electronics | L29: =VLOOKUP($J29,'Product_Dim (2)'!$A$2:$G$101,{4,5,6},FALSE) -> Appliances | M29: {=VLOOKUP($J29,'Product_Dim (2)'!$A$2:$G$101,{6},FALSE)} -> 480.9 | N29: =VLOOKUP($J29,'Product_Dim (2)'!$A$2:$G$101,7,FALSE) -> 104 | O29: STORE8 | P29: =VLOOKUP($O29,'Store_Dim (2)'!$A$2:$E$21,2,FALSE) -> Bean, Jones and Park | Q29: =VLOOKUP(Table6[[#This Row],[Store_ID]],Table4[],3,FALSE) -> West | R29: =VLOOKUP(Table6[[#This Row],[Store_ID]],Table4[],4,FALSE) -> Thompsonborough | S29: =VLOOKUP(Table6[[#This Row],[Store_ID]],Table4[],5,FALSE) -> Online | T29: 3 | U29: 815.49 | V29: 0.17 | W29: Credit Card | X29: 2030.5701
A30: SALE28 | B30: =VLOOKUP(Table6[[#This Row],[Customer_ID]],Table1[[Customer_ID]:[Name]],2,FALSE) -> Theresa Campbell | C30: =VLOOKUP(Table6[[#This Row],[Customer_ID]],Table1[[Customer_ID]:[City]],5,FALSE) -> New Brian | D30: =VLOOKUP(Table6[[#This Row],[Customer_ID]],Table1[],3,FALSE) -> 42 | E30: =VLOOKUP(Table6[[#This Row],[Customer_ID]],Table1[],4,FALSE) -> Female | F30: =VLOOKUP(Table6[[#This Row],[Customer_ID]],Table1[],6,FALSE) -> Wisconsin | G30: =VLOOKUP(Table6[[#This Row],[Customer_ID]],Table1[],8,FALSE) -> Bronze | H30: CUST1148 | I30: 45923 | J30: PROD13 | K30: =VLOOKUP($J30,'Product_Dim (2)'!$A$2:$G$101,{3,4,5,6},FALSE) -> Electronics | L30: =VLOOKUP($J30,'Product_Dim (2)'!$A$2:$G$101,{4,5,6},FALSE) -> Accessories | M30: {=VLOOKUP($J30,'Product_Dim (2)'!$A$2:$G$101,{6},FALSE)} -> 242.23 | N30: =VLOOKUP($J30,'Product_Dim (2)'!$A$2:$G$101,7,FALSE) -> 453 | O30: STORE2 | P30: =VLOOKUP($O30,'Store_Dim (2)'!$A$2:$E$21,2,FALSE) -> Black-Horn | Q30: =VLOOKUP(Table6[[#This Row],[Store_ID]],Table4[],3,FALSE) -> South | R30: =VLOOKUP(Table6[[#This Row],[Store_ID]],Table4[],4,FALSE) -> North Nancyview | S30: =VLOOKUP(Table6[[#This Row],[Store_ID]],Table4[],5,FALSE) -> Outlet | T30: 2 | U30: 74.21 | V30: 0.11 | W30: PayPal | X30: 132.0938
A31: SALE29 | B31: =VLOOKUP(Table6[[#This Row],[Customer_ID]],Table1[[Customer_ID]:[Name]],2,FALSE) -> Sherry Cabrera | C31: =VLOOKUP(Table6[[#This Row],[Customer_ID]],Table1[[Customer_ID]:[City]],5,FALSE) -> Shannonview | D31: =VLOOKUP(Table6[[#This Row],[Customer_ID]],Table1[],3,FALSE) -> 55 | E31: =VLOOKUP(Table6[[#This Row],[Customer_ID]],Table1[],4,FALSE) -> Male | F31: =VLOOKUP(Table6[[#This Row],[Customer_ID]],Table1[],6,FALSE) -> Pennsylvania | G31: =VLOOKUP(Table6[[#This Row],[Customer_ID]],Table1[],8,FALSE) -> Silver | H31: CUST1348 | I31: 45302 | J31: PROD99 | K31: =VLOOKUP($J31,'Product_Dim (2)'!$A$2:$G$101,{3,4,5,6},FALSE) -> Home | L31: =VLOOKUP($J31,'Product_Dim (2)'!$A$2:$G$101,{4,5,6},FALSE) -> Kitchen | M31: {=VLOOKUP($J31,'Product_Dim (2)'!$A$2:$G$101,{6},FALSE)} -> 201.41 | N31: =VLOOKUP($J31,'Product_Dim (2)'!$A$2:$G$101,7,FALSE) -> 146 | O31: STORE3 | P31: =VLOOKUP($O31,'Store_Dim (2)'!$A$2:$E$21,2,FALSE) -> Johnson-Wright | Q31: =VLOOKUP(Table6[[#This Row],[Store_ID]],Table4[],3,FALSE) -> North | R31: =VLOOKUP(Table6[[#This Row],[Store_ID]],Table4[],4,FALSE) -> Hoodberg | S31: =VLOOKUP(Table6[[#This Row],[Store_ID]],Table4[],5,FALSE) -> Outlet | T31: =X31/(U31*(1-V31)) -> 4 | U31: 451.67 | V31: 0.15 | W31: Credit Card | X31: 1535.678
A32: SALE30 | B32: =VLOOKUP(Table6[[#This Row],[Customer_ID]],Table1[[Customer_ID]:[Name]],2,FALSE) -> Joshua Ryan | C32: =VLOOKUP(Table6[[#This Row],[Customer_ID]],Table1[[Customer_ID]:[City]],5,FALSE) -> New David | D32: =VLOOKUP(Table6[[#This Row],[Customer_ID]],Table1[],3,FALSE) -> 27 | E32: =VLOOKUP(Table6[[#This Row],[Customer_ID]],Table1[],4,FALSE) -> Female | F32: =VLOOKUP(Table6[[#This Row],[Customer_ID]],Table1[],6,FALSE) -> New Jersey | G32: =VLOOKUP(Table6[[#This Row],[Customer_ID]],Table1[],8,FALSE) -> Platinum | H32: CUST1028 | I32: 45217 | J32: PROD5 | K32: =VLOOKUP($J32,'Product_Dim (2)'!$A$2:$G$101,{3,4,5,6},FALSE) -> Clothing | L32: =VLOOKUP($J32,'Product_Dim (2)'!$A$2:$G$101,{4,5,6},FALSE) -> Accessories | M32: {=VLOOKUP($J32,'Product_Dim (2)'!$A$2:$G$101,{6},FALSE)} -> 261 | N32: =VLOOKUP($J32,'Product_Dim (2)'!$A$2:$G$101,7,FALSE) -> 59 | O32: STORE19 | P32: =VLOOKUP($O32,'Store_Dim (2)'!$A$2:$E$21,2,FALSE) -> Mann-Austin | Q32: =VLOOKUP(Table6[[#This Row],[Store_ID]],Table4[],3,FALSE) -> East | R32: =VLOOKUP(Table6[[#This Row],[Store_ID]],Table4[],4,FALSE) -> Vasquezborough | S32: =VLOOKUP(Table6[[#This Row],[Store_ID]],Table4[],5,FALSE) -> Online | T32: 1 | U32: 429.38 | V32: 0.13 | W32: PayPal | X32: 373.5606
A33: SALE31 | B33: =VLOOKUP(Table6[[#This Row],[Customer_ID]],Table1[[Customer_ID]:[Name]],2,FALSE) -> Shane Brown | C33: =VLOOKUP(Table6[[#This Row],[Customer_ID]],Table1[[Customer_ID]:[City]],5,FALSE) -> East Andrea | D33: =VLOOKUP(Table6[[#This Row],[Customer_ID]],Table1[],3,FALSE) -> 23 | E33: =VLOOKUP(Table6[[#This Row],[Customer_ID]],Table1[],4,FALSE) -> Female | F33: =VLOOKUP(Table6[[#This Row],[Customer_ID]],Table1[],6,FALSE) -> Michigan | G33: =VLOOKUP(Table6[[#This Row],[Customer_ID]],Table1[],8,FALSE) -> Gold | H33: CUST1412 | I33: 45593 | J33: PROD53 | K33: =VLOOKUP($J33,'Product_Dim (2)'!$A$2:$G$101,{3,4,5,6},FALSE) -> Clothing | L33: =VLOOKUP($J33,'Product_Dim (2)'!$A$2:$G$101,{4,5,6},FALSE) -> Bottoms | M33: {=VLOOKUP($J33,'Product_Dim (2)'!$A$2:$G$101,{6},FALSE)} -> 386.56 | N33: =VLOOKUP($J33,'Product_Dim (2)'!$A$2:$G$101,7,FALSE) -> 125 | O33: STORE12 | P33: =VLOOKUP($O33,'Store_Dim (2)'!$A$2:$E$21,2,FALSE) -> Thomas, Bridges and Harris | Q33: =VLOOKUP(Table6[[#This Row],[Store_ID]],Table4[],3,FALSE) -> North | R33: =VLOOKUP(Table6[[#This Row],[Store_ID]],Table4[],4,FALSE) -> Sabrinatown | S33: =VLOOKUP(Table6[[#This Row],[Store_ID]],Table4[],5,FALSE) -> Online | T33: 2 | U33: 148.96 | V33: 0.03 | W33: COD | X33: 288.9824
A34: SALE32 | B34: =VLOOKUP(Table6[[#This Row],[Customer_ID]],Table1[[Customer_ID]:[Name]],2,FALSE) -> Jennifer Johnson | C34: =VLOOKUP(Table6[[#This Row],[Customer_ID]],Table1[[Customer_ID]:[City]],5,FALSE) -> Cheyenneborough | D34: =VLOOKUP(Table6[[#This Row],[Customer_ID]],Table1[],3,FALSE) -> 54 | E34: =VLOOKUP(Table6[[#This Row],[Customer_ID]],Table1[],4,FALSE) -> Male | F34: =VLOOKUP(Table6[[#This Row],[Customer_ID]],Table1[],6,FALSE) -> New Hampshire | G34: =VLOOKUP(Table6[[#This Row],[Customer_ID]],Table1[],8,FALSE) -> Bronze | H34: CUST1398 | I34: 45597 | J34: PROD75 | K34: =VLOOKUP($J34,'Product_Dim (2)'!$A$2:$G$101,{3,4,5,6},FALSE) -> Clothing | L34: =VLOOKUP($J34,'Product_Dim (2)'!$A$2:$G$101,{4,5,6},FALSE) -> Footwear | M34: {=VLOOKUP($J34,'Product_Dim (2)'!$A$2:$G$101,{6},FALSE)} -> 158.14 | N34: =VLOOKUP($J34,'Product_Dim (2)'!$A$2:$G$101,7,FALSE) -> 82 | O34: STORE8 | P34: =VLOOKUP($O34,'Store_Dim (2)'!$A$2:$E$21,2,FALSE) -> Bean, Jones and Park | Q34: =VLOOKUP(Table6[[#This Row],[Store_ID]],Table4[],3,FALSE) -> West | R34: =VLOOKUP(Table6[[#This Row],[Store_ID]],Table4[],4,FALSE) -> Thompsonborough | S34: =VLOOKUP(Table6[[#This Row],[Store_ID]],Table4[],5,FALSE) -> Online | T34: 4 | U34: 313.83 | V34: 0.08 | W34: Credit Card | X34: 1154.8944
A35: SALE33 | B35: =VLOOKUP(Table6[[#This Row],[Customer_ID]],Table1[[Customer_ID]:[Name]],2,FALSE) -> April Phillips | C35: =VLOOKUP(Table6[[#This Row],[Customer_ID]],Table1[[Customer_ID]:[City]],5,FALSE) -> Lake Carolyn | D35: =VLOOKUP(Table6[[#This Row],[Customer_ID]],Table1[],3,FALSE) -> 62 | E35: =VLOOKUP(Table6[[#This Row],[Customer_ID]],Table1[],4,FALSE) -> Female | F35: =VLOOKUP(Table6[[#This Row],[Customer_ID]],Table1[],6,FALSE) -> Hawaii | G35: =VLOOKUP(Table6[[#This Row],[Customer_ID]],Table1[],8,FALSE) -> Platinum | H35: CUST1453 | I35: 45620 | J35: PROD12 | K35: =VLOOKUP($J35,'Product_Dim (2)'!$A$2:$G$101,{3,4,5,6},FALSE) -> Beauty | L35: =VLOOKUP($J35,'Product_Dim (2)'!$A$2:$G$101,{4,5,6},FALSE) -> Haircare | M35: {=VLOOKUP($J35,'Product_Dim (2)'!$A$2:$G$101,{6},FALSE)} -> 115.82 | N35: =VLOOKUP($J35,'Product_Dim (2)'!$A$2:$G$101,7,FALSE) -> 460 | O35: STORE6 | P35: =VLOOKUP($O35,'Store_Dim (2)'!$A$2:$E$21,2,FALSE) -> Benson-Elliott | Q35: =VLOOKUP(Table6[[#This Row],[Store_ID]],Table4[],3,FALSE) -> East | R35: =VLOOKUP(Table6[[#This Row],[Store_ID]],Table4[],4,FALSE) -> Port Josephberg | S35: =VLOOKUP(Table6[[#This Row],[Store_ID]],Table4[],5,FALSE) -> Online | T35: 2 | U35: 717.31 | V35: 0.15 | W35: Credit Card | X35: 1219.427
A36: SALE34 | B36: =VLOOKUP(Table6[[#This Row],[Customer_ID]],Table1[[Customer_ID]:[Name]],2,FALSE) -> Evelyn Brown | C36: =VLOOKUP(Table6[[#This Row],[Customer_ID]],Table1[[Customer_ID]:[City]],5,FALSE) -> West Victoriaborough | D36: =VLOOKUP(Table6[[#This Row],[Customer_ID]],Table1[],3,FALSE) -> 39 | E36: =VLOOKUP(Table6[[#This Row],[Customer_ID]],Table1[],4,FALSE) -> Male | F36: =VLOOKUP(Table6[[#This Row],[Customer_ID]],Table1[],6,FALSE) -> New Mexico | G36: =VLOOKUP(Table6[[#This Row],[Customer_ID]],Table1[],8,FALSE) -> Gold | H36: CUST1344 | I36: 45215 | J36: PROD79 | K36: =VLOOKUP($J36,'Product_Dim (2)'!$A$2:$G$101,{3,4,5,6},FALSE) -> Home | L36: =VLOOKUP($J36,'Product_Dim (2)'!$A$2:$G$101,{4,5,6},FALSE) -> Lighting | M36: {=VLOOKUP($J36,'Product_Dim (2)'!$A$2:$G$101,{6},FALSE)} -> 228.53 | N36: =VLOOKUP($J36,'Product_Dim (2)'!$A$2:$G$101,7,FALSE) -> 469 | O36: STORE1 | P36: =VLOOKUP($O36,'Store_Dim (2)'!$A$2:$E$21,2,FALSE) -> Martinez, Adkins and Johnson | Q36: =VLOOKUP(Table6[[#This Row],[Store_ID]],Table4[],3,FALSE) -> North | R36: =VLOOKUP(Table6[[#This Row],[Store_ID]],Table4[],4,FALSE) -> Danielmouth | S36: =VLOOKUP(Table6[[#This Row],[Store_ID]],Table4[],5,FALSE) -> Flagship | T36: =X36/(U36*(1-V36)) -> 3 | U36: 873.22 | V36: 0.18 | W36: Credit Card | X36: 2148.1212
A37: SALE35 | B37: =VLOOKUP(Table6[[#This Row],[Customer_ID]],Table1[[Customer_ID]:[Name]],2,FALSE) -> Julia Jackson | C37: =VLOOKUP(Table6[[#This Row],[Customer_ID]],Table1[[Customer_ID]:[City]],5,FALSE) -> Edwardland | D37: =VLOOKUP(Table6[[#This Row],[Customer_ID]],Table1[],3,FALSE) -> 46 | E37: =VLOOKUP(Table6[[#This Row],[Customer_ID]],Table1[],4,FALSE) -> Male | F37: =VLOOKUP(Table6[[#This Row],[Customer_ID]],Table1[],6,FALSE) -> California | G37: =VLOOKUP(Table6[[#This Row],[Customer_ID]],Table1[],8,FALSE) -> Platinum | H37: CUST1218 | I37: 45878 | J37: PROD16 | K37: =VLOOKUP($J37,'Product_Dim (2)'!$A$2:$G$101,{3,4,5,6},FALSE) -> Beauty | L37: =VLOOKUP($J37,'Product_Dim (2)'!$A$2:$G$101,{4,5,6},FALSE) -> Grooming | M37: {=VLOOKUP($J37,'Product_Dim (2)'!$A$2:$G$101,{6},FALSE)} -> 337.42 | N37: =VLOOKUP($J37,'Product_Dim (2)'!$A$2:$G$101,7,FALSE) -> 256 | O37: STORE3 | P37: =VLOOKUP($O37,'Store_Dim (2)'!$A$2:$E$21,2,FALSE) -> Johnson-Wright | Q37: =VLOOKUP(Table6[[#This Row],[Store_ID]],Table4[],3,FALSE) -> North | R37: =VLOOKUP(Table6[[#This Row],[Store_ID]],Table4[],4,FALSE) -> Hoodberg | S37: =VLOOKUP(Table6[[#This Row],[Store_ID]],Table4[],5,FALSE) -> Outlet | T37: 4 | U37: 109.36 | V37: 0.19 | W37: COD | X37: 354.3264
A38: SALE36 | B38: =VLOOKUP(Table6[[#This Row],[Customer_ID]],Table1[[Customer_ID]:[Name]],2,FALSE) -> Tammy Miller Md | C38: =VLOOKUP(Table6[[#This Row],[Customer_ID]],Table1[[Customer_ID]:[City]],5,FALSE) -> Austinfurt | D38: =VLOOKUP(Table6[[#This Row],[Customer_ID]],Table1[],3,FALSE) -> 19 | E38: =VLOOKUP(Table6[[#This Row],[Customer_ID]],Table1[],4,FALSE) -> Female | F38: =VLOOKUP(Table6[[#This Row],[Customer_ID]],Table1[],6,FALSE) -> Mississippi | G38: =VLOOKUP(Table6[[#This Row],[Customer_ID]],Table1[],8,FALSE) -> Gold | H38: CUST1086 | I38: 45635 | J38: PROD5 | K38: =VLOOKUP($J38,'Product_Dim (2)'!$A$2:$G$101,{3,4,5,6},FALSE) -> Clothing | L38: =VLOOKUP($J38,'Product_Dim (2)'!$A$2:$G$101,{4,5,6},FALSE) -> Accessories | M38: {=VLOOKUP($J38,'Product_Dim (2)'!$A$2:$G$101,{6},FALSE)} -> 261 | N38: =VLOOKUP($J38,'Product_Dim (2)'!$A$2:$G$101,7,FALSE) -> 59 | O38: STORE7 | P38: =VLOOKUP($O38,'Store_Dim (2)'!$A$2:$E$21,2,FALSE) -> Martinez-Mullins | Q38: =VLOOKUP(Table6[[#This Row],[Store_ID]],Table4[],3,FALSE) -> South | R38: =VLOOKUP(Table6[[#This Row],[Store_ID]],Table4[],4,FALSE) -> Williamsfurt | S38: =VLOOKUP(Table6[[#This Row],[Store_ID]],Table4[],5,FALSE) -> Online | T38: 3 | U38: 559.52 | V38: 0.16 | W38: PayPal | X38: 1409.9904
A39: SALE37 | B39: =VLOOKUP(Table6[[#This Row],[Customer_ID]],Table1[[Customer_ID]:[Name]],2,FALSE) -> Darrell Miller | C39: =VLOOKUP(Table6[[#This Row],[Customer_ID]],Table1[[Customer_ID]:[City]],5,FALSE) -> Port Carol | D39: =VLOOKUP(Table6[[#This Row],[Customer_ID]],Table1[],3,FALSE) -> 59 | E39: =VLOOKUP(Table6[[#This Row],[Customer_ID]],Table1[],4,FALSE) -> Female | F39: =VLOOKUP(Table6[[#This Row],[Customer_ID]],Table1[],6,FALSE) -> Florida | G39: =VLOOKUP(Table6[[#This Row],[Customer_ID]],Table1[],8,FALSE) -> Platinum | H39: CUST1492 | I39: 45329 | J39: PROD10 | K39: =VLOOKUP($J39,'Product_Dim (2)'!$A$2:$G$101,{3,4,5,6},FALSE) -> Home | L39: =VLOOKUP($J39,'Product_Dim (2)'!$A$2:$G$101,{4,5,6},FALSE) -> Kitchen | M39: {=VLOOKUP($J39,'Product_Dim (2)'!$A$2:$G$101,{6},FALSE)} -> 298.86 | N39: =VLOOKUP($J39,'Product_Dim (2)'!$A$2:$G$101,7,FALSE) -> 308 | O39: STORE17 | P39: =VLOOKUP($O39,'Store_Dim (2)'!$A$2:$E$21,2,FALSE) -> Holloway Ltd | Q39: =VLOOKUP(Table6[[#This Row],[Store_ID]],Table4[],3,FALSE) -> North | R39: =VLOOKUP(Table6[[#This Row],[Store_ID]],Table4[],4,FALSE) -> Bensonhaven | S39: =VLOOKUP(Table6[[#This Row],[Store_ID]],Table4[],5,FALSE) -> Flagship | T39: 3 | U39: 121.76 | V39: 0.27 | W39: PayPal | X39: 266.6544
A40: SALE38 | B40: =VLOOKUP(Table6[[#This Row],[Customer_ID]],Table1[[Customer_ID]:[Name]],2,FALSE) -> Daniel Austin | C40: =VLOOKUP(Table6[[#This Row],[Customer_ID]],Table1[[Customer_ID]:[City]],5,FALSE) -> Lake Howardberg | D40: =VLOOKUP(Table6[[#This Row],[Customer_ID]],Table1[],3,FALSE) -> 29 | E40: =VLOOKUP(Table6[[#This Row],[Customer_ID]],Table1[],4,FALSE) -> Male | F40: =VLOOKUP(Table6[[#This Row],[Customer_ID]],Table1[],6,FALSE) -> Kentucky | G40: =VLOOKUP(Table6[[#This Row],[Customer_ID]],Table1[],8,FALSE) -> Gold | H40: CUST1189 | I40: 45378 | J40: PROD33 | K40: =VLOOKUP($J40,'Product_Dim (2)'!$A$2:$G$101,{3,4,5,6},FALSE) -> Home | L40: =VLOOKUP($J40,'Product_Dim (2)'!$A$2:$G$101,{4,5,6},FALSE) -> Decor | M40: {=VLOOKUP($J40,'Product_Dim (2)'!$A$2:$G$101,{6},FALSE)} -> 179.77 | N40: =VLOOKUP($J40,'Product_Dim (2)'!$A$2:$G$101,7,FALSE) -> 305 | O40: STORE13 | P40: =VLOOKUP($O40,'Store_Dim (2)'!$A$2:$E$21,2,FALSE) -> Gardner, Humphrey and Contreras | Q40: =VLOOKUP(Table6[[#This Row],[Store_ID]],Table4[],3,FALSE) -> East | R40: =VLOOKUP(Table6[[#This Row],[Store_ID]],Table4[],4,FALSE) -> Johnsonville | S40: =VLOOKUP(Table6[[#This Row],[Store_ID]],Table4[],5,FALSE) -> Flagship | T40: 4 | U40: 735.32 | V40: 0.06 | W40: COD | X40: 2764.8032
A41: SALE39 | B41: =VLOOKUP(Table6[[#This Row],[Customer_ID]],Table1[[Customer_ID]:[Name]],2,FALSE) -> John Smith | C41: =VLOOKUP(Table6[[#This Row],[Customer_ID]],Table1[[Customer_ID]:[City]],5,FALSE) -> South Andrewport | D41: =VLOOKUP(Table6[[#This Row],[Customer_ID]],Table1[],3,FALSE) -> 27 | E41: =VLOOKUP(Table6[[#This Row],[Customer_ID]],Table1[],4,FALSE) -> Male | F41: =VLOOKUP(Table6[[#This Row],[Customer_ID]],Table1[],6,FALSE) -> California | G41: =VLOOKUP(Table6[[#This Row],[Customer_ID]],Table1[],8,FALSE) -> Platinum | H41: CUST1431 | I41: 45264 | J41: PROD94 | K41: =VLOOKUP($J41,'Product_Dim (2)'!$A$2:$G$101,{3,4,5,6},FALSE) -> Beauty | L41: =VLOOKUP($J41,'Product_Dim (2)'!$A$2:$G$101,{4,5,6},FALSE) -> Skincare | M41: {=VLOOKUP($J41,'Product_Dim (2)'!$A$2:$G$101,{6},FALSE)} -> 358.47 | N41: =VLOOKUP($J41,'Product_Dim (2)'!$A$2:$G$101,7,FALSE) -> 213 | O41: STORE3 | P41: =VLOOKUP($O41,'Store_Dim (2)'!$A$2:$E$21,2,FALSE) -> Johnson-Wright | Q41: =VLOOKUP(Table6[[#This Row],[Store_ID]],Table4[],3,FALSE) -> North | R41: =VLOOKUP(Table6[[#This Row],[Store_ID]],Table4[],4,FALSE) -> Hoodberg | S41: =VLOOKUP(Table6[[#This Row],[Store_ID]],Table4[],5,FALSE) -> Outlet | T41: 2 | U41: 600.73 | V41: 0.08 | W41: Credit Card | X41: 1105.3432
A42: SALE40 | B42: =VLOOKUP(Table6[[#This Row],[Customer_ID]],Table1[[Customer_ID]:[Name]],2,FALSE) -> Tonya Burch | C42: =VLOOKUP(Table6[[#This Row],[Customer_ID]],Table1[[Customer_ID]:[City]],5,FALSE) -> Olsonhaven | D42: =VLOOKUP(Table6[[#This Row],[Customer_ID]],Table1[],3,FALSE) -> 39 | E42: =VLOOKUP(Table6[[#This Row],[Customer_ID]],Table1[],4,FALSE) -> Female | F42: =VLOOKUP(Table6[[#This Row],[Customer_ID]],Table1[],6,FALSE) -> Iowa | G42: =VLOOKUP(Table6[[#This Row],[Customer_ID]],Table1[],8,FALSE) -> Gold | H42: CUST1072 | I42: 45486 | J42: PROD26 | K42: =VLOOKUP($J42,'Product_Dim (2)'!$A$2:$G$101,{3,4,5,6},FALSE) -> Electronics | L42: =VLOOKUP($J42,'Product_Dim (2)'!$A$2:$G$101,{4,5,6},FALSE) -> Audio | M42: {=VLOOKUP($J42,'Product_Dim (2)'!$A$2:$G$101,{6},FALSE)} -> 322.41 | N42: =VLOOKUP($J42,'Product_Dim (2)'!$A$2:$G$101,7,FALSE) -> 213 | O42: STORE19 | P42: =VLOOKUP($O42,'Store_Dim (2)'!$A$2:$E$21,2,FALSE) -> Mann-Austin | Q42: =VLOOKUP(Table6[[#This Row],[Store_ID]],Table4[],3,FALSE) -> East | R42: =VLOOKUP(Table6[[#This Row],[Store_ID]],Table4[],4,FALSE) -> Vasquezborough | S42: =VLOOKUP(Table6[[#This Row],[Store_ID]],Table4[],5,FALSE) -> Online | T42: 2 | U42: 873.86 | V42: 0.07 | W42: COD | X42: 1625.3796
A43: SALE41 | B43: =VLOOKUP(Table6[[#This Row],[Customer_ID]],Table1[[Customer_ID]:[Name]],2,FALSE) -> Edward Cole | C43: =VLOOKUP(Table6[[#This Row],[Customer_ID]],Table1[[Customer_ID]:[City]],5,FALSE) -> Lake Charlotte | D43: =VLOOKUP(Table6[[#This Row],[Customer_ID]],Table1[],3,FALSE) -> 36 | E43: =VLOOKUP(Table6[[#This Row],[Customer_ID]],Table1[],4,FALSE) -> Male | F43: =VLOOKUP(Table6[[#This Row],[Customer_ID]],Table1[],6,FALSE) -> Arizona | G43: =VLOOKUP(Table6[[#This Row],[Customer_ID]],Table1[],8,FALSE) -> Gold | H43: CUST1302 | I43: 45241 | J43: PROD23 | K43: =VLOOKUP($J43,'Product_Dim (2)'!$A$2:$G$101,{3,4,5,6},FALSE) -> Clothing | L43: =VLOOKUP($J43,'Product_Dim (2)'!$A$2:$G$101,{4,5,6},FALSE) -> Tops | M43: {=VLOOKUP($J43,'Product_Dim (2)'!$A$2:$G$101,{6},FALSE)} -> 265.73267 | N43: =VLOOKUP($J43,'Product_Dim (2)'!$A$2:$G$101,7,FALSE) -> 360 | O43: STORE8 | P43: =VLOOKUP($O43,'Store_Dim (2)'!$A$2:$E$21,2,FALSE) -> Bean, Jones and Park | Q43: =VLOOKUP(Table6[[#This Row],[Store_ID]],Table4[],3,FALSE) -> West | R43: =VLOOKUP(Table6[[#This Row],[Store_ID]],Table4[],4,FALSE) -> Thompsonborough | S43: =VLOOKUP(Table6[[#This Row],[Store_ID]],Table4[],5,FALSE) -> Online | T43: 3 | U43: 342.47 | V43: 0.08 | W43: PayPal | X43: 945.2172
A44: SALE42 | B44: =VLOOKUP(Table6[[#This Row],[Customer_ID]],Table1[[Customer_ID]:[Name]],2,FALSE) -> Jennifer Woods | C44: =VLOOKUP(Table6[[#This Row],[Customer_ID]],Table1[[Customer_ID]:[City]],5,FALSE) -> West Brendamouth | D44: =VLOOKUP(Table6[[#This Row],[Customer_ID]],Table1[],3,FALSE) -> 37 | E44: =VLOOKUP(Table6[[#This Row],[Customer_ID]],Table1[],4,FALSE) -> Male | F44: =VLOOKUP(Table6[[#This Row],[Customer_ID]],Table1[],6,FALSE) -> North Carolina | G44: =VLOOKUP(Table6[[#This Row],[Customer_ID]],Table1[],8,FALSE) -> Platinum | H44: CUST1335 | I44: 45649 | J44: PROD29 | K44: =VLOOKUP($J44,'Product_Dim (2)'!$A$2:$G$101,{3,4,5,6},FALSE) -> Home | L44: =VLOOKUP($J44,'Product_Dim (2)'!$A$2:$G$101,{4,5,6},FALSE) -> Decor | M44: {=VLOOKUP($J44,'Product_Dim (2)'!$A$2:$G$101,{6},FALSE)} -> 218.48 | N44: =VLOOKUP($J44,'Product_Dim (2)'!$A$2:$G$101,7,FALSE) -> 276 | O44: STORE9 | P44: =VLOOKUP($O44,'Store_Dim (2)'!$A$2:$E$21,2,FALSE) -> Moore, Padilla and Butler | Q44: =VLOOKUP(Table6[[#This Row],[Store_ID]],Table4[],3,FALSE) -> South | R44: =VLOOKUP(Table6[[#This Row],[Store_ID]],Table4[],4,FALSE) -> East Johnstad | S44: =VLOOKUP(Table6[[#This Row],[Store_ID]],Table4[],5,FALSE) -> Flagship | T44: 2 | U44: 915.15 | V44: 0.16 | W44: PayPal | X44: 1537.452
A45: SALE43 | B45: =VLOOKUP(Table6[[#This Row],[Customer_ID]],Table1[[Customer_ID]:[Name]],2,FALSE) -> Christy Hoffman | C45: =VLOOKUP(Table6[[#This Row],[Customer_ID]],Table1[[Customer_ID]:[City]],5,FALSE) -> Garyberg | D45: =VLOOKUP(Table6[[#This Row],[Customer_ID]],Table1[],3,FALSE) -> 26 | E45: =VLOOKUP(Table6[[#This Row],[Customer_ID]],Table1[],4,FALSE) -> Female | F45: =VLOOKUP(Table6[[#This Row],[Customer_ID]],Table1[],6,FALSE) -> Indiana | G45: =VLOOKUP(Table6[[#This Row],[Customer_ID]],Table1[],8,FALSE) -> Platinum | H45: CUST1084 | I45: 45677 | J45: PROD33 | K45: =VLOOKUP($J45,'Product_Dim (2)'!$A$2:$G$101,{3,4,5,6},FALSE) -> Home | L45: =VLOOKUP($J45,'Product_Dim (2)'!$A$2:$G$101,{4,5,6},FALSE) -> Decor | M45: {=VLOOKUP($J45,'Product_Dim (2)'!$A$2:$G$101,{6},FALSE)} -> 179.77 | N45: =VLOOKUP($J45,'Product_Dim (2)'!$A$2:$G$101,7,FALSE) -> 305 | O45: STORE17 | P45: =VLOOKUP($O45,'Store_Dim (2)'!$A$2:$E$21,2,FALSE) -> Holloway Ltd | Q45: =VLOOKUP(Table6[[#This Row],[Store_ID]],Table4[],3,FALSE) -> North | R45: =VLOOKUP(Table6[[#This Row],[Store_ID]],Table4[],4,FALSE) -> Bensonhaven | S45: =VLOOKUP(Table6[[#This Row],[Store_ID]],Table4[],5,FALSE) -> Flagship | T45: =X45/(U45*(1-V45)) -> 3 | U45: 863.11 | V45: 0.28 | W45: PayPal | X45: 1864.3176
A46: SALE44 | B46: =VLOOKUP(Table6[[#This Row],[Customer_ID]],Table1[[Customer_ID]:[Name]],2,FALSE) -> Sarah Brady | C46: =VLOOKUP(Table6[[#This Row],[Customer_ID]],Table1[[Customer_ID]:[City]],5,FALSE) -> Johnsonland | D46: =VLOOKUP(Table6[[#This Row],[Customer_ID]],Table1[],3,FALSE) -> 47 | E46: =VLOOKUP(Table6[[#This Row],[Customer_ID]],Table1[],4,FALSE) -> Male | F46: =VLOOKUP(Table6[[#This Row],[Customer_ID]],Table1[],6,FALSE) -> Iowa | G46: =VLOOKUP(Table6[[#This Row],[Customer_ID]],Table1[],8,FALSE) -> Platinum | H46: CUST1203 | I46: 45538 | J46: PROD43 | K46: =VLOOKUP($J46,'Product_Dim (2)'!$A$2:$G$101,{3,4,5,6},FALSE) -> Electronics | L46: =VLOOKUP($J46,'Product_Dim (2)'!$A$2:$G$101,{4,5,6},FALSE) -> Computer | M46: {=VLOOKUP($J46,'Product_Dim (2)'!$A$2:$G$101,{6},FALSE)} -> 253.33 | N46: =VLOOKUP($J46,'Product_Dim (2)'!$A$2:$G$101,7,FALSE) -> 266 | O46: STORE12 | P46: =VLOOKUP($O46,'Store_Dim (2)'!$A$2:$E$21,2,FALSE) -> Thomas, Bridges and Harris | Q46: =VLOOKUP(Table6[[#This Row],[Store_ID]],Table4[],3,FALSE) -> North | R46: =VLOOKUP(Table6[[#This Row],[Store_ID]],Table4[],4,FALSE) -> Sabrinatown | S46: =VLOOKUP(Table6[[#This Row],[Store_ID]],Table4[],5,FALSE) -> Online | T46: 2 | U46: 209.32 | V46: 0.23 | W46: COD | X46: 322.3528
A47: SALE45 | B47: =VLOOKUP(Table6[[#This Row],[Customer_ID]],Table1[[Customer_ID]:[Name]],2,FALSE) -> Manuel Fisher | C47: =VLOOKUP(Table6[[#This Row],[Customer_ID]],Table1[[Customer_ID]:[City]],5,FALSE) -> Kanebury | D47: =VLOOKUP(Table6[[#This Row],[Customer_ID]],Table1[],3,FALSE) -> 21 | E47: =VLOOKUP(Table6[[#This Row],[Customer_ID]],Table1[],4,FALSE) -> Female | F47: =VLOOKUP(Table6[[#This Row],[Customer_ID]],Table1[],6,FALSE) -> New Hampshire | G47: =VLOOKUP(Table6[[#This Row],[Customer_ID]],Table1[],8,FALSE) -> Gold | H47: CUST1470 | I47: 45606 | J47: PROD59 | K47: =VLOOKUP($J47,'Product_Dim (2)'!$A$2:$G$101,{3,4,5,6},FALSE) -> Beauty | L47: =VLOOKUP($J47,'Product_Dim (2)'!$A$2:$G$101,{4,5,6},FALSE) -> Haircare | M47: {=VLOOKUP($J47,'Product_Dim (2)'!$A$2:$G$101,{6},FALSE)} -> 17.31 | N47: =VLOOKUP($J47,'Product_Dim (2)'!$A$2:$G$101,7,FALSE) -> 399 | O47: STORE8 | P47: =VLOOKUP($O47,'Store_Dim (2)'!$A$2:$E$21,2,FALSE) -> Bean, Jones and Park | Q47: =VLOOKUP(Table6[[#This Row],[Store_ID]],Table4[],3,FALSE) -> West | R47: =VLOOKUP(Table6[[#This Row],[Store_ID]],Table4[],4,FALSE) -> Thompsonborough | S47: =VLOOKUP(Table6[[#This Row],[Store_ID]],Table4[],5,FALSE) -> Online | T47: 4 | U47: 288.6 | V47: 0.09 | W47: PayPal | X47: 1050.504
A48: SALE46 | B48: =VLOOKUP(Table6[[#This Row],[Customer_ID]],Table1[[Customer_ID]:[Name]],2,FALSE) -> Eric Singh | C48: =VLOOKUP(Table6[[#This Row],[Customer_ID]],Table1[[Customer_ID]:[City]],5,FALSE) -> Port Lisa | D48: =VLOOKUP(Table6[[#This Row],[Customer_ID]],Table1[],3,FALSE) -> 29 | E48: =VLOOKUP(Table6[[#This Row],[Customer_ID]],Table1[],4,FALSE) -> Female | F48: =VLOOKUP(Table6[[#This Row],[Customer_ID]],Table1[],6,FALSE) -> New Mexico | G48: =VLOOKUP(Table6[[#This Row],[Customer_ID]],Table1[],8,FALSE) -> Gold | H48: CUST1070 | I48: 45570 | J48: PROD78 | K48: =VLOOKUP($J48,'Product_Dim (2)'!$A$2:$G$101,{3,4,5,6},FALSE) -> Home | L48: =VLOOKUP($J48,'Product_Dim (2)'!$A$2:$G$101,{4,5,6},FALSE) -> Decor | M48: {=VLOOKUP($J48,'Product_Dim (2)'!$A$2:$G$101,{6},FALSE)} -> 325.26 | N48: =VLOOKUP($J48,'Product_Dim (2)'!$A$2:$G$101,7,FALSE) -> 400 | O48: STORE16 | P48: =VLOOKUP($O48,'Store_Dim (2)'!$A$2:$E$21,2,FALSE) -> Frederick-Wright | Q48: =VLOOKUP(Table6[[#This Row],[Store_ID]],Table4[],3,FALSE) -> West | R48: =VLOOKUP(Table6[[#This Row],[Store_ID]],Table4[],4,FALSE) -> New Jimmymouth | S48: =VLOOKUP(Table6[[#This Row],[Store_ID]],Table4[],5,FALSE) -> Flagship | T48: 1 | U48: 418.69 | V48: 0.06 | W48: PayPal | X48: 393.5686
A49: SALE47 | B49: =VLOOKUP(Table6[[#This Row],[Customer_ID]],Table1[[Customer_ID]:[Name]],2,FALSE) -> Melissa Howard | C49: =VLOOKUP(Table6[[#This Row],[Customer_ID]],Table1[[Customer_ID]:[City]],5,FALSE) -> Maynardton | D49: =VLOOKUP(Table6[[#This Row],[Customer_ID]],Table1[],3,FALSE) -> 53 | E49: =VLOOKUP(Table6[[#This Row],[Customer_ID]],Table1[],4,FALSE) -> Female | F49: =VLOOKUP(Table6[[#This Row],[Customer_ID]],Table1[],6,FALSE) -> New Hampshire | G49: =VLOOKUP(Table6[[#This Row],[Customer_ID]],Table1[],8,FALSE) -> Gold | H49: CUST1008 | I49: 45466 | J49: PROD30 | K49: =VLOOKUP($J49,'Product_Dim (2)'!$A$2:$G$101,{3,4,5,6},FALSE) -> Home | L49: =VLOOKUP($J49,'Product_Dim (2)'!$A$2:$G$101,{4,5,6},FALSE) -> Kitchen | M49: {=VLOOKUP($J49,'Product_Dim (2)'!$A$2:$G$101,{6},FALSE)} -> 19.52 | N49: =VLOOKUP($J49,'Product_Dim (2)'!$A$2:$G$101,7,FALSE) -> 57 | O49: STORE11 | P49: =VLOOKUP($O49,'Store_Dim (2)'!$A$2:$E$21,2,FALSE) -> Aguirre-Keller | Q49: =VLOOKUP(Table6[[#This Row],[Store_ID]],Table4[],3,FALSE) -> South | R49: =VLOOKUP(Table6[[#This Row],[Store_ID]],Table4[],4,FALSE) -> Lake Michael | S49: =VLOOKUP(Table6[[#This Row],[Store_ID]],Table4[],5,FALSE) -> Online | T49: 1 | U49: 135.78 | V49: 0.14 | W49: PayPal | X49: 116.7708
A50: SALE48 | B50: =VLOOKUP(Table6[[#This Row],[Customer_ID]],Table1[[Customer_ID]:[Name]],2,FALSE) -> Sarah Brady | C50: =VLOOKUP(Table6[[#This Row],[Customer_ID]],Table1[[Customer_ID]:[City]],5,FALSE) -> Johnsonland | D50: =VLOOKUP(Table6[[#This Row],[Customer_ID]],Table1[],3,FALSE) -> 47 | E50: =VLOOKUP(Table6[[#This Row],[Customer_ID]],Table1[],4,FALSE) -> Male | F50: =VLOOKUP(Table6[[#This Row],[Customer_ID]],Table1[],6,FALSE) -> Iowa | G50: =VLOOKUP(Table6[[#This Row],[Customer_ID]],Table1[],8,FALSE) -> Platinum | H50: CUST1203 | I50: 45218 | J50: PROD44 | K50: =VLOOKUP($J50,'Product_Dim (2)'!$A$2:$G$101,{3,4,5,6},FALSE) -> Sports | L50: =VLOOKUP($J50,'Product_Dim (2)'!$A$2:$G$101,{4,5,6},FALSE) -> Fitness | M50: {=VLOOKUP($J50,'Product_Dim (2)'!$A$2:$G$101,{6},FALSE)} -> 167.12 | N50: =VLOOKUP($J50,'Product_Dim (2)'!$A$2:$G$101,7,FALSE) -> 316 | O50: STORE17 | P50: =VLOOKUP($O50,'Store_Dim (2)'!$A$2:$E$21,2,FALSE) -> Holloway Ltd | Q50: =VLOOKUP(Table6[[#This Row],[Store_ID]],Table4[],3,FALSE) -> North | R50: =VLOOKUP(Table6[[#This Row],[Store_ID]],Table4[],4,FALSE) -> Bensonhaven | S50: =VLOOKUP(Table6[[#This Row],[Store_ID]],Table4[],5,FALSE) -> Flagship | T50: 1 | U50: 517.13 | V50: 0.28 | W50: Credit Card | X50: 372.3336
A51: SALE49 | B51: =VLOOKUP(Table6[[#This Row],[Customer_ID]],Table1[[Customer_ID]:[Name]],2,FALSE) -> Dr. Tamara White Md | C51: =VLOOKUP(Table6[[#This Row],[Customer_ID]],Table1[[Customer_ID]:[City]],5,FALSE) -> New Benjamin | D51: =VLOOKUP(Table6[[#This Row],[Customer_ID]],Table1[],3,FALSE) -> 60 | E51: =VLOOKUP(Table6[[#This Row],[Customer_ID]],Table1[],4,FALSE) -> Male | F51: =VLOOKUP(Table6[[#This Row],[Customer_ID]],Table1[],6,FALSE) -> North Carolina | G51: =VLOOKUP(Table6[[#This Row],[Customer_ID]],Table1[],8,FALSE) -> Bronze | H51: CUST1420 | I51: 45607 | J51: PROD21 | K51: =VLOOKUP($J51,'Product_Dim (2)'!$A$2:$G$101,{3,4,5,6},FALSE) -> Home | L51: =VLOOKUP($J51,'Product_Dim (2)'!$A$2:$G$101,{4,5,6},FALSE) -> Storage | M51: {=VLOOKUP($J51,'Product_Dim (2)'!$A$2:$G$101,{6},FALSE)} -> 123.46 | N51: =VLOOKUP($J51,'Product_Dim (2)'!$A$2:$G$101,7,FALSE) -> 76 | O51: STORE16 | P51: =VLOOKUP($O51,'Store_Dim (2)'!$A$2:$E$21,2,FALSE) -> Frederick-Wright | Q51: =VLOOKUP(Table6[[#This Row],[Store_ID]],Table4[],3,FALSE) -> West | R51: =VLOOKUP(Table6[[#This Row],[Store_ID]],Table4[],4,FALSE) -> New Jimmymouth | S51: =VLOOKUP(Table6[[#This Row],[Store_ID]],Table4[],5,FALSE) -> Flagship | T51: 2 | U51: 384.66 | V51: 0.08 | W51: COD | X51: 707.7744
A52: SALE50 | B52: =VLOOKUP(Table6[[#This Row],[Customer_ID]],Table1[[Customer_ID]:[Name]],2,FALSE) -> Eric Singh | C52: =VLOOKUP(Table6[[#This Row],[Customer_ID]],Table1[[Customer_ID]:[City]],5,FALSE) -> Port Lisa | D52: =VLOOKUP(Table6[[#This Row],[Customer_ID]],Table1[],3,FALSE) -> 29 | E52: =VLOOKUP(Table6[[#This Row],[Customer_ID]],Table1[],4,FALSE) -> Female | F52: =VLOOKUP(Table6[[#This Row],[Customer_ID]],Table1[],6,FALSE) -> New Mexico | G52: =VLOOKUP(Table6[[#This Row],[Customer_ID]],Table1[],8,FALSE) -> Gold | H52: CUST1070 | I52: 45291 | J52: PROD52 | K52: =VLOOKUP($J52,'Product_Dim (2)'!$A$2:$G$101,{3,4,5,6},FALSE) -> Sports | L52: =VLOOKUP($J52,'Product_Dim (2)'!$A$2:$G$101,{4,5,6},FALSE) -> Team Sports | M52: {=VLOOKUP($J52,'Product_Dim (2)'!$A$2:$G$101,{6},FALSE)} -> 212.26 | N52: =VLOOKUP($J52,'Product_Dim (2)'!$A$2:$G$101,7,FALSE) -> 82 | O52: STORE9 | P52: =VLOOKUP($O52,'Store_Dim (2)'!$A$2:$E$21,2,FALSE) -> Moore, Padilla and Butler | Q52: =VLOOKUP(Table6[[#This Row],[Store_ID]],Table4[],3,FALSE) -> South | R52: =VLOOKUP(Table6[[#This Row],[Store_ID]],Table4[],4,FALSE) -> East Johnstad | S52: =VLOOKUP(Table6[[#This Row],[Store_ID]],Table4[],5,FALSE) -> Flagship | T52: 3 | U52: 83.7 | V52: 0.24 | W52: PayPal | X52: 190.836
A53: SALE51 | B53: =VLOOKUP(Table6[[#This Row],[Customer_ID]],Table1[[Customer_ID]:[Name]],2,FALSE) -> Maria Ramirez | C53: =VLOOKUP(Table6[[#This Row],[Customer_ID]],Table1[[Customer_ID]:[City]],5,FALSE) -> West Brandon | D53: =VLOOKUP(Table6[[#This Row],[Customer_ID]],Table1[],3,FALSE) -> 37 | E53: =VLOOKUP(Table6[[#This Row],[Customer_ID]],Table1[],4,FALSE) -> Male | F53: =VLOOKUP(Table6[[#This Row],[Customer_ID]],Table1[],6,FALSE) -> Montana | G53: =VLOOKUP(Table6[[#This Row],[Customer_ID]],Table1[],8,FALSE) -> Bronze | H53: CUST1142 | I53: 45689 | J53: PROD69 | K53: =VLOOKUP($J53,'Product_Dim (2)'!$A$2:$G$101,{3,4,5,6},FALSE) -> Clothing | L53: =VLOOKUP($J53,'Product_Dim (2)'!$A$2:$G$101,{4,5,6},FALSE) -> Bottoms | M53: {=VLOOKUP($J53,'Product_Dim (2)'!$A$2:$G$101,{6},FALSE)} -> 218.22 | N53: =VLOOKUP($J53,'Product_Dim (2)'!$A$2:$G$101,7,FALSE) -> 224 | O53: STORE7 | P53: =VLOOKUP($O53,'Store_Dim (2)'!$A$2:$E$21,2,FALSE) -> Martinez-Mullins | Q53: =VLOOKUP(Table6[[#This Row],[Store_ID]],Table4[],3,FALSE) -> South | R53: =VLOOKUP(Table6[[#This Row],[Store_ID]],Table4[],4,FALSE) -> Williamsfurt | S53: =VLOOKUP(Table6[[#This Row],[Store_ID]],Table4[],5,FALSE) -> Online | T53: 3 | U53: 76.57 | V53: 0.26 | W53: Credit Card | X53: 169.9854
A54: SALE52 | B54: =VLOOKUP(Table6[[#This Row],[Customer_ID]],Table1[[Customer_ID]:[Name]],2,FALSE) -> Theresa Campbell | C54: =VLOOKUP(Table6[[#This Row],[Customer_ID]],Table1[[Customer_ID]:[City]],5,FALSE) -> New Brian | D54: =VLOOKUP(Table6[[#This Row],[Customer_ID]],Table1[],3,FALSE) -> 42 | E54: =VLOOKUP(Table6[[#This Row],[Customer_ID]],Table1[],4,FALSE) -> Female | F54: =VLOOKUP(Table6[[#This Row],[Customer_ID]],Table1[],6,FALSE) -> Wisconsin | G54: =VLOOKUP(Table6[[#This Row],[Customer_ID]],Table1[],8,FALSE) -> Bronze | H54: CUST1148 | I54: 45894 | J54: PROD89 | K54: =VLOOKUP($J54,'Product_Dim (2)'!$A$2:$G$101,{3,4,5,6},FALSE) -> Beauty | L54: =VLOOKUP($J54,'Product_Dim (2)'!$A$2:$G$101,{4,5,6},FALSE) -> Makeup | M54: {=VLOOKUP($J54,'Product_Dim (2)'!$A$2:$G$101,{6},FALSE)} -> 183.04 | N54: =VLOOKUP($J54,'Product_Dim (2)'!$A$2:$G$101,7,FALSE) -> 457 | O54: STORE6 | P54: =VLOOKUP($O54,'Store_Dim (2)'!$A$2:$E$21,2,FALSE) -> Benson-Elliott | Q54: =VLOOKUP(Table6[[#This Row],[Store_ID]],Table4[],3,FALSE) -> East | R54: =VLOOKUP(Table6[[#This Row],[Store_ID]],Table4[],4,FALSE) -> Port Josephberg | S54: =VLOOKUP(Table6[[#This Row],[Store_ID]],Table4[],5,FALSE) -> Online | T54: 3 | U54: =X54/(T54*(1-V54)) -> 162.0211 | V54: 0 | W54: Credit Card | X54: 486.0633
A55: SALE53 | B55: =VLOOKUP(Table6[[#This Row],[Customer_ID]],Table1[[Customer_ID]:[Name]],2,FALSE) -> Alex Mann Ii | C55: =VLOOKUP(Table6[[#This Row],[Customer_ID]],Table1[[Customer_ID]:[City]],5,FALSE) -> South Zacharychester | D55: =VLOOKUP(Table6[[#This Row],[Customer_ID]],Table1[],3,FALSE) -> 58 | E55: =VLOOKUP(Table6[[#This Row],[Customer_ID]],Table1[],4,FALSE) -> Male | F55: =VLOOKUP(Table6[[#This Row],[Customer_ID]],Table1[],6,FALSE) -> Oklahoma | G55: =VLOOKUP(Table6[[#This Row],[Customer_ID]],Table1[],8,FALSE) -> Bronze | H55: CUST1324 | I55: 45677 | J55: PROD20 | K55: =VLOOKUP($J55,'Product_Dim (2)'!$A$2:$G$101,{3,4,5,6},FALSE) -> Sports | L55: =VLOOKUP($J55,'Product_Dim (2)'!$A$2:$G$101,{4,5,6},FALSE) -> Accessories | M55: {=VLOOKUP($J55,'Product_Dim (2)'!$A$2:$G$101,{6},FALSE)} -> 131.51 | N55: =VLOOKUP($J55,'Product_Dim (2)'!$A$2:$G$101,7,FALSE) -> 0 | O55: STORE8 | P55: =VLOOKUP($O55,'Store_Dim (2)'!$A$2:$E$21,2,FALSE) -> Bean, Jones and Park | Q55: =VLOOKUP(Table6[[#This Row],[Store_ID]],Table4[],3,FALSE) -> West | R55: =VLOOKUP(Table6[[#This Row],[Store_ID]],Table4[],4,FALSE) -> Thompsonborough | S55: =VLOOKUP(Table6[[#This Row],[Store_ID]],Table4[],5,FALSE) -> Online | T55: 1 | U55: 900.35 | V55: 0.13 | W55: COD | X55: 783.3045
A56: SALE54 | B56: =VLOOKUP(Table6[[#This Row],[Customer_ID]],Table1[[Customer_ID]:[Name]],2,FALSE) -> Amy Fowler | C56: =VLOOKUP(Table6[[#This Row],[Customer_ID]],Table1[[Customer_ID]:[City]],5,FALSE) -> West Bobbyshire | D56: =VLOOKUP(Table6[[#This Row],[Customer_ID]],Table1[],3,FALSE) -> 62 | E56: =VLOOKUP(Table6[[#This Row],[Customer_ID]],Table1[],4,FALSE) -> Female | F56: =VLOOKUP(Table6[[#This Row],[Customer_ID]],Table1[],6,FALSE) -> New York | G56: =VLOOKUP(Table6[[#This Row],[Customer_ID]],Table1[],8,FALSE) -> Platinum | H56: CUST1095 | I56: 45706 | J56: PROD40 | K56: =VLOOKUP($J56,'Product_Dim (2)'!$A$2:$G$101,{3,4,5,6},FALSE) -> Electronics | L56: =VLOOKUP($J56,'Product_Dim (2)'!$A$2:$G$101,{4,5,6},FALSE) -> Audio | M56: {=VLOOKUP($J56,'Product_Dim (2)'!$A$2:$G$101,{6},FALSE)} -> 38.52 | N56: =VLOOKUP($J56,'Product_Dim (2)'!$A$2:$G$101,7,FALSE) -> 378 | O56: STORE10 | P56: =VLOOKUP($O56,'Store_Dim (2)'!$A$2:$E$21,2,FALSE) -> Hill, Wagner and Ballard | Q56: =VLOOKUP(Table6[[#This Row],[Store_ID]],Table4[],3,FALSE) -> East | R56: =VLOOKUP(Table6[[#This Row],[Store_ID]],Table4[],4,FALSE) -> East Davidville | S56: =VLOOKUP(Table6[[#This Row],[Store_ID]],Table4[],5,FALSE) -> Online | T56: 4 | U56: 428.09 | V56: 0.07 | W56: Credit Card | X56: 1592.4948
A57: SALE55 | B57: =VLOOKUP(Table6[[#This Row],[Customer_ID]],Table1[[Customer_ID]:[Name]],2,FALSE) -> Jennifer Myers | C57: =VLOOKUP(Table6[[#This Row],[Customer_ID]],Table1[[Customer_ID]:[City]],5,FALSE) -> Marthaborough | D57: =VLOOKUP(Table6[[#This Row],[Customer_ID]],Table1[],3,FALSE) -> 46 | E57: =VLOOKUP(Table6[[#This Row],[Customer_ID]],Table1[],4,FALSE) -> Male | F57: =VLOOKUP(Table6[[#This Row],[Customer_ID]],Table1[],6,FALSE) -> Wisconsin | G57: =VLOOKUP(Table6[[#This Row],[Customer_ID]],Table1[],8,FALSE) -> Platinum | H57: CUST1416 | I57: 45589 | J57: PROD49 | K57: =VLOOKUP($J57,'Product_Dim (2)'!$A$2:$G$101,{3,4,5,6},FALSE) -> Beauty | L57: =VLOOKUP($J57,'Product_Dim (2)'!$A$2:$G$101,{4,5,6},FALSE) -> Fragrance | M57: {=VLOOKUP($J57,'Product_Dim (2)'!$A$2:$G$101,{6},FALSE)} -> 43.29 | N57: =VLOOKUP($J57,'Product_Dim (2)'!$A$2:$G$101,7,FALSE) -> 267 | O57: STORE11 | P57: =VLOOKUP($O57,'Store_Dim (2)'!$A$2:$E$21,2,FALSE) -> Aguirre-Keller | Q57: =VLOOKUP(Table6[[#This Row],[Store_ID]],Table4[],3,FALSE) -> South | R57: =VLOOKUP(Table6[[#This Row],[Store_ID]],Table4[],4,FALSE) -> Lake Michael | S57: =VLOOKUP(Table6[[#This Row],[Store_ID]],Table4[],5,FALSE) -> Online | T57: 2 | U57: 559.71 | V57: 0.3 | W57: COD | X57: 783.594
A58: SALE56 | B58: =VLOOKUP(Table6[[#This Row],[Customer_ID]],Table1[[Customer_ID]:[Name]],2,FALSE) -> Jennifer Garcia | C58: =VLOOKUP(Table6[[#This Row],[Customer_ID]],Table1[[Customer_ID]:[City]],5,FALSE) -> New Sean | D58: =VLOOKUP(Table6[[#This Row],[Customer_ID]],Table1[],3,FALSE) -> 61 | E58: =VLOOKUP(Table6[[#This Row],[Customer_ID]],Table1[],4,FALSE) -> Female | F58: =VLOOKUP(Table6[[#This Row],[Customer_ID]],Table1[],6,FALSE) -> New Mexico | G58: =VLOOKUP(Table6[[#This Row],[Customer_ID]],Table1[],8,FALSE) -> Bronze | H58: CUST1080 | I58: 45282 | J58: PROD34 | K58: =VLOOKUP($J58,'Product_Dim (2)'!$A$2:$G$101,{3,4,5,6},FALSE) -> Electronics | L58: =VLOOKUP($J58,'Product_Dim (2)'!$A$2:$G$101,{4,5,6},FALSE) -> Computer | M58: {=VLOOKUP($J58,'Product_Dim (2)'!$A$2:$G$101,{6},FALSE)} -> 419.28 | N58: =VLOOKUP($J58,'Product_Dim (2)'!$A$2:$G$101,7,FALSE) -> 86 | O58: STORE6 | P58: =VLOOKUP($O58,'Store_Dim (2)'!$A$2:$E$21,2,FALSE) -> Benson-Elliott | Q58: =VLOOKUP(Table6[[#This Row],[Store_ID]],Table4[],3,FALSE) -> East | R58: =VLOOKUP(Table6[[#This Row],[Store_ID]],Table4[],4,FALSE) -> Port Josephberg | S58: =VLOOKUP(Table6[[#This Row],[Store_ID]],Table4[],5,FALSE) -> Online | T58: 2 | U58: 833.7 | V58: 0.06 | W58: PayPal | X58: 1567.356
A59: SALE57 | B59: =VLOOKUP(Table6[[#This Row],[Customer_ID]],Table1[[Customer_ID]:[Name]],2,FALSE) -> Michael Foley | C59: =VLOOKUP(Table6[[#This Row],[Customer_ID]],Table1[[Customer_ID]:[City]],5,FALSE) -> Oneillfurt | D59: =VLOOKUP(Table6[[#This Row],[Customer_ID]],Table1[],3,FALSE) -> 63 | E59: =VLOOKUP(Table6[[#This Row],[Customer_ID]],Table1[],4,FALSE) -> Female | F59: =VLOOKUP(Table6[[#This Row],[Customer_ID]],Table1[],6,FALSE) -> Vermont | G59: =VLOOKUP(Table6[[#This Row],[Customer_ID]],Table1[],8,FALSE) -> Gold | H59: CUST1467 | I59: 45462 | J59: PROD47 | K59: =VLOOKUP($J59,'Product_Dim (2)'!$A$2:$G$101,{3,4,5,6},FALSE) -> Beauty | L59: =VLOOKUP($J59,'Product_Dim (2)'!$A$2:$G$101,{4,5,6},FALSE) -> Makeup | M59: {=VLOOKUP($J59,'Product_Dim (2)'!$A$2:$G$101,{6},FALSE)} -> 250.41615 | N59: =VLOOKUP($J59,'Product_Dim (2)'!$A$2:$G$101,7,FALSE) -> 431 | O59: STORE14 | P59: =VLOOKUP($O59,'Store_Dim (2)'!$A$2:$E$21,2,FALSE) -> Mcdonald Inc | Q59: =VLOOKUP(Table6[[#This Row],[Store_ID]],Table4[],3,FALSE) -> South | R59: =VLOOKUP(Table6[[#This Row],[Store_ID]],Table4[],4,FALSE) -> Christopherland | S59: =VLOOKUP(Table6[[#This Row],[Store_ID]],Table4[],5,FALSE) -> Outlet | T59: 2 | U59: 680.16 | V59: 0.28 | W59: Credit Card | X59: 979.4304
A60: SALE58 | B60: =VLOOKUP(Table6[[#This Row],[Customer_ID]],Table1[[Customer_ID]:[Name]],2,FALSE) -> David Ross | C60: =VLOOKUP(Table6[[#This Row],[Customer_ID]],Table1[[Customer_ID]:[City]],5,FALSE) -> South Angela | D60: =VLOOKUP(Table6[[#This Row],[Customer_ID]],Table1[],3,FALSE) -> 22 | E60: =VLOOKUP(Table6[[#This Row],[Customer_ID]],Table1[],4,FALSE) -> Female | F60: =VLOOKUP(Table6[[#This Row],[Customer_ID]],Table1[],6,FALSE) -> Arkansas | G60: =VLOOKUP(Table6[[#This Row],[Customer_ID]],Table1[],8,FALSE) -> Silver | H60: CUST1404 | I60: 45633 | J60: PROD15 | K60: =VLOOKUP($J60,'Product_Dim (2)'!$A$2:$G$101,{3,4,5,6},FALSE) -> Electronics | L60: =VLOOKUP($J60,'Product_Dim (2)'!$A$2:$G$101,{4,5,6},FALSE) -> Appliances | M60: {=VLOOKUP($J60,'Product_Dim (2)'!$A$2:$G$101,{6},FALSE)} -> 465.34 | N60: =VLOOKUP($J60,'Product_Dim (2)'!$A$2:$G$101,7,FALSE) -> 301 | O60: STORE7 | P60: =VLOOKUP($O60,'Store_Dim (2)'!$A$2:$E$21,2,FALSE) -> Martinez-Mullins | Q60: =VLOOKUP(Table6[[#This Row],[Store_ID]],Table4[],3,FALSE) -> South | R60: =VLOOKUP(Table6[[#This Row],[Store_ID]],Table4[],4,FALSE) -> Williamsfurt | S60: =VLOOKUP(Table6[[#This Row],[Store_ID]],Table4[],5,FALSE) -> Online | T60: 4 | U60: 733.42 | V60: =1-(X60/(T60*U60)) -> 0.13 | W60: PayPal | X60: 2552.3016
A61: SALE59 | B61: =VLOOKUP(Table6[[#This Row],[Customer_ID]],Table1[[Customer_ID]:[Name]],2,FALSE) -> Melinda Johnson | C61: =VLOOKUP(Table6[[#This Row],[Customer_ID]],Table1[[Customer_ID]:[City]],5,FALSE) -> Kaufmanfurt | D61: =VLOOKUP(Table6[[#This Row],[Customer_ID]],Table1[],3,FALSE) -> 51 | E61: =VLOOKUP(Table6[[#This Row],[Customer_ID]],Table1[],4,FALSE) -> Male | F61: =VLOOKUP(Table6[[#This Row],[Customer_ID]],Table1[],6,FALSE) -> Ohio | G61: =VLOOKUP(Table6[[#This Row],[Customer_ID]],Table1[],8,FALSE) -> Bronze | H61: CUST1367 | I61: 45257 | J61: PROD89 | K61: =VLOOKUP($J61,'Product_Dim (2)'!$A$2:$G$101,{3,4,5,6},FALSE) -> Beauty | L61: =VLOOKUP($J61,'Product_Dim (2)'!$A$2:$G$101,{4,5,6},FALSE) -> Makeup | M61: {=VLOOKUP($J61,'Product_Dim (2)'!$A$2:$G$101,{6},FALSE)} -> 183.04 | N61: =VLOOKUP($J61,'Product_Dim (2)'!$A$2:$G$101,7,FALSE) -> 457 | O61: STORE11 | P61: =VLOOKUP($O61,'Store_Dim (2)'!$A$2:$E$21,2,FALSE) -> Aguirre-Keller | Q61: =VLOOKUP(Table6[[#This Row],[Store_ID]],Table4[],3,FALSE) -> South | R61: =VLOOKUP(Table6[[#This Row],[Store_ID]],Table4[],4,FALSE) -> Lake Michael | S61: =VLOOKUP(Table6[[#This Row],[Store_ID]],Table4[],5,FALSE) -> Online | T61: 1 | U61: 996.33 | V61: 0.23 | W61: PayPal | X61: 767.1741
A62: SALE60 | B62: =VLOOKUP(Table6[[#This Row],[Customer_ID]],Table1[[Customer_ID]:[Name]],2,FALSE) -> Isabel Foster | C62: =VLOOKUP(Table6[[#This Row],[Customer_ID]],Table1[[Customer_ID]:[City]],5,FALSE) -> Port Joshuaville | D62: =VLOOKUP(Table6[[#This Row],[Customer_ID]],Table1[],3,FALSE) -> 36 | E62: =VLOOKUP(Table6[[#This Row],[Customer_ID]],Table1[],4,FALSE) -> Male | F62: =VLOOKUP(Table6[[#This Row],[Customer_ID]],Table1[],6,FALSE) -> New Jersey | G62: =VLOOKUP(Table6[[#This Row],[Customer_ID]],Table1[],8,FALSE) -> Gold | H62: CUST1408 | I62: 45854 | J62: PROD31 | K62: =VLOOKUP($J62,'Product_Dim (2)'!$A$2:$G$101,{3,4,5,6},FALSE) -> Sports | L62: =VLOOKUP($J62,'Product_Dim (2)'!$A$2:$G$101,{4,5,6},FALSE) -> Team Sports | M62: {=VLOOKUP($J62,'Product_Dim (2)'!$A$2:$G$101,{6},FALSE)} -> 204.39 | N62: =VLOOKUP($J62,'Product_Dim (2)'!$A$2:$G$101,7,FALSE) -> 281 | O62: STORE10 | P62: =VLOOKUP($O62,'Store_Dim (2)'!$A$2:$E$21,2,FALSE) -> Hill, Wagner and Ballard | Q62: =VLOOKUP(Table6[[#This Row],[Store_ID]],Table4[],3,FALSE) -> East | R62: =VLOOKUP(Table6[[#This Row],[Store_ID]],Table4[],4,FALSE) -> East Davidville | S62: =VLOOKUP(Table6[[#This Row],[Store_ID]],Table4[],5,FALSE) -> Online | T62: 1 | U62: 198.83 | V62: 0.09 | W62: COD | X62: 180.9353
A63: SALE61 | B63: =VLOOKUP(Table6[[#This Row],[Customer_ID]],Table1[[Customer_ID]:[Name]],2,FALSE) -> Maria Hill | C63: =VLOOKUP(Table6[[#This Row],[Customer_ID]],Table1[[Customer_ID]:[City]],5,FALSE) -> Zamoraborough | D63: =VLOOKUP(Table6[[#This Row],[Customer_ID]],Table1[],3,FALSE) -> 58 | E63: =VLOOKUP(Table6[[#This Row],[Customer_ID]],Table1[],4,FALSE) -> Female | F63: =VLOOKUP(Table6[[#This Row],[Customer_ID]],Table1[],6,FALSE) -> Nevada | G63: =VLOOKUP(Table6[[#This Row],[Customer_ID]],Table1[],8,FALSE) -> Platinum | H63: CUST1239 | I63: 45716 | J63: PROD19 | K63: =VLOOKUP($J63,'Product_Dim (2)'!$A$2:$G$101,{3,4,5,6},FALSE) -> Sports | L63: =VLOOKUP($J63,'Product_Dim (2)'!$A$2:$G$101,{4,5,6},FALSE) -> Equipment | M63: {=VLOOKUP($J63,'Product_Dim (2)'!$A$2:$G$101,{6},FALSE)} -> 21.34 | N63: =VLOOKUP($J63,'Product_Dim (2)'!$A$2:$G$101,7,FALSE) -> 65 | O63: STORE7 | P63: =VLOOKUP($O63,'Store_Dim (2)'!$A$2:$E$21,2,FALSE) -> Martinez-Mullins | Q63: =VLOOKUP(Table6[[#This Row],[Store_ID]],Table4[],3,FALSE) -> South | R63: =VLOOKUP(Table6[[#This Row],[Store_ID]],Table4[],4,FALSE) -> Williamsfurt | S63: =VLOOKUP(Table6[[#This Row],[Store_ID]],Table4[],5,FALSE) -> Online | T63: 1 | U63: 374.92 | V63: 0.18 | W63: PayPal | X63: 307.4344
A64: SALE62 | B64: =VLOOKUP(Table6[[#This Row],[Customer_ID]],Table1[[Customer_ID]:[Name]],2,FALSE) -> David Pierce | C64: =VLOOKUP(Table6[[#This Row],[Customer_ID]],Table1[[Customer_ID]:[City]],5,FALSE) -> Grayland | D64: =VLOOKUP(Table6[[#This Row],[Customer_ID]],Table1[],3,FALSE) -> 45 | E64: =VLOOKUP(Table6[[#This Row],[Customer_ID]],Table1[],4,FALSE) -> Female | F64: =VLOOKUP(Table6[[#This Row],[Customer_ID]],Table1[],6,FALSE) -> Washington | G64: =VLOOKUP(Table6[[#This Row],[Customer_ID]],Table1[],8,FALSE) -> Platinum | H64: CUST1464 | I64: 45515 | J64: PROD93 | K64: =VLOOKUP($J64,'Product_Dim (2)'!$A$2:$G$101,{3,4,5,6},FALSE) -> Electronics | L64: =VLOOKUP($J64,'Product_Dim (2)'!$A$2:$G$101,{4,5,6},FALSE) -> Computer | M64: {=VLOOKUP($J64,'Product_Dim (2)'!$A$2:$G$101,{6},FALSE)} -> 377.52 | N64: =VLOOKUP($J64,'Product_Dim (2)'!$A$2:$G$101,7,FALSE) -> 485 | O64: STORE16 | P64: =VLOOKUP($O64,'Store_Dim (2)'!$A$2:$E$21,2,FALSE) -> Frederick-Wright | Q64: =VLOOKUP(Table6[[#This Row],[Store_ID]],Table4[],3,FALSE) -> West | R64: =VLOOKUP(Table6[[#This Row],[Store_ID]],Table4[],4,FALSE) -> New Jimmymouth | S64: =VLOOKUP(Table6[[#This Row],[Store_ID]],Table4[],5,FALSE) -> Flagship | T64: 1 | U64: 468.94 | V64: 0.12 | W64: Credit Card | X64: 412.6672
A65: SALE63 | B65: =VLOOKUP(Table6[[#This Row],[Customer_ID]],Table1[[Customer_ID]:[Name]],2,FALSE) -> James Wolfe | C65: =VLOOKUP(Table6[[#This Row],[Customer_ID]],Table1[[Customer_ID]:[City]],5,FALSE) -> Benjaminton | D65: =VLOOKUP(Table6[[#This Row],[Customer_ID]],Table1[],3,FALSE) -> 62 | E65: =VLOOKUP(Table6[[#This Row],[Customer_ID]],Table1[],4,FALSE) -> Female | F65: =VLOOKUP(Table6[[#This Row],[Customer_ID]],Table1[],6,FALSE) -> Arizona | G65: =VLOOKUP(Table6[[#This Row],[Customer_ID]],Table1[],8,FALSE) -> Gold | H65: CUST1126 | I65: 45927 | J65: PROD89 | K65: =VLOOKUP($J65,'Product_Dim (2)'!$A$2:$G$101,{3,4,5,6},FALSE) -> Beauty | L65: =VLOOKUP($J65,'Product_Dim (2)'!$A$2:$G$101,{4,5,6},FALSE) -> Makeup | M65: {=VLOOKUP($J65,'Product_Dim (2)'!$A$2:$G$101,{6},FALSE)} -> 183.04 | N65: =VLOOKUP($J65,'Product_Dim (2)'!$A$2:$G$101,7,FALSE) -> 457 | O65: STORE12 | P65: =VLOOKUP($O65,'Store_Dim (2)'!$A$2:$E$21,2,FALSE) -> Thomas, Bridges and Harris | Q65: =VLOOKUP(Table6[[#This Row],[Store_ID]],Table4[],3,FALSE) -> North | R65: =VLOOKUP(Table6[[#This Row],[Store_ID]],Table4[],4,FALSE) -> Sabrinatown | S65: =VLOOKUP(Table6[[#This Row],[Store_ID]],Table4[],5,FALSE) -> Online | T65: 2 | U65: 121.37 | V65: 0.05 | W65: Credit Card | X65: 230.603
A66: SALE64 | B66: =VLOOKUP(Table6[[#This Row],[Customer_ID]],Table1[[Customer_ID]:[Name]],2,FALSE) -> Damon Perez | C66: =VLOOKUP(Table6[[#This Row],[Customer_ID]],Table1[[Customer_ID]:[City]],5,FALSE) -> Jasonton | D66: =VLOOKUP(Table6[[#This Row],[Customer_ID]],Table1[],3,FALSE) -> 21 | E66: =VLOOKUP(Table6[[#This Row],[Customer_ID]],Table1[],4,FALSE) -> Male | F66: =VLOOKUP(Table6[[#This Row],[Customer_ID]],Table1[],6,FALSE) -> Ohio | G66: =VLOOKUP(Table6[[#This Row],[Customer_ID]],Table1[],8,FALSE) -> Gold | H66: CUST1255 | I66: 45914 | J66: PROD53 | K66: =VLOOKUP($J66,'Product_Dim (2)'!$A$2:$G$101,{3,4,5,6},FALSE) -> Clothing | L66: =VLOOKUP($J66,'Product_Dim (2)'!$A$2:$G$101,{4,5,6},FALSE) -> Bottoms | M66: {=VLOOKUP($J66,'Product_Dim (2)'!$A$2:$G$101,{6},FALSE)} -> 386.56 | N66: =VLOOKUP($J66,'Product_Dim (2)'!$A$2:$G$101,7,FALSE) -> 125 | O66: STORE10 | P66: =VLOOKUP($O66,'Store_Dim (2)'!$A$2:$E$21,2,FALSE) -> Hill, Wagner and Ballard | Q66: =VLOOKUP(Table6[[#This Row],[Store_ID]],Table4[],3,FALSE) -> East | R66: =VLOOKUP(Table6[[#This Row],[Store_ID]],Table4[],4,FALSE) -> East Davidville | S66: =VLOOKUP(Table6[[#This Row],[Store_ID]],Table4[],5,FALSE) -> Online | T66: 3 | U66: 480.06 | V66: 0.01 | W66: Credit Card | X66: =T66*U66*(1-V66) -> 1425.7782
A67: SALE65 | B67: =VLOOKUP(Table6[[#This Row],[Customer_ID]],Table1[[Customer_ID]:[Name]],2,FALSE) -> Mariah Brown | C67: =VLOOKUP(Table6[[#This Row],[Customer_ID]],Table1[[Customer_ID]:[City]],5,FALSE) -> Palmerbury | D67: =VLOOKUP(Table6[[#This Row],[Customer_ID]],Table1[],3,FALSE) -> 37 | E67: =VLOOKUP(Table6[[#This Row],[Customer_ID]],Table1[],4,FALSE) -> Male | F67: =VLOOKUP(Table6[[#This Row],[Customer_ID]],Table1[],6,FALSE) -> Tennessee | G67: =VLOOKUP(Table6[[#This Row],[Customer_ID]],Table1[],8,FALSE) -> Silver | H67: CUST1162 | I67: 45290 | J67: PROD99 | K67: =VLOOKUP($J67,'Product_Dim (2)'!$A$2:$G$101,{3,4,5,6},FALSE) -> Home | L67: =VLOOKUP($J67,'Product_Dim (2)'!$A$2:$G$101,{4,5,6},FALSE) -> Kitchen | M67: {=VLOOKUP($J67,'Product_Dim (2)'!$A$2:$G$101,{6},FALSE)} -> 201.41 | N67: =VLOOKUP($J67,'Product_Dim (2)'!$A$2:$G$101,7,FALSE) -> 146 | O67: STORE17 | P67: =VLOOKUP($O67,'Store_Dim (2)'!$A$2:$E$21,2,FALSE) -> Holloway Ltd | Q67: =VLOOKUP(Table6[[#This Row],[Store_ID]],Table4[],3,FALSE) -> North | R67: =VLOOKUP(Table6[[#This Row],[Store_ID]],Table4[],4,FALSE) -> Bensonhaven | S67: =VLOOKUP(Table6[[#This Row],[Store_ID]],Table4[],5,FALSE) -> Flagship | T67: 2 | U67: 856.57 | V67: 0.24 | W67: Credit Card | X67: 1301.9864
A68: SALE66 | B68: =VLOOKUP(Table6[[#This Row],[Customer_ID]],Table1[[Customer_ID]:[Name]],2,FALSE) -> Tyrone Olson | C68: =VLOOKUP(Table6[[#This Row],[Customer_ID]],Table1[[Customer_ID]:[City]],5,FALSE) -> Emilytown | D68: =VLOOKUP(Table6[[#This Row],[Customer_ID]],Table1[],3,FALSE) -> 45 | E68: =VLOOKUP(Table6[[#This Row],[Customer_ID]],Table1[],4,FALSE) -> Female | F68: =VLOOKUP(Table6[[#This Row],[Customer_ID]],Table1[],6,FALSE) -> California | G68: =VLOOKUP(Table6[[#This Row],[Customer_ID]],Table1[],8,FALSE) -> Silver | H68: CUST1269 | I68: 45213 | J68: PROD77 | K68: =VLOOKUP($J68,'Product_Dim (2)'!$A$2:$G$101,{3,4,5,6},FALSE) -> Electronics | L68: =VLOOKUP($J68,'Product_Dim (2)'!$A$2:$G$101,{4,5,6},FALSE) -> Appliances | M68: {=VLOOKUP($J68,'Product_Dim (2)'!$A$2:$G$101,{6},FALSE)} -> 480.9 | N68: =VLOOKUP($J68,'Product_Dim (2)'!$A$2:$G$101,7,FALSE) -> 104 | O68: STORE2 | P68: =VLOOKUP($O68,'Store_Dim (2)'!$A$2:$E$21,2,FALSE) -> Black-Horn | Q68: =VLOOKUP(Table6[[#This Row],[Store_ID]],Table4[],3,FALSE) -> South | R68: =VLOOKUP(Table6[[#This Row],[Store_ID]],Table4[],4,FALSE) -> North Nancyview | S68: =VLOOKUP(Table6[[#This Row],[Store_ID]],Table4[],5,FALSE) -> Outlet | T68: 4 | U68: 814.25 | V68: 0.18 | W68: Credit Card | X68: 2670.74
A69: SALE67 | B69: =VLOOKUP(Table6[[#This Row],[Customer_ID]],Table1[[Customer_ID]:[Name]],2,FALSE) -> Sarah Smith | C69: =VLOOKUP(Table6[[#This Row],[Customer_ID]],Table1[[Customer_ID]:[City]],5,FALSE) -> East Rodney | D69: =VLOOKUP(Table6[[#This Row],[Customer_ID]],Table1[],3,FALSE) -> 48 | E69: =VLOOKUP(Table6[[#This Row],[Customer_ID]],Table1[],4,FALSE) -> Male | F69: =VLOOKUP(Table6[[#This Row],[Customer_ID]],Table1[],6,FALSE) -> Nevada | G69: =VLOOKUP(Table6[[#This Row],[Customer_ID]],Table1[],8,FALSE) -> Gold | H69: CUST1483 | I69: 45255 | J69: PROD12 | K69: =VLOOKUP($J69,'Product_Dim (2)'!$A$2:$G$101,{3,4,5,6},FALSE) -> Beauty | L69: =VLOOKUP($J69,'Product_Dim (2)'!$A$2:$G$101,{4,5,6},FALSE) -> Haircare | M69: {=VLOOKUP($J69,'Product_Dim (2)'!$A$2:$G$101,{6},FALSE)} -> 115.82 | N69: =VLOOKUP($J69,'Product_Dim (2)'!$A$2:$G$101,7,FALSE) -> 460 | O69: STORE2 | P69: =VLOOKUP($O69,'Store_Dim (2)'!$A$2:$E$21,2,FALSE) -> Black-Horn | Q69: =VLOOKUP(Table6[[#This Row],[Store_ID]],Table4[],3,FALSE) -> South | R69: =VLOOKUP(Table6[[#This Row],[Store_ID]],Table4[],4,FALSE) -> North Nancyview | S69: =VLOOKUP(Table6[[#This Row],[Store_ID]],Table4[],5,FALSE) -> Outlet | T69: 1 | U69: 989.17 | V69: 0.2 | W69: PayPal | X69: 791.336
A70: SALE68 | B70: =VLOOKUP(Table6[[#This Row],[Customer_ID]],Table1[[Customer_ID]:[Name]],2,FALSE) -> Jacqueline Anthony | C70: =VLOOKUP(Table6[[#This Row],[Customer_ID]],Table1[[Customer_ID]:[City]],5,FALSE) -> Vincentside | D70: =VLOOKUP(Table6[[#This Row],[Customer_ID]],Table1[],3,FALSE) -> 28 | E70: =VLOOKUP(Table6[[#This Row],[Customer_ID]],Table1[],4,FALSE) -> Male | F70: =VLOOKUP(Table6[[#This Row],[Customer_ID]],Table1[],6,FALSE) -> Ohio | G70: =VLOOKUP(Table6[[#This Row],[Customer_ID]],Table1[],8,FALSE) -> Bronze | H70: CUST1372 | I70: 45270 | J70: PROD72 | K70: =VLOOKUP($J70,'Product_Dim (2)'!$A$2:$G$101,{3,4,5,6},FALSE) -> Sports | L70: =VLOOKUP($J70,'Product_Dim (2)'!$A$2:$G$101,{4,5,6},FALSE) -> Fitness | M70: {=VLOOKUP($J70,'Product_Dim (2)'!$A$2:$G$101,{6},FALSE)} -> 477.61 | N70: =VLOOKUP($J70,'Product_Dim (2)'!$A$2:$G$101,7,FALSE) -> 300 | O70: STORE10 | P70: =VLOOKUP($O70,'Store_Dim (2)'!$A$2:$E$21,2,FALSE) -> Hill, Wagner and Ballard | Q70: =VLOOKUP(Table6[[#This Row],[Store_ID]],Table4[],3,FALSE) -> East | R70: =VLOOKUP(Table6[[#This Row],[Store_ID]],Table4[],4,FALSE) -> East Davidville | S70: =VLOOKUP(Table6[[#This Row],[Store_ID]],Table4[],5,FALSE) -> Online | T70: 4 | U70: 62.48 | V70: 0.18 | W70: Credit Card | X70: 204.9344
A71: SALE69 | B71: =VLOOKUP(Table6[[#This Row],[Customer_ID]],Table1[[Customer_ID]:[Name]],2,FALSE) -> Rebecca Baker | C71: =VLOOKUP(Table6[[#This Row],[Customer_ID]],Table1[[Customer_ID]:[City]],5,FALSE) -> New Katherine | D71: =VLOOKUP(Table6[[#This Row],[Customer_ID]],Table1[],3,FALSE) -> 35 | E71: =VLOOKUP(Table6[[#This Row],[Customer_ID]],Table1[],4,FALSE) -> Male | F71: =VLOOKUP(Table6[[#This Row],[Customer_ID]],Table1[],6,FALSE) -> Kansas | G71: =VLOOKUP(Table6[[#This Row],[Customer_ID]],Table1[],8,FALSE) -> Silver | H71: CUST1423 | I71: 45897 | J71: PROD13 | K71: =VLOOKUP($J71,'Product_Dim (2)'!$A$2:$G$101,{3,4,5,6},FALSE) -> Electronics | L71: =VLOOKUP($J71,'Product_Dim (2)'!$A$2:$G$101,{4,5,6},FALSE) -> Accessories | M71: {=VLOOKUP($J71,'Product_Dim (2)'!$A$2:$G$101,{6},FALSE)} -> 242.23 | N71: =VLOOKUP($J71,'Product_Dim (2)'!$A$2:$G$101,7,FALSE) -> 453 | O71: STORE16 | P71: =VLOOKUP($O71,'Store_Dim (2)'!$A$2:$E$21,2,FALSE) -> Frederick-Wright | Q71: =VLOOKUP(Table6[[#This Row],[Store_ID]],Table4[],3,FALSE) -> West | R71: =VLOOKUP(Table6[[#This Row],[Store_ID]],Table4[],4,FALSE) -> New Jimmymouth | S71: =VLOOKUP(Table6[[#This Row],[Store_ID]],Table4[],5,FALSE) -> Flagship | T71: 4 | U71: 561.24 | V71: 0.24 | W71: Credit Card | X71: 1706.1696
A72: SALE70 | B72: =VLOOKUP(Table6[[#This Row],[Customer_ID]],Table1[[Customer_ID]:[Name]],2,FALSE) -> Cheryl Copeland | C72: =VLOOKUP(Table6[[#This Row],[Customer_ID]],Table1[[Customer_ID]:[City]],5,FALSE) -> Snowmouth | D72: =VLOOKUP(Table6[[#This Row],[Customer_ID]],Table1[],3,FALSE) -> 51 | E72: =VLOOKUP(Table6[[#This Row],[Customer_ID]],Table1[],4,FALSE) -> Male | F72: =VLOOKUP(Table6[[#This Row],[Customer_ID]],Table1[],6,FALSE) -> Maryland | G72: =VLOOKUP(Table6[[#This Row],[Customer_ID]],Table1[],8,FALSE) -> Platinum | H72: CUST1058 | I72: 45849 | J72: PROD60 | K72: =VLOOKUP($J72,'Product_Dim (2)'!$A$2:$G$101,{3,4,5,6},FALSE) -> Beauty | L72: =VLOOKUP($J72,'Product_Dim (2)'!$A$2:$G$101,{4,5,6},FALSE) -> Fragrance | M72: {=VLOOKUP($J72,'Product_Dim (2)'!$A$2:$G$101,{6},FALSE)} -> 482.75 | N72: =VLOOKUP($J72,'Product_Dim (2)'!$A$2:$G$101,7,FALSE) -> 444 | O72: STORE5 | P72: =VLOOKUP($O72,'Store_Dim (2)'!$A$2:$E$21,2,FALSE) -> Gray Ltd | Q72: =VLOOKUP(Table6[[#This Row],[Store_ID]],Table4[],3,FALSE) -> North | R72: =VLOOKUP(Table6[[#This Row],[Store_ID]],Table4[],4,FALSE) -> New Michaelchester | S72: =VLOOKUP(Table6[[#This Row],[Store_ID]],Table4[],5,FALSE) -> Outlet | T72: 3 | U72: 92.24 | V72: 0.28 | W72: COD | X72: =T72*U72*(1-V72) -> 199.2384
A73: SALE71 | B73: =VLOOKUP(Table6[[#This Row],[Customer_ID]],Table1[[Customer_ID]:[Name]],2,FALSE) -> Daniel Contreras | C73: =VLOOKUP(Table6[[#This Row],[Customer_ID]],Table1[[Customer_ID]:[City]],5,FALSE) -> Robertview | D73: =VLOOKUP(Table6[[#This Row],[Customer_ID]],Table1[],3,FALSE) -> 36 | E73: =VLOOKUP(Table6[[#This Row],[Customer_ID]],Table1[],4,FALSE) -> Female | F73: =VLOOKUP(Table6[[#This Row],[Customer_ID]],Table1[],6,FALSE) -> Florida | G73: =VLOOKUP(Table6[[#This Row],[Customer_ID]],Table1[],8,FALSE) -> Platinum | H73: CUST1168 | I73: 45889 | J73: PROD72 | K73: =VLOOKUP($J73,'Product_Dim (2)'!$A$2:$G$101,{3,4,5,6},FALSE) -> Sports | L73: =VLOOKUP($J73,'Product_Dim (2)'!$A$2:$G$101,{4,5,6},FALSE) -> Fitness | M73: {=VLOOKUP($J73,'Product_Dim (2)'!$A$2:$G$101,{6},FALSE)} -> 477.61 | N73: =VLOOKUP($J73,'Product_Dim (2)'!$A$2:$G$101,7,FALSE) -> 300 | O73: STORE1 | P73: =VLOOKUP($O73,'Store_Dim (2)'!$A$2:$E$21,2,FALSE) -> Martinez, Adkins and Johnson | Q73: =VLOOKUP(Table6[[#This Row],[Store_ID]],Table4[],3,FALSE) -> North | R73: =VLOOKUP(Table6[[#This Row],[Store_ID]],Table4[],4,FALSE) -> Danielmouth | S73: =VLOOKUP(Table6[[#This Row],[Store_ID]],Table4[],5,FALSE) -> Flagship | T73: 2 | U73: 668.3 | V73: 0.07 | W73: Credit Card | X73: 1243.038
A74: SALE72 | B74: =VLOOKUP(Table6[[#This Row],[Customer_ID]],Table1[[Customer_ID]:[Name]],2,FALSE) -> Sarah Smith | C74: =VLOOKUP(Table6[[#This Row],[Customer_ID]],Table1[[Customer_ID]:[City]],5,FALSE) -> Kathleenport | D74: =VLOOKUP(Table6[[#This Row],[Customer_ID]],Table1[],3,FALSE) -> 55 | E74: =VLOOKUP(Table6[[#This Row],[Customer_ID]],Table1[],4,FALSE) -> Male | F74: =VLOOKUP(Table6[[#This Row],[Customer_ID]],Table1[],6,FALSE) -> Wyoming | G74: =VLOOKUP(Table6[[#This Row],[Customer_ID]],Table1[],8,FALSE) -> Gold | H74: CUST1409 | I74: 45533 | J74: PROD38 | K74: =VLOOKUP($J74,'Product_Dim (2)'!$A$2:$G$101,{3,4,5,6},FALSE) -> Sports | L74: =VLOOKUP($J74,'Product_Dim (2)'!$A$2:$G$101,{4,5,6},FALSE) -> Outdoor | M74: {=VLOOKUP($J74,'Product_Dim (2)'!$A$2:$G$101,{6},FALSE)} -> 135.61 | N74: =VLOOKUP($J74,'Product_Dim (2)'!$A$2:$G$101,7,FALSE) -> 394 | O74: STORE5 | P74: =VLOOKUP($O74,'Store_Dim (2)'!$A$2:$E$21,2,FALSE) -> Gray Ltd | Q74: =VLOOKUP(Table6[[#This Row],[Store_ID]],Table4[],3,FALSE) -> North | R74: =VLOOKUP(Table6[[#This Row],[Store_ID]],Table4[],4,FALSE) -> New Michaelchester | S74: =VLOOKUP(Table6[[#This Row],[Store_ID]],Table4[],5,FALSE) -> Outlet | T74: 1 | U74: 553.82 | V74: 0.09 | W74: Credit Card | X74: 503.9762
A75: SALE73 | B75: =VLOOKUP(Table6[[#This Row],[Customer_ID]],Table1[[Customer_ID]:[Name]],2,FALSE) -> Christopher Carter | C75: =VLOOKUP(Table6[[#This Row],[Customer_ID]],Table1[[Customer_ID]:[City]],5,FALSE) -> Brendastad | D75: =VLOOKUP(Table6[[#This Row],[Customer_ID]],Table1[],3,FALSE) -> 27 | E75: =VLOOKUP(Table6[[#This Row],[Customer_ID]],Table1[],4,FALSE) -> Female | F75: =VLOOKUP(Table6[[#This Row],[Customer_ID]],Table1[],6,FALSE) -> South Dakota | G75: =VLOOKUP(Table6[[#This Row],[Customer_ID]],Table1[],8,FALSE) -> Platinum | H75: CUST1037 | I75: 45626 | J75: PROD45 | K75: =VLOOKUP($J75,'Product_Dim (2)'!$A$2:$G$101,{3,4,5,6},FALSE) -> Sports | L75: =VLOOKUP($J75,'Product_Dim (2)'!$A$2:$G$101,{4,5,6},FALSE) -> Team Sports | M75: {=VLOOKUP($J75,'Product_Dim (2)'!$A$2:$G$101,{6},FALSE)} -> 318.91 | N75: =VLOOKUP($J75,'Product_Dim (2)'!$A$2:$G$101,7,FALSE) -> 114 | O75: STORE11 | P75: =VLOOKUP($O75,'Store_Dim (2)'!$A$2:$E$21,2,FALSE) -> Aguirre-Keller | Q75: =VLOOKUP(Table6[[#This Row],[Store_ID]],Table4[],3,FALSE) -> South | R75: =VLOOKUP(Table6[[#This Row],[Store_ID]],Table4[],4,FALSE) -> Lake Michael | S75: =VLOOKUP(Table6[[#This Row],[Store_ID]],Table4[],5,FALSE) -> Online | T75: 2 | U75: 556.43 | V75: 0.13 | W75: Credit Card | X75: 968.1882
A76: SALE74 | B76: =VLOOKUP(Table6[[#This Row],[Customer_ID]],Table1[[Customer_ID]:[Name]],2,FALSE) -> Samantha Robinson | C76: =VLOOKUP(Table6[[#This Row],[Customer_ID]],Table1[[Customer_ID]:[City]],5,FALSE) -> North Roy | D76: =VLOOKUP(Table6[[#This Row],[Customer_ID]],Table1[],3,FALSE) -> 23 | E76: =VLOOKUP(Table6[[#This Row],[Customer_ID]],Table1[],4,FALSE) -> Male | F76: =VLOOKUP(Table6[[#This Row],[Customer_ID]],Table1[],6,FALSE) -> Mississippi | G76: =VLOOKUP(Table6[[#This Row],[Customer_ID]],Table1[],8,FALSE) -> Bronze | H76: CUST1273 | I76: 45942 | J76: PROD20 | K76: =VLOOKUP($J76,'Product_Dim (2)'!$A$2:$G$101,{3,4,5,6},FALSE) -> Sports | L76: =VLOOKUP($J76,'Product_Dim (2)'!$A$2:$G$101,{4,5,6},FALSE) -> Accessories | M76: {=VLOOKUP($J76,'Product_Dim (2)'!$A$2:$G$101,{6},FALSE)} -> 131.51 | N76: =VLOOKUP($J76,'Product_Dim (2)'!$A$2:$G$101,7,FALSE) -> 0 | O76: STORE8 | P76: =VLOOKUP($O76,'Store_Dim (2)'!$A$2:$E$21,2,FALSE) -> Bean, Jones and Park | Q76: =VLOOKUP(Table6[[#This Row],[Store_ID]],Table4[],3,FALSE) -> West | R76: =VLOOKUP(Table6[[#This Row],[Store_ID]],Table4[],4,FALSE) -> Thompsonborough | S76: =VLOOKUP(Table6[[#This Row],[Store_ID]],Table4[],5,FALSE) -> Online | T76: 1 | U76: 184.98 | V76: 0.1 | W76: COD | X76: 166.482
A77: SALE75 | B77: =VLOOKUP(Table6[[#This Row],[Customer_ID]],Table1[[Customer_ID]:[Name]],2,FALSE) -> Rachel Myers | C77: =VLOOKUP(Table6[[#This Row],[Customer_ID]],Table1[[Customer_ID]:[City]],5,FALSE) -> Robertberg | D77: =VLOOKUP(Table6[[#This Row],[Customer_ID]],Table1[],3,FALSE) -> 52 | E77: =VLOOKUP(Table6[[#This Row],[Customer_ID]],Table1[],4,FALSE) -> Male | F77: =VLOOKUP(Table6[[#This Row],[Customer_ID]],Table1[],6,FALSE) -> North Dakota | G77: =VLOOKUP(Table6[[#This Row],[Customer_ID]],Table1[],8,FALSE) -> Silver | H77: CUST1035 | I77: 45500 | J77: PROD97 | K77: =VLOOKUP($J77,'Product_Dim (2)'!$A$2:$G$101,{3,4,5,6},FALSE) -> Sports | L77: =VLOOKUP($J77,'Product_Dim (2)'!$A$2:$G$101,{4,5,6},FALSE) -> Team Sports | M77: {=VLOOKUP($J77,'Product_Dim (2)'!$A$2:$G$101,{6},FALSE)} -> 245.98 | N77: =VLOOKUP($J77,'Product_Dim (2)'!$A$2:$G$101,7,FALSE) -> 471 | O77: STORE12 | P77: =VLOOKUP($O77,'Store_Dim (2)'!$A$2:$E$21,2,FALSE) -> Thomas, Bridges and Harris | Q77: =VLOOKUP(Table6[[#This Row],[Store_ID]],Table4[],3,FALSE) -> North | R77: =VLOOKUP(Table6[[#This Row],[Store_ID]],Table4[],4,FALSE) -> Sabrinatown | S77: =VLOOKUP(Table6[[#This Row],[Store_ID]],Table4[],5,FALSE) -> Online | T77: 4 | U77: 700.18 | V77: 0.23 | W77: Credit Card | X77: 2156.5544
A78: SALE76 | B78: =VLOOKUP(Table6[[#This Row],[Customer_ID]],Table1[[Customer_ID]:[Name]],2,FALSE) -> Michael Torres | C78: =VLOOKUP(Table6[[#This Row],[Customer_ID]],Table1[[Customer_ID]:[City]],5,FALSE) -> Gonzalezfort | D78: =VLOOKUP(Table6[[#This Row],[Customer_ID]],Table1[],3,FALSE) -> 46 | E78: =VLOOKUP(Table6[[#This Row],[Customer_ID]],Table1[],4,FALSE) -> Female | F78: =VLOOKUP(Table6[[#This Row],[Customer_ID]],Table1[],6,FALSE) -> New Jersey | G78: =VLOOKUP(Table6[[#This Row],[Customer_ID]],Table1[],8,FALSE) -> Platinum | H78: CUST1019 | I78: 45285 | J78: PROD76 | K78: =VLOOKUP($J78,'Product_Dim (2)'!$A$2:$G$101,{3,4,5,6},FALSE) -> Electronics | L78: =VLOOKUP($J78,'Product_Dim (2)'!$A$2:$G$101,{4,5,6},FALSE) -> Computer | M78: {=VLOOKUP($J78,'Product_Dim (2)'!$A$2:$G$101,{6},FALSE)} -> 392.89 | N78: =VLOOKUP($J78,'Product_Dim (2)'!$A$2:$G$101,7,FALSE) -> 320 | O78: STORE10 | P78: =VLOOKUP($O78,'Store_Dim (2)'!$A$2:$E$21,2,FALSE) -> Hill, Wagner and Ballard | Q78: =VLOOKUP(Table6[[#This Row],[Store_ID]],Table4[],3,FALSE) -> East | R78: =VLOOKUP(Table6[[#This Row],[Store_ID]],Table4[],4,FALSE) -> East Davidville | S78: =VLOOKUP(Table6[[#This Row],[Store_ID]],Table4[],5,FALSE) -> Online | T78: 2 | U78: 686.31 | V78: 0.25 | W78: Credit Card | X78: 1029.465
A79: SALE77 | B79: =VLOOKUP(Table6[[#This Row],[Customer_ID]],Table1[[Customer_ID]:[Name]],2,FALSE) -> Daniel Boyd | C79: =VLOOKUP(Table6[[#This Row],[Customer_ID]],Table1[[Customer_ID]:[City]],5,FALSE) -> West Pamelafurt | D79: =VLOOKUP(Table6[[#This Row],[Customer_ID]],Table1[],3,FALSE) -> 29 | E79: =VLOOKUP(Table6[[#This Row],[Customer_ID]],Table1[],4,FALSE) -> Female | F79: =VLOOKUP(Table6[[#This Row],[Customer_ID]],Table1[],6,FALSE) -> West Virginia | G79: =VLOOKUP(Table6[[#This Row],[Customer_ID]],Table1[],8,FALSE) -> Bronze | H79: CUST1007 | I79: 45800 | J79: PROD67 | K79: =VLOOKUP($J79,'Product_Dim (2)'!$A$2:$G$101,{3,4,5,6},FALSE) -> Electronics | L79: =VLOOKUP($J79,'Product_Dim (2)'!$A$2:$G$101,{4,5,6},FALSE) -> Accessories | M79: {=VLOOKUP($J79,'Product_Dim (2)'!$A$2:$G$101,{6},FALSE)} -> 349.17 | N79: =VLOOKUP($J79,'Product_Dim (2)'!$A$2:$G$101,7,FALSE) -> 476 | O79: STORE15 | P79: =VLOOKUP($O79,'Store_Dim (2)'!$A$2:$E$21,2,FALSE) -> Shelton PLC | Q79: =VLOOKUP(Table6[[#This Row],[Store_ID]],Table4[],3,FALSE) -> North | R79: =VLOOKUP(Table6[[#This Row],[Store_ID]],Table4[],4,FALSE) -> East Jenniferstad | S79: =VLOOKUP(Table6[[#This Row],[Store_ID]],Table4[],5,FALSE) -> Flagship | T79: 1 | U79: 687.82 | V79: 0.27 | W79: COD | X79: 502.1086
A80: SALE78 | B80: =VLOOKUP(Table6[[#This Row],[Customer_ID]],Table1[[Customer_ID]:[Name]],2,FALSE) -> Lisa Young | C80: =VLOOKUP(Table6[[#This Row],[Customer_ID]],Table1[[Customer_ID]:[City]],5,FALSE) -> Maybury | D80: =VLOOKUP(Table6[[#This Row],[Customer_ID]],Table1[],3,FALSE) -> 38 | E80: =VLOOKUP(Table6[[#This Row],[Customer_ID]],Table1[],4,FALSE) -> Male | F80: =VLOOKUP(Table6[[#This Row],[Customer_ID]],Table1[],6,FALSE) -> Georgia | G80: =VLOOKUP(Table6[[#This Row],[Customer_ID]],Table1[],8,FALSE) -> Platinum | H80: CUST1221 | I80: 45609 | J80: PROD83 | K80: =VLOOKUP($J80,'Product_Dim (2)'!$A$2:$G$101,{3,4,5,6},FALSE) -> Beauty | L80: =VLOOKUP($J80,'Product_Dim (2)'!$A$2:$G$101,{4,5,6},FALSE) -> Skincare | M80: {=VLOOKUP($J80,'Product_Dim (2)'!$A$2:$G$101,{6},FALSE)} -> 250.41615 | N80: =VLOOKUP($J80,'Product_Dim (2)'!$A$2:$G$101,7,FALSE) -> 159 | O80: STORE8 | P80: =VLOOKUP($O80,'Store_Dim (2)'!$A$2:$E$21,2,FALSE) -> Bean, Jones and Park | Q80: =VLOOKUP(Table6[[#This Row],[Store_ID]],Table4[],3,FALSE) -> West | R80: =VLOOKUP(Table6[[#This Row],[Store_ID]],Table4[],4,FALSE) -> Thompsonborough | S80: =VLOOKUP(Table6[[#This Row],[Store_ID]],Table4[],5,FALSE) -> Online | T80: 2 | U80: 900.55 | V80: 0.16 | W80: Credit Card | X80: 1512.924
A81: SALE79 | B81: =VLOOKUP(Table6[[#This Row],[Customer_ID]],Table1[[Customer_ID]:[Name]],2,FALSE) -> Tyler Conrad | C81: =VLOOKUP(Table6[[#This Row],[Customer_ID]],Table1[[Customer_ID]:[City]],5,FALSE) -> North Curtischester | D81: =VLOOKUP(Table6[[#This Row],[Customer_ID]],Table1[],3,FALSE) -> 53 | E81: =VLOOKUP(Table6[[#This Row],[Customer_ID]],Table1[],4,FALSE) -> Female | F81: =VLOOKUP(Table6[[#This Row],[Customer_ID]],Table1[],6,FALSE) -> North Dakota | G81: =VLOOKUP(Table6[[#This Row],[Customer_ID]],Table1[],8,FALSE) -> Platinum | H81: CUST1115 | I81: 45268 | J81: PROD21 | K81: =VLOOKUP($J81,'Product_Dim (2)'!$A$2:$G$101,{3,4,5,6},FALSE) -> Home | L81: =VLOOKUP($J81,'Product_Dim (2)'!$A$2:$G$101,{4,5,6},FALSE) -> Storage | M81: {=VLOOKUP($J81,'Product_Dim (2)'!$A$2:$G$101,{6},FALSE)} -> 123.46 | N81: =VLOOKUP($J81,'Product_Dim (2)'!$A$2:$G$101,7,FALSE) -> 76 | O81: STORE2 | P81: =VLOOKUP($O81,'Store_Dim (2)'!$A$2:$E$21,2,FALSE) -> Black-Horn | Q81: =VLOOKUP(Table6[[#This Row],[Store_ID]],Table4[],3,FALSE) -> South | R81: =VLOOKUP(Table6[[#This Row],[Store_ID]],Table4[],4,FALSE) -> North Nancyview | S81: =VLOOKUP(Table6[[#This Row],[Store_ID]],Table4[],5,FALSE) -> Outlet | T81: 1 | U81: 341.17 | V81: 0.15 | W81: Credit Card | X81: 289.9945
A82: SALE80 | B82: =VLOOKUP(Table6[[#This Row],[Customer_ID]],Table1[[Customer_ID]:[Name]],2,FALSE) -> John Bradford | C82: =VLOOKUP(Table6[[#This Row],[Customer_ID]],Table1[[Customer_ID]:[City]],5,FALSE) -> Anabury | D82: =VLOOKUP(Table6[[#This Row],[Customer_ID]],Table1[],3,FALSE) -> 48 | E82: =VLOOKUP(Table6[[#This Row],[Customer_ID]],Table1[],4,FALSE) -> Male | F82: =VLOOKUP(Table6[[#This Row],[Customer_ID]],Table1[],6,FALSE) -> Vermont | G82: =VLOOKUP(Table6[[#This Row],[Customer_ID]],Table1[],8,FALSE) -> Silver | H82: CUST1176 | I82: 45885 | J82: PROD52 | K82: =VLOOKUP($J82,'Product_Dim (2)'!$A$2:$G$101,{3,4,5,6},FALSE) -> Sports | L82: =VLOOKUP($J82,'Product_Dim (2)'!$A$2:$G$101,{4,5,6},FALSE) -> Team Sports | M82: {=VLOOKUP($J82,'Product_Dim (2)'!$A$2:$G$101,{6},FALSE)} -> 212.26 | N82: =VLOOKUP($J82,'Product_Dim (2)'!$A$2:$G$101,7,FALSE) -> 82 | O82: STORE8 | P82: =VLOOKUP($O82,'Store_Dim (2)'!$A$2:$E$21,2,FALSE) -> Bean, Jones and Park | Q82: =VLOOKUP(Table6[[#This Row],[Store_ID]],Table4[],3,FALSE) -> West | R82: =VLOOKUP(Table6[[#This Row],[Store_ID]],Table4[],4,FALSE) -> Thompsonborough | S82: =VLOOKUP(Table6[[#This Row],[Store_ID]],Table4[],5,FALSE) -> Online | T82: 1 | U82: 442.27 | V82: 0.06 | W82: COD | X82: 415.7338
A83: SALE81 | B83: =VLOOKUP(Table6[[#This Row],[Customer_ID]],Table1[[Customer_ID]:[Name]],2,FALSE) -> Dr. Ashley Yates Md | C83: =VLOOKUP(Table6[[#This Row],[Customer_ID]],Table1[[Customer_ID]:[City]],5,FALSE) -> New Maria | D83: =VLOOKUP(Table6[[#This Row],[Customer_ID]],Table1[],3,FALSE) -> 32 | E83: =VLOOKUP(Table6[[#This Row],[Customer_ID]],Table1[],4,FALSE) -> Male | F83: =VLOOKUP(Table6[[#This Row],[Customer_ID]],Table1[],6,FALSE) -> Wisconsin | G83: =VLOOKUP(Table6[[#This Row],[Customer_ID]],Table1[],8,FALSE) -> Bronze | H83: CUST1253 | I83: 45616 | J83: PROD71 | K83: =VLOOKUP($J83,'Product_Dim (2)'!$A$2:$G$101,{3,4,5,6},FALSE) -> Beauty | L83: =VLOOKUP($J83,'Product_Dim (2)'!$A$2:$G$101,{4,5,6},FALSE) -> Haircare | M83: {=VLOOKUP($J83,'Product_Dim (2)'!$A$2:$G$101,{6},FALSE)} -> 214.32 | N83: =VLOOKUP($J83,'Product_Dim (2)'!$A$2:$G$101,7,FALSE) -> 383 | O83: STORE9 | P83: =VLOOKUP($O83,'Store_Dim (2)'!$A$2:$E$21,2,FALSE) -> Moore, Padilla and Butler | Q83: =VLOOKUP(Table6[[#This Row],[Store_ID]],Table4[],3,FALSE) -> South | R83: =VLOOKUP(Table6[[#This Row],[Store_ID]],Table4[],4,FALSE) -> East Johnstad | S83: =VLOOKUP(Table6[[#This Row],[Store_ID]],Table4[],5,FALSE) -> Flagship | T83: 1 | U83: 363.73 | V83: 0.25 | W83: PayPal | X83: 272.7975
A84: SALE82 | B84: =VLOOKUP(Table6[[#This Row],[Customer_ID]],Table1[[Customer_ID]:[Name]],2,FALSE) -> Frank Stewart | C84: =VLOOKUP(Table6[[#This Row],[Customer_ID]],Table1[[Customer_ID]:[City]],5,FALSE) -> Fischerborough | D84: =VLOOKUP(Table6[[#This Row],[Customer_ID]],Table1[],3,FALSE) -> 44 | E84: =VLOOKUP(Table6[[#This Row],[Customer_ID]],Table1[],4,FALSE) -> Female | F84: =VLOOKUP(Table6[[#This Row],[Customer_ID]],Table1[],6,FALSE) -> Delaware | G84: =VLOOKUP(Table6[[#This Row],[Customer_ID]],Table1[],8,FALSE) -> Bronze | H84: CUST1378 | I84: 45518 | J84: PROD91 | K84: =VLOOKUP($J84,'Product_Dim (2)'!$A$2:$G$101,{3,4,5,6},FALSE) -> Clothing | L84: =VLOOKUP($J84,'Product_Dim (2)'!$A$2:$G$101,{4,5,6},FALSE) -> Footwear | M84: {=VLOOKUP($J84,'Product_Dim (2)'!$A$2:$G$101,{6},FALSE)} -> 438.25 | N84: =VLOOKUP($J84,'Product_Dim (2)'!$A$2:$G$101,7,FALSE) -> 496 | O84: STORE17 | P84: =VLOOKUP($O84,'Store_Dim (2)'!$A$2:$E$21,2,FALSE) -> Holloway Ltd | Q84: =VLOOKUP(Table6[[#This Row],[Store_ID]],Table4[],3,FALSE) -> North | R84: =VLOOKUP(Table6[[#This Row],[Store_ID]],Table4[],4,FALSE) -> Bensonhaven | S84: =VLOOKUP(Table6[[#This Row],[Store_ID]],Table4[],5,FALSE) -> Flagship | T84: 2 | U84: 601.33 | V84: 0.16 | W84: PayPal | X84: 1010.2344
A85: SALE83 | B85: =VLOOKUP(Table6[[#This Row],[Customer_ID]],Table1[[Customer_ID]:[Name]],2,FALSE) -> Justin Ingram | C85: =VLOOKUP(Table6[[#This Row],[Customer_ID]],Table1[[Customer_ID]:[City]],5,FALSE) -> Lake Lisaland | D85: =VLOOKUP(Table6[[#This Row],[Customer_ID]],Table1[],3,FALSE) -> 34 | E85: =VLOOKUP(Table6[[#This Row],[Customer_ID]],Table1[],4,FALSE) -> Male | F85: =VLOOKUP(Table6[[#This Row],[Customer_ID]],Table1[],6,FALSE) -> Louisiana | G85: =VLOOKUP(Table6[[#This Row],[Customer_ID]],Table1[],8,FALSE) -> Bronze | H85: CUST1403 | I85: 45427 | J85: PROD17 | K85: =VLOOKUP($J85,'Product_Dim (2)'!$A$2:$G$101,{3,4,5,6},FALSE) -> Sports | L85: =VLOOKUP($J85,'Product_Dim (2)'!$A$2:$G$101,{4,5,6},FALSE) -> Accessories | M85: {=VLOOKUP($J85,'Product_Dim (2)'!$A$2:$G$101,{6},FALSE)} -> 144.53 | N85: =VLOOKUP($J85,'Product_Dim (2)'!$A$2:$G$101,7,FALSE) -> 367 | O85: STORE18 | P85: =VLOOKUP($O85,'Store_Dim (2)'!$A$2:$E$21,2,FALSE) -> Guerrero-Schmitt | Q85: =VLOOKUP(Table6[[#This Row],[Store_ID]],Table4[],3,FALSE) -> East | R85: =VLOOKUP(Table6[[#This Row],[Store_ID]],Table4[],4,FALSE) -> East Stevechester | S85: =VLOOKUP(Table6[[#This Row],[Store_ID]],Table4[],5,FALSE) -> Flagship | T85: 4 | U85: 34.39 | V85: 0.03 | W85: PayPal | X85: 133.4332
A86: SALE84 | B86: =VLOOKUP(Table6[[#This Row],[Customer_ID]],Table1[[Customer_ID]:[Name]],2,FALSE) -> Rebecca Baker | C86: =VLOOKUP(Table6[[#This Row],[Customer_ID]],Table1[[Customer_ID]:[City]],5,FALSE) -> New Katherine | D86: =VLOOKUP(Table6[[#This Row],[Customer_ID]],Table1[],3,FALSE) -> 35 | E86: =VLOOKUP(Table6[[#This Row],[Customer_ID]],Table1[],4,FALSE) -> Male | F86: =VLOOKUP(Table6[[#This Row],[Customer_ID]],Table1[],6,FALSE) -> Kansas | G86: =VLOOKUP(Table6[[#This Row],[Customer_ID]],Table1[],8,FALSE) -> Silver | H86: CUST1423 | I86: 45268 | J86: PROD46 | K86: =VLOOKUP($J86,'Product_Dim (2)'!$A$2:$G$101,{3,4,5,6},FALSE) -> Clothing | L86: =VLOOKUP($J86,'Product_Dim (2)'!$A$2:$G$101,{4,5,6},FALSE) -> Outerwear | M86: {=VLOOKUP($J86,'Product_Dim (2)'!$A$2:$G$101,{6},FALSE)} -> 167.34 | N86: =VLOOKUP($J86,'Product_Dim (2)'!$A$2:$G$101,7,FALSE) -> 296 | O86: STORE17 | P86: =VLOOKUP($O86,'Store_Dim (2)'!$A$2:$E$21,2,FALSE) -> Holloway Ltd | Q86: =VLOOKUP(Table6[[#This Row],[Store_ID]],Table4[],3,FALSE) -> North | R86: =VLOOKUP(Table6[[#This Row],[Store_ID]],Table4[],4,FALSE) -> Bensonhaven | S86: =VLOOKUP(Table6[[#This Row],[Store_ID]],Table4[],5,FALSE) -> Flagship | T86: 1 | U86: 773.57 | V86: 0.05 | W86: COD | X86: =T86*U86*(1-V86) -> 734.8915
A87: SALE85 | B87: =VLOOKUP(Table6[[#This Row],[Customer_ID]],Table1[[Customer_ID]:[Name]],2,FALSE) -> Katherine Dorsey | C87: =VLOOKUP(Table6[[#This Row],[Customer_ID]],Table1[[Customer_ID]:[City]],5,FALSE) -> Christopherland | D87: =VLOOKUP(Table6[[#This Row],[Customer_ID]],Table1[],3,FALSE) -> 24 | E87: =VLOOKUP(Table6[[#This Row],[Customer_ID]],Table1[],4,FALSE) -> Male | F87: =VLOOKUP(Table6[[#This Row],[Customer_ID]],Table1[],6,FALSE) -> Oklahoma | G87: =VLOOKUP(Table6[[#This Row],[Customer_ID]],Table1[],8,FALSE) -> Platinum | H87: CUST1054 | I87: 45282 | J87: PROD88 | K87: =VLOOKUP($J87,'Product_Dim (2)'!$A$2:$G$101,{3,4,5,6},FALSE) -> Sports | L87: =VLOOKUP($J87,'Product_Dim (2)'!$A$2:$G$101,{4,5,6},FALSE) -> Accessories | M87: {=VLOOKUP($J87,'Product_Dim (2)'!$A$2:$G$101,{6},FALSE)} -> 131.24 | N87: =VLOOKUP($J87,'Product_Dim (2)'!$A$2:$G$101,7,FALSE) -> 232 | O87: STORE7 | P87: =VLOOKUP($O87,'Store_Dim (2)'!$A$2:$E$21,2,FALSE) -> Martinez-Mullins | Q87: =VLOOKUP(Table6[[#This Row],[Store_ID]],Table4[],3,FALSE) -> South | R87: =VLOOKUP(Table6[[#This Row],[Store_ID]],Table4[],4,FALSE) -> Williamsfurt | S87: =VLOOKUP(Table6[[#This Row],[Store_ID]],Table4[],5,FALSE) -> Online | T87: 4 | U87: 127.1 | V87: 0.24 | W87: COD | X87: 386.384
A88: SALE86 | B88: =VLOOKUP(Table6[[#This Row],[Customer_ID]],Table1[[Customer_ID]:[Name]],2,FALSE) -> John Sloan | C88: =VLOOKUP(Table6[[#This Row],[Customer_ID]],Table1[[Customer_ID]:[City]],5,FALSE) -> East Johntown | D88: =VLOOKUP(Table6[[#This Row],[Customer_ID]],Table1[],3,FALSE) -> 23 | E88: =VLOOKUP(Table6[[#This Row],[Customer_ID]],Table1[],4,FALSE) -> Female | F88: =VLOOKUP(Table6[[#This Row],[Customer_ID]],Table1[],6,FALSE) -> Delaware | G88: =VLOOKUP(Table6[[#This Row],[Customer_ID]],Table1[],8,FALSE) -> Platinum | H88: CUST1303 | I88: 45545 | J88: PROD20 | K88: =VLOOKUP($J88,'Product_Dim (2)'!$A$2:$G$101,{3,4,5,6},FALSE) -> Sports | L88: =VLOOKUP($J88,'Product_Dim (2)'!$A$2:$G$101,{4,5,6},FALSE) -> Accessories | M88: {=VLOOKUP($J88,'Product_Dim (2)'!$A$2:$G$101,{6},FALSE)} -> 131.51 | N88: =VLOOKUP($J88,'Product_Dim (2)'!$A$2:$G$101,7,FALSE) -> 0 | O88: STORE3 | P88: =VLOOKUP($O88,'Store_Dim (2)'!$A$2:$E$21,2,FALSE) -> Johnson-Wright | Q88: =VLOOKUP(Table6[[#This Row],[Store_ID]],Table4[],3,FALSE) -> North | R88: =VLOOKUP(Table6[[#This Row],[Store_ID]],Table4[],4,FALSE) -> Hoodberg | S88: =VLOOKUP(Table6[[#This Row],[Store_ID]],Table4[],5,FALSE) -> Outlet | T88: 3 | U88: 899.58 | V88: 0.28 | W88: PayPal | X88: 1943.0928
A89: SALE87 | B89: =VLOOKUP(Table6[[#This Row],[Customer_ID]],Table1[[Customer_ID]:[Name]],2,FALSE) -> Reginald Willis | C89: =VLOOKUP(Table6[[#This Row],[Customer_ID]],Table1[[Customer_ID]:[City]],5,FALSE) -> Kellybury | D89: =VLOOKUP(Table6[[#This Row],[Customer_ID]],Table1[],3,FALSE) -> 62 | E89: =VLOOKUP(Table6[[#This Row],[Customer_ID]],Table1[],4,FALSE) -> Female | F89: =VLOOKUP(Table6[[#This Row],[Customer_ID]],Table1[],6,FALSE) -> New York | G89: =VLOOKUP(Table6[[#This Row],[Customer_ID]],Table1[],8,FALSE) -> Bronze | H89: CUST1327 | I89: 45755 | J89: PROD1 | K89: =VLOOKUP($J89,'Product_Dim (2)'!$A$2:$G$101,{3,4,5,6},FALSE) -> Clothing | L89: =VLOOKUP($J89,'Product_Dim (2)'!$A$2:$G$101,{4,5,6},FALSE) -> Tops | M89: {=VLOOKUP($J89,'Product_Dim (2)'!$A$2:$G$101,{6},FALSE)} -> 342.56 | N89: =VLOOKUP($J89,'Product_Dim (2)'!$A$2:$G$101,7,FALSE) -> 181 | O89: STORE10 | P89: =VLOOKUP($O89,'Store_Dim (2)'!$A$2:$E$21,2,FALSE) -> Hill, Wagner and Ballard | Q89: =VLOOKUP(Table6[[#This Row],[Store_ID]],Table4[],3,FALSE) -> East | R89: =VLOOKUP(Table6[[#This Row],[Store_ID]],Table4[],4,FALSE) -> East Davidville | S89: =VLOOKUP(Table6[[#This Row],[Store_ID]],Table4[],5,FALSE) -> Online | T89: 3 | U89: 964.39 | V89: 0.04 | W89: Credit Card | X89: 2777.4432
A90: SALE88 | B90: =VLOOKUP(Table6[[#This Row],[Customer_ID]],Table1[[Customer_ID]:[Name]],2,FALSE) -> Mario Jacobs | C90: =VLOOKUP(Table6[[#This Row],[Customer_ID]],Table1[[Customer_ID]:[City]],5,FALSE) -> Port James | D90: =VLOOKUP(Table6[[#This Row],[Customer_ID]],Table1[],3,FALSE) -> 18 | E90: =VLOOKUP(Table6[[#This Row],[Customer_ID]],Table1[],4,FALSE) -> Male | F90: =VLOOKUP(Table6[[#This Row],[Customer_ID]],Table1[],6,FALSE) -> New York | G90: =VLOOKUP(Table6[[#This Row],[Customer_ID]],Table1[],8,FALSE) -> Platinum | H90: CUST1183 | I90: 45588 | J90: PROD38 | K90: =VLOOKUP($J90,'Product_Dim (2)'!$A$2:$G$101,{3,4,5,6},FALSE) -> Sports | L90: =VLOOKUP($J90,'Product_Dim (2)'!$A$2:$G$101,{4,5,6},FALSE) -> Outdoor | M90: {=VLOOKUP($J90,'Product_Dim (2)'!$A$2:$G$101,{6},FALSE)} -> 135.61 | N90: =VLOOKUP($J90,'Product_Dim (2)'!$A$2:$G$101,7,FALSE) -> 394 | O90: STORE0 | P90: =VLOOKUP($O90,'Store_Dim (2)'!$A$2:$E$21,2,FALSE) -> Rivera-Warner | Q90: =VLOOKUP(Table6[[#This Row],[Store_ID]],Table4[],3,FALSE) -> East | R90: =VLOOKUP(Table6[[#This Row],[Store_ID]],Table4[],4,FALSE) -> Washingtonfurt | S90: =VLOOKUP(Table6[[#This Row],[Store_ID]],Table4[],5,FALSE) -> Flagship | T90: 2 | U90: 217.83 | V90: 0.14 | W90: PayPal | X90: 374.6676
A91: SALE89 | B91: =VLOOKUP(Table6[[#This Row],[Customer_ID]],Table1[[Customer_ID]:[Name]],2,FALSE) -> Carlos Skinner | C91: =VLOOKUP(Table6[[#This Row],[Customer_ID]],Table1[[Customer_ID]:[City]],5,FALSE) -> Dwaynemouth | D91: =VLOOKUP(Table6[[#This Row],[Customer_ID]],Table1[],3,FALSE) -> 46 | E91: =VLOOKUP(Table6[[#This Row],[Customer_ID]],Table1[],4,FALSE) -> Male | F91: =VLOOKUP(Table6[[#This Row],[Customer_ID]],Table1[],6,FALSE) -> Alabama | G91: =VLOOKUP(Table6[[#This Row],[Customer_ID]],Table1[],8,FALSE) -> Bronze | H91: CUST1143 | I91: 45848 | J91: PROD17 | K91: =VLOOKUP($J91,'Product_Dim (2)'!$A$2:$G$101,{3,4,5,6},FALSE) -> Sports | L91: =VLOOKUP($J91,'Product_Dim (2)'!$A$2:$G$101,{4,5,6},FALSE) -> Accessories | M91: {=VLOOKUP($J91,'Product_Dim (2)'!$A$2:$G$101,{6},FALSE)} -> 144.53 | N91: =VLOOKUP($J91,'Product_Dim (2)'!$A$2:$G$101,7,FALSE) -> 367 | O91: STORE1 | P91: =VLOOKUP($O91,'Store_Dim (2)'!$A$2:$E$21,2,FALSE) -> Martinez, Adkins and Johnson | Q91: =VLOOKUP(Table6[[#This Row],[Store_ID]],Table4[],3,FALSE) -> North | R91: =VLOOKUP(Table6[[#This Row],[Store_ID]],Table4[],4,FALSE) -> Danielmouth | S91: =VLOOKUP(Table6[[#This Row],[Store_ID]],Table4[],5,FALSE) -> Flagship | T91: 4 | U91: 187.71 | V91: 0.06 | W91: COD | X91: 705.7896
A92: SALE90 | B92: =VLOOKUP(Table6[[#This Row],[Customer_ID]],Table1[[Customer_ID]:[Name]],2,FALSE) -> Dominic Page | C92: =VLOOKUP(Table6[[#This Row],[Customer_ID]],Table1[[Customer_ID]:[City]],5,FALSE) -> Port Michaelburgh | D92: =VLOOKUP(Table6[[#This Row],[Customer_ID]],Table1[],3,FALSE) -> 53 | E92: =VLOOKUP(Table6[[#This Row],[Customer_ID]],Table1[],4,FALSE) -> Male | F92: =VLOOKUP(Table6[[#This Row],[Customer_ID]],Table1[],6,FALSE) -> Pennsylvania | G92: =VLOOKUP(Table6[[#This Row],[Customer_ID]],Table1[],8,FALSE) -> Bronze | H92: CUST1010 | I92: 45577 | J92: PROD33 | K92: =VLOOKUP($J92,'Product_Dim (2)'!$A$2:$G$101,{3,4,5,6},FALSE) -> Home | L92: =VLOOKUP($J92,'Product_Dim (2)'!$A$2:$G$101,{4,5,6},FALSE) -> Decor | M92: {=VLOOKUP($J92,'Product_Dim (2)'!$A$2:$G$101,{6},FALSE)} -> 179.77 | N92: =VLOOKUP($J92,'Product_Dim (2)'!$A$2:$G$101,7,FALSE) -> 305 | O92: STORE18 | P92: =VLOOKUP($O92,'Store_Dim (2)'!$A$2:$E$21,2,FALSE) -> Guerrero-Schmitt | Q92: =VLOOKUP(Table6[[#This Row],[Store_ID]],Table4[],3,FALSE) -> East | R92: =VLOOKUP(Table6[[#This Row],[Store_ID]],Table4[],4,FALSE) -> East Stevechester | S92: =VLOOKUP(Table6[[#This Row],[Store_ID]],Table4[],5,FALSE) -> Flagship | T92: 2 | U92: 350.12 | V92: 0.12 | W92: COD | X92: 616.2112
A93: SALE91 | B93: =VLOOKUP(Table6[[#This Row],[Customer_ID]],Table1[[Customer_ID]:[Name]],2,FALSE) -> David Lozano | C93: =VLOOKUP(Table6[[#This Row],[Customer_ID]],Table1[[Customer_ID]:[City]],5,FALSE) -> North Michaelfurt | D93: =VLOOKUP(Table6[[#This Row],[Customer_ID]],Table1[],3,FALSE) -> 23 | E93: =VLOOKUP(Table6[[#This Row],[Customer_ID]],Table1[],4,FALSE) -> Female | F93: =VLOOKUP(Table6[[#This Row],[Customer_ID]],Table1[],6,FALSE) -> Wisconsin | G93: =VLOOKUP(Table6[[#This Row],[Customer_ID]],Table1[],8,FALSE) -> Gold | H93: CUST1406 | I93: 45312 | J93: PROD16 | K93: =VLOOKUP($J93,'Product_Dim (2)'!$A$2:$G$101,{3,4,5,6},FALSE) -> Beauty | L93: =VLOOKUP($J93,'Product_Dim (2)'!$A$2:$G$101,{4,5,6},FALSE) -> Grooming | M93: {=VLOOKUP($J93,'Product_Dim (2)'!$A$2:$G$101,{6},FALSE)} -> 337.42 | N93: =VLOOKUP($J93,'Product_Dim (2)'!$A$2:$G$101,7,FALSE) -> 256 | O93: STORE1 | P93: =VLOOKUP($O93,'Store_Dim (2)'!$A$2:$E$21,2,FALSE) -> Martinez, Adkins and Johnson | Q93: =VLOOKUP(Table6[[#This Row],[Store_ID]],Table4[],3,FALSE) -> North | R93: =VLOOKUP(Table6[[#This Row],[Store_ID]],Table4[],4,FALSE) -> Danielmouth | S93: =VLOOKUP(Table6[[#This Row],[Store_ID]],Table4[],5,FALSE) -> Flagship | T93: 4 | U93: 102.19 | V93: 0.17 | W93: PayPal | X93: 339.2708
A94: SALE92 | B94: =VLOOKUP(Table6[[#This Row],[Customer_ID]],Table1[[Customer_ID]:[Name]],2,FALSE) -> Daniel Boyd | C94: =VLOOKUP(Table6[[#This Row],[Customer_ID]],Table1[[Customer_ID]:[City]],5,FALSE) -> West Pamelafurt | D94: =VLOOKUP(Table6[[#This Row],[Customer_ID]],Table1[],3,FALSE) -> 29 | E94: =VLOOKUP(Table6[[#This Row],[Customer_ID]],Table1[],4,FALSE) -> Female | F94: =VLOOKUP(Table6[[#This Row],[Customer_ID]],Table1[],6,FALSE) -> West Virginia | G94: =VLOOKUP(Table6[[#This Row],[Customer_ID]],Table1[],8,FALSE) -> Bronze | H94: CUST1007 | I94: 45350 | J94: PROD86 | K94: =VLOOKUP($J94,'Product_Dim (2)'!$A$2:$G$101,{3,4,5,6},FALSE) -> Home | L94: =VLOOKUP($J94,'Product_Dim (2)'!$A$2:$G$101,{4,5,6},FALSE) -> Kitchen | M94: {=VLOOKUP($J94,'Product_Dim (2)'!$A$2:$G$101,{6},FALSE)} -> 176.07 | N94: =VLOOKUP($J94,'Product_Dim (2)'!$A$2:$G$101,7,FALSE) -> 82 | O94: STORE4 | P94: =VLOOKUP($O94,'Store_Dim (2)'!$A$2:$E$21,2,FALSE) -> Alexander Group | Q94: =VLOOKUP(Table6[[#This Row],[Store_ID]],Table4[],3,FALSE) -> South | R94: =VLOOKUP(Table6[[#This Row],[Store_ID]],Table4[],4,FALSE) -> Port Sharon | S94: =VLOOKUP(Table6[[#This Row],[Store_ID]],Table4[],5,FALSE) -> Online | T94: 1 | U94: 696.53 | V94: 0.17 | W94: Credit Card | X94: 578.1199
A95: SALE93 | B95: =VLOOKUP(Table6[[#This Row],[Customer_ID]],Table1[[Customer_ID]:[Name]],2,FALSE) -> Michael Thomas | C95: =VLOOKUP(Table6[[#This Row],[Customer_ID]],Table1[[Customer_ID]:[City]],5,FALSE) -> Woodmouth | D95: =VLOOKUP(Table6[[#This Row],[Customer_ID]],Table1[],3,FALSE) -> 21 | E95: =VLOOKUP(Table6[[#This Row],[Customer_ID]],Table1[],4,FALSE) -> Female | F95: =VLOOKUP(Table6[[#This Row],[Customer_ID]],Table1[],6,FALSE) -> Nevada | G95: =VLOOKUP(Table6[[#This Row],[Customer_ID]],Table1[],8,FALSE) -> Silver | H95: CUST1065 | I95: 45657 | J95: PROD19 | K95: =VLOOKUP($J95,'Product_Dim (2)'!$A$2:$G$101,{3,4,5,6},FALSE) -> Sports | L95: =VLOOKUP($J95,'Product_Dim (2)'!$A$2:$G$101,{4,5,6},FALSE) -> Equipment | M95: {=VLOOKUP($J95,'Product_Dim (2)'!$A$2:$G$101,{6},FALSE)} -> 21.34 | N95: =VLOOKUP($J95,'Product_Dim (2)'!$A$2:$G$101,7,FALSE) -> 65 | O95: STORE4 | P95: =VLOOKUP($O95,'Store_Dim (2)'!$A$2:$E$21,2,FALSE) -> Alexander Group | Q95: =VLOOKUP(Table6[[#This Row],[Store_ID]],Table4[],3,FALSE) -> South | R95: =VLOOKUP(Table6[[#This Row],[Store_ID]],Table4[],4,FALSE) -> Port Sharon | S95: =VLOOKUP(Table6[[#This Row],[Store_ID]],Table4[],5,FALSE) -> Online | T95: 2 | U95: 327.52 | V95: 0.15 | W95: PayPal | X95: 556.784
A96: SALE94 | B96: =VLOOKUP(Table6[[#This Row],[Customer_ID]],Table1[[Customer_ID]:[Name]],2,FALSE) -> Tracy Stephens | C96: =VLOOKUP(Table6[[#This Row],[Customer_ID]],Table1[[Customer_ID]:[City]],5,FALSE) -> New Joshuatown | D96: =VLOOKUP(Table6[[#This Row],[Customer_ID]],Table1[],3,FALSE) -> 64 | E96: =VLOOKUP(Table6[[#This Row],[Customer_ID]],Table1[],4,FALSE) -> Male | F96: =VLOOKUP(Table6[[#This Row],[Customer_ID]],Table1[],6,FALSE) -> Maine | G96: =VLOOKUP(Table6[[#This Row],[Customer_ID]],Table1[],8,FALSE) -> Platinum | H96: CUST1298 | I96: 45530 | J96: PROD97 | K96: =VLOOKUP($J96,'Product_Dim (2)'!$A$2:$G$101,{3,4,5,6},FALSE) -> Sports | L96: =VLOOKUP($J96,'Product_Dim (2)'!$A$2:$G$101,{4,5,6},FALSE) -> Team Sports | M96: {=VLOOKUP($J96,'Product_Dim (2)'!$A$2:$G$101,{6},FALSE)} -> 245.98 | N96: =VLOOKUP($J96,'Product_Dim (2)'!$A$2:$G$101,7,FALSE) -> 471 | O96: STORE19 | P96: =VLOOKUP($O96,'Store_Dim (2)'!$A$2:$E$21,2,FALSE) -> Mann-Austin | Q96: =VLOOKUP(Table6[[#This Row],[Store_ID]],Table4[],3,FALSE) -> East | R96: =VLOOKUP(Table6[[#This Row],[Store_ID]],Table4[],4,FALSE) -> Vasquezborough | S96: =VLOOKUP(Table6[[#This Row],[Store_ID]],Table4[],5,FALSE) -> Online | T96: 2 | U96: 569.36 | V96: 0.01 | W96: PayPal | X96: =T96*U96*(1-V96) -> 1127.3328
A97: SALE95 | B97: =VLOOKUP(Table6[[#This Row],[Customer_ID]],Table1[[Customer_ID]:[Name]],2,FALSE) -> Darren Burton | C97: =VLOOKUP(Table6[[#This Row],[Customer_ID]],Table1[[Customer_ID]:[City]],5,FALSE) -> Lake Alice | D97: =VLOOKUP(Table6[[#This Row],[Customer_ID]],Table1[],3,FALSE) -> 21 | E97: =VLOOKUP(Table6[[#This Row],[Customer_ID]],Table1[],4,FALSE) -> Female | F97: =VLOOKUP(Table6[[#This Row],[Customer_ID]],Table1[],6,FALSE) -> Tennessee | G97: =VLOOKUP(Table6[[#This Row],[Customer_ID]],Table1[],8,FALSE) -> Bronze | H97: CUST1321 | I97: 45556 | J97: PROD99 | K97: =VLOOKUP($J97,'Product_Dim (2)'!$A$2:$G$101,{3,4,5,6},FALSE) -> Home | L97: =VLOOKUP($J97,'Product_Dim (2)'!$A$2:$G$101,{4,5,6},FALSE) -> Kitchen | M97: {=VLOOKUP($J97,'Product_Dim (2)'!$A$2:$G$101,{6},FALSE)} -> 201.41 | N97: =VLOOKUP($J97,'Product_Dim (2)'!$A$2:$G$101,7,FALSE) -> 146 | O97: STORE6 | P97: =VLOOKUP($O97,'Store_Dim (2)'!$A$2:$E$21,2,FALSE) -> Benson-Elliott | Q97: =VLOOKUP(Table6[[#This Row],[Store_ID]],Table4[],3,FALSE) -> East | R97: =VLOOKUP(Table6[[#This Row],[Store_ID]],Table4[],4,FALSE) -> Port Josephberg | S97: =VLOOKUP(Table6[[#This Row],[Store_ID]],Table4[],5,FALSE) -> Online | T97: 2 | U97: 68.29 | V97: 0.14 | W97: COD | X97: 117.4588
A98: SALE96 | B98: =VLOOKUP(Table6[[#This Row],[Customer_ID]],Table1[[Customer_ID]:[Name]],2,FALSE) -> Nancy Page | C98: =VLOOKUP(Table6[[#This Row],[Customer_ID]],Table1[[Customer_ID]:[City]],5,FALSE) -> West Julia | D98: =VLOOKUP(Table6[[#This Row],[Customer_ID]],Table1[],3,FALSE) -> 19 | E98: =VLOOKUP(Table6[[#This Row],[Customer_ID]],Table1[],4,FALSE) -> Male | F98: =VLOOKUP(Table6[[#This Row],[Customer_ID]],Table1[],6,FALSE) -> Utah | G98: =VLOOKUP(Table6[[#This Row],[Customer_ID]],Table1[],8,FALSE) -> Bronze | H98: CUST1244 | I98: 45523 | J98: PROD50 | K98: =VLOOKUP($J98,'Product_Dim (2)'!$A$2:$G$101,{3,4,5,6},FALSE) -> Sports | L98: =VLOOKUP($J98,'Product_Dim (2)'!$A$2:$G$101,{4,5,6},FALSE) -> Fitness | M98: {=VLOOKUP($J98,'Product_Dim (2)'!$A$2:$G$101,{6},FALSE)} -> 190.29 | N98: =VLOOKUP($J98,'Product_Dim (2)'!$A$2:$G$101,7,FALSE) -> 260 | O98: STORE10 | P98: =VLOOKUP($O98,'Store_Dim (2)'!$A$2:$E$21,2,FALSE) -> Hill, Wagner and Ballard | Q98: =VLOOKUP(Table6[[#This Row],[Store_ID]],Table4[],3,FALSE) -> East | R98: =VLOOKUP(Table6[[#This Row],[Store_ID]],Table4[],4,FALSE) -> East Davidville | S98: =VLOOKUP(Table6[[#This Row],[Store_ID]],Table4[],5,FALSE) -> Online | T98: 1 | U98: 842.9 | V98: 0.06 | W98: COD | X98: 792.326
A99: SALE97 | B99: =VLOOKUP(Table6[[#This Row],[Customer_ID]],Table1[[Customer_ID]:[Name]],2,FALSE) -> Cynthia Roberts | C99: =VLOOKUP(Table6[[#This Row],[Customer_ID]],Table1[[Customer_ID]:[City]],5,FALSE) -> Millerfort | D99: =VLOOKUP(Table6[[#This Row],[Customer_ID]],Table1[],3,FALSE) -> 22 | E99: =VLOOKUP(Table6[[#This Row],[Customer_ID]],Table1[],4,FALSE) -> Female | F99: =VLOOKUP(Table6[[#This Row],[Customer_ID]],Table1[],6,FALSE) -> Vermont | G99: =VLOOKUP(Table6[[#This Row],[Customer_ID]],Table1[],8,FALSE) -> Gold | H99: CUST1287 | I99: 45587 | J99: PROD3 | K99: =VLOOKUP($J99,'Product_Dim (2)'!$A$2:$G$101,{3,4,5,6},FALSE) -> Clothing | L99: =VLOOKUP($J99,'Product_Dim (2)'!$A$2:$G$101,{4,5,6},FALSE) -> Outerwear | M99: {=VLOOKUP($J99,'Product_Dim (2)'!$A$2:$G$101,{6},FALSE)} -> 364.67 | N99: =VLOOKUP($J99,'Product_Dim (2)'!$A$2:$G$101,7,FALSE) -> 452 | O99: STORE3 | P99: =VLOOKUP($O99,'Store_Dim (2)'!$A$2:$E$21,2,FALSE) -> Johnson-Wright | Q99: =VLOOKUP(Table6[[#This Row],[Store_ID]],Table4[],3,FALSE) -> North | R99: =VLOOKUP(Table6[[#This Row],[Store_ID]],Table4[],4,FALSE) -> Hoodberg | S99: =VLOOKUP(Table6[[#This Row],[Store_ID]],Table4[],5,FALSE) -> Outlet | T99: 3 | U99: 751.94 | V99: 0.26 | W99: PayPal | X99: 1669.3068
A100: SALE98 | B100: =VLOOKUP(Table6[[#This Row],[Customer_ID]],Table1[[Customer_ID]:[Name]],2,FALSE) -> Joseph Richards | C100: =VLOOKUP(Table6[[#This Row],[Customer_ID]],Table1[[Customer_ID]:[City]],5,FALSE) -> Wigginsville | D100: =VLOOKUP(Table6[[#This Row],[Customer_ID]],Table1[],3,FALSE) -> 34 | E100: =VLOOKUP(Table6[[#This Row],[Customer_ID]],Table1[],4,FALSE) -> Female | F100: =VLOOKUP(Table6[[#This Row],[Customer_ID]],Table1[],6,FALSE) -> Alabama | G100: =VLOOKUP(Table6[[#This Row],[Customer_ID]],Table1[],8,FALSE) -> Bronze | H100: CUST1131 | I100: 45580 | J100: PROD56 | K100: =VLOOKUP($J100,'Product_Dim (2)'!$A$2:$G$101,{3,4,5,6},FALSE) -> Home | L100: =VLOOKUP($J100,'Product_Dim (2)'!$A$2:$G$101,{4,5,6},FALSE) -> Decor | M100: {=VLOOKUP($J100,'Product_Dim (2)'!$A$2:$G$101,{6},FALSE)} -> 461.47 | N100: =VLOOKUP($J100,'Product_Dim (2)'!$A$2:$G$101,7,FALSE) -> 190 | O100: STORE7 | P100: =VLOOKUP($O100,'Store_Dim (2)'!$A$2:$E$21,2,FALSE) -> Martinez-Mullins | Q100: =VLOOKUP(Table6[[#This Row],[Store_ID]],Table4[],3,FALSE) -> South | R100: =VLOOKUP(Table6[[#This Row],[Store_ID]],Table4[],4,FALSE) -> Williamsfurt | S100: =VLOOKUP(Table6[[#This Row],[Store_ID]],Table4[],5,FALSE) -> Online | T100: 4 | U100: 476.28 | V100: 0.17 | W100: Credit Card | X100: 1581.2496
...

Sheet Aggregrate functions
B4: Total number of transactions | G4: =COUNTA(Table6[Sales_ID]) -> 2000
B5: Total revenue generated | G5: =SUM(Table6[Total_Amount]) -> 2174394.7
B6: Average revenue per transaction | G6: =AVERAGE(Table6[Total_Amount]) -> 1087.1973
B7: Average quantity of products sold per transaction | G7: =INT(AVERAGE(Table6[Quantity])) -> 2
B8: Average discount percentage | G8: =AVERAGE(Table6[Discount]) -> 0.14796
B9: Loyalty | G9: =INDEX(Table6[Loyalty_level],_xlfn.MODE.MULT(MATCH(Table6[Loyalty_level],Table6[Loyalty_level],FALSE))) -> Platinum
B10: Total revenue from Male customers | G10: =SUMIF(Table6[Sex],"Male",Table6[Total_Amount]) -> 942950.47
B11: Total revenue from Female customers | G11: =SUMIF(Table6[Sex],"Female",Table6[Total_Amount]) -> 1231444.2
B12: Number of purchases by female customers | G12: =COUNTIF(Table6[Sex],"Female") -> 1096
B13: Number of purchases by male customers | G13: =COUNTIF(Table6[Sex],"Male") -> 904
B14: Total revenue generated from location | D14: Indiana | G14: =SUMIF(Table6[State],"Indiana",Table6[Total_Amount]) -> 51827.029
B15: Most popular popular category | G15: =INDEX(Table6[Category],_xlfn.MODE.MULT(MATCH(Table6[Category],Table6[Category],0))) -> Sports
B16: Location with the Most customers | G16: =INDEX(Table6[City],_xlfn.MODE.MULT(MATCH(Table6[City],Table6[City],0))) -> Christopherland
B17: Total quantity | G17: =SUM(Table6[Quantity]) -> 4964

Sheet Analysis ToolPak
E6: Quantity | I6: Total_Amount | M6: Discount
E8: Mean | F8: 2.482 | I8: Mean | J8: 1087.1973 | M8: Mean | N8: 0.14796
E9: Standard Error | F9: 0.024852501 | I9: Standard Error | J9: 18.327237 | M9: Standard Error | N9: 0.0019598571
E10: Median | F10: 2 | I10: Median | J10: 868.7182 | M10: Median | N10: 0.14
E11: Mode | F11: 2 | I11: Mode | J11: #N/A | M11: Mode | N11: 0.1
E12: Standard Deviation | F12: 1.1114376 | I12: Standard Deviation | J12: 819.61896 | M12: Standard Deviation | N12: 0.087647473
E13: Sample Variance | F13: 1.2352936 | I13: Sample Variance | J13: 671775.25 | M13: Sample Variance | N13: 0.0076820794
E14: Kurtosis | F14: -1.3441226 | I14: Kurtosis | J14: 0.045826153 | M14: Kurtosis | N14: -1.208024
E15: Skewness | F15: 0.022378357 | I15: Skewness | J15: 0.87904704 | M15: Skewness | N15: 0.062951035
E16: Range | F16: 3 | I16: Range | J16: 3889.7838 | M16: Range | N16: 0.3
E17: Minimum | F17: 1 | I17: Minimum | J17: 18.459 | M17: Minimum | N17: 0
E18: Maximum | F18: 4 | I18: Maximum | J18: 3908.2428 | M18: Maximum | N18: 0.3
E19: Sum | F19: 4964 | I19: Sum | J19: 2174394.7 | M19: Sum | N19: 295.92
E20: Count | F20: 2000 | I20: Count | J20: 2000 | M20: Count | N20: 2000

Sheet Customer_Dim
A1: Customer_ID | B1: Name | C1: Age | D1: Gender | E1: City | F1: State | G1: Country | H1: Loyalty_Level
A2: CUST1322 | B2: Samuel Arias | C2: 54 | D2: Male | E2: North Nicole | F2: Wyoming | G2: USA | H2: Bronze
A3: CUST1448 | B3: Eric Holmes | C3: 64 | D3: Female | E3: Smithville | F3: Wyoming | G3: USA | H3: Bronze
A4: CUST1264 | B4: Matthew Payne | C4: 25 | D4: Male | E4: Grahamfurt | F4: Wyoming | G4: USA | H4: Gold
A5: CUST1409 | B5: Sarah Smith | C5: 55 | D5: Male | E5: Kathleenport | F5: Wyoming | G5: USA | H5: Gold
A6: CUST1444 | B6: Cheryl Carr | C6: 19 | D6: Male | E6: Jessicaland | F6: Wyoming | G6: USA | H6: Gold
A7: CUST1283 | B7: Bryan Garcia | C7: 54 | D7: Female | E7: Garciaborough | F7: Wyoming | G7: USA | H7: Silver
A8: CUST1148 | B8: Theresa Campbell | C8: 42 | D8: Female | E8: New Brian | F8: Wisconsin | G8: USA | H8: Bronze
A9: CUST1253 | B9: Dr. Ashley Yates Md | C9: 32 | D9: Male | E9: New Maria | F9: Wisconsin | G9: USA | H9: Bronze
A10: CUST1325 | B10: Andrew Smith | C10: 60 | D10: Male | E10: East Matthew | F10: Wisconsin | G10: USA | H10: Bronze
A11: CUST1473 | B11: Laura Mathews | C11: 53 | D11: Male | E11: Chambersfurt | F11: Wisconsin | G11: USA | H11: Bronze | J11: mode | K11: =INDEX(Table1[Loyalty_Level],_xlfn.MODE.MULT(MATCH(Table1[Loyalty_Level],Table1[Loyalty_Level],0))) -> Platinum
A12: CUST1406 | B12: David Lozano | C12: 23 | D12: Female | E12: North Michaelfurt | F12: Wisconsin | G12: USA | H12: Gold
A13: CUST1089 | B13: Jamie Yoder | C13: 43 | D13: Male | E13: New Gabrielleville | F13: Wisconsin | G13: USA | H13: Platinum
A14: CUST1416 | B14: Jennifer Myers | C14: 46 | D14: Male | E14: Marthaborough | F14: Wisconsin | G14: USA | H14: Platinum
A15: CUST1352 | B15: Michael Greene | C15: 52 | D15: Female | E15: Port Saramouth | F15: Wisconsin | G15: USA | H15: Silver
A16: CUST1441 | B16: Dalton Walters | C16: 31 | D16: Male | E16: Jonesstad | F16: Wisconsin | G16: USA | H16: Silver
A17: CUST1007 | B17: Daniel Boyd | C17: 29 | D17: Female | E17: West Pamelafurt | F17: West Virginia | G17: USA | H17: Bronze
A18: CUST1172 | B18: Thomas Rhodes | C18: 41 | D18: Female | E18: Port Richard | F18: West Virginia | G18: USA | H18: Bronze
A19: CUST1296 | B19: Jared Moran | C19: 28 | D19: Female | E19: South David | F19: West Virginia | G19: USA | H19: Bronze
A20: CUST1479 | B20: Dylan Gutierrez | C20: 40 | D20: Male | E20: New Jamesview | F20: West Virginia | G20: USA | H20: Bronze
A21: CUST1051 | B21: Sarah Rodgers | C21: 23 | D21: Female | E21: New Julia | F21: West Virginia | G21: USA | H21: Gold
A22: CUST1238 | B22: Steven Smith | C22: 40 | D22: Male | E22: Port Krista | F22: West Virginia | G22: USA | H22: Platinum
A23: CUST1073 | B23: Christopher Brown | C23: 56 | D23: Female | E23: Sandrastad | F23: West Virginia | G23: USA | H23: Silver
... A501: CUST1493 | B501: Amanda Powell | C501: 28 | D501: Male | E501: South William | F501: Alabama | G501: USA | H501: Silver

Sheet Product_Dim (2)
A1: Product_ID | B1: Product_Name | C1: Category | D1: Sub_Category | E1: Brand | F1: Cost | G1: Stock
A2: PROD0 | B2: Brother Laser Printer | C2: Electronics | D2: Computer | E2: Hunt Inc | F2: 112.42 | G2: 416
A3: PROD1 | B3: Men's Graphic T-Shirt | C3: Clothing | D3: Tops | E3: Terry-Moore | F3: 342.56 | G3: 181
A4: PROD2 | B4: Women's Casual Hoodie | C4: Clothing | D4: Outerwear | E4: Sims Inc | F4: 265.73267 | G4: 352
A5: PROD3 | B5: Men's Running Jacket | C5: Clothing | D5: Outerwear | E5: Pineda Ltd | F5: 364.67 | G5: 452
A6: PROD4 | B6: Women's Yoga Pants | C6: Clothing | D6: Bottoms | E6: Gonzales-Davis | F6: 306.46 | G6: 487 | J6: =AVERAGEIF(Table24[Category],"Home",Table24[Stock]) -> 226.05
A7: PROD5 | B7: Men's Leather Belt | C7: Clothing | D7: Accessories | E7: Baldwin, Garza and Gonzalez | F7: 261 | G7: 59
A8: PROD6 | B8: Herbal Face Moisturizer | C8: Beauty | D8: Skincare | E8: Davidson PLC | F8: 312.8 | G8: 350
A9: PROD7 | B9: LED Table Lamp | C9: Home | D9: Lighting | E9: Harrell LLC | F9: 218.86 | G9: 170 | I9: =AVERAGEIF(Table24[Category],"Beauty",F2:F101) -> 250.41615
A10: PROD8 | B10: Wireless Bluetooth Earbuds | C10: Electronics | D10: Audio | E10: Perez-Johnston | F10: 439.07 | G10: 142
A11: PROD9 | B11: Adjustable Dumbbell Set | C11: Sports | D11: Fitness | E11: Hill PLC | F11: 495.72 | G11: 323
A12: PROD10 | B12: Ceramic Kitchen Bowl Set | C12: Home | D12: Kitchen | E12: Hamilton Group | F12: 298.86 | G12: 308
A13: PROD11 | B13: HD Smart TV Stick | C13: Electronics | D13: Accessories | E13: Gibson, Hobbs and Weaver | F13: 449.4 | G13: 274.7
A14: PROD12 | B14: Hair Strengthening Shampoo | C14: Beauty | D14: Haircare | E14: Rice LLC | F14: 115.82 | G14: 460
A15: PROD13 | B15: USB-C Fast Charger | C15: Electronics | D15: Accessories | E15: Dawson-Perkins | F15: 242.23 | G15: 453
A16: PROD14 | B16: Decorative Wall Mirror | C16: Home | D16: Decor | E16: Luna, Anderson and Bowman | F16: 48.01 | G16: 439
A17: PROD15 | B17: 4K Home Projector | C17: Electronics | D17: Appliances | E17: Thomas LLC | F17: 465.34 | G17: 301
A18: PROD16 | B18: Beard Grooming Kit | C18: Beauty | D18: Grooming | E18: Erickson-Green | F18: 337.42 | G18: 256
A19: PROD17 | B19: Soccer Training Cone Set | C19: Sports | D19: Accessories | E19: Ford, Murphy and Wilson | F19: 144.53 | G19: 367
A20: PROD18 | B20: Women's Denim Jeans | C20: Clothing | D20: Bottoms | E20: Guerra-Hendrix | F20: 265.73267 | G20: 343
A21: PROD19 | B21: Knee Support Brace | C21: Sports | D21: Equipment | E21: May-Reese | F21: 21.34 | G21: 65
A22: PROD20 | B22: Outdoor Sports Water Bottle | C22: Sports | D22: Accessories | E22: Soto-Ellis | F22: 131.51 | G22: =AVERAGEIF(Table24[Category],"Sports",Table24[Stock]) -> 281.95833
A23: PROD21 | B23: Multi-Purpose Storage Box | C23: Home | D23: Storage | E23: Gardner-Montes | F23: 123.46 | G23: 76
A24: PROD22 | B24: Carbon Fiber Tennis Racket | C24: Sports | D24: Equipment | E24: Flores, Pineda and Rodriguez | F24: 484.62 | G24: 432
A25: PROD23 | B25: Men's Formal Shirt | C25: Clothing | D25: Tops | E25: Moon, Mora and Santos | F25: 265.73267 | G25: 360
A26: PROD24 | B26: Foldable Camping Chair | C26: Sports | D26: Outdoor | E26: Cook Ltd | F26: 166.06 | G26: 340
A27: PROD25 | B27: Women's Scarf Set | C27: Clothing | D27: Accessories | E27: Brown and Sons | F27: 174.02 | G27: 268
A28: PROD26 | B28: Wireless Bluetooth Speaker | C28: Electronics | D28: Audio | E28: Reed-Schmidt | F28: 322.41 | G28: 213
A29: PROD27 | B29: Decorative Floor Vase | C29: Home | D29: Decor | E29: Khan, Jones and Paul | F29: 234.806 | G29: 378
A30: PROD28 | B30: Sports Stopwatch Timer | C30: Sports | D30: Accessories | E30: Burns-Hansen | F30: 38.76 | G30: 137
A31: PROD29 | B31: Fabric Sofa Throw Blanket | C31: Home | D31: Decor | E31: Hoffman Group | F31: 218.48 | G31: 276
A32: PROD30 | B32: Stainless Steel Cutlery Set | C32: Home | D32: Kitchen | E32: Stevens, Fernandez and Martin | F32: 19.52 | G32: 57
A33: PROD31 | B33: Basketball | C33: Sports | D33: Team Sports | E33: Nolan-Snow | F33: 204.39 | G33: 281
A34: PROD32 | B34: Vitamin C Face Serum | C34: Beauty | D34: Skincare | E34: Griffin Ltd | F34: 283.83 | G34: 244
... A56: PROD54 | B56: Sports Stopwatch Pro | C56: Sports | D56: Accessories | E56: Thompson-French | F56: 434.84 | G56: 185
A57: PROD55 | B57: Ceramic Plant Pot | C57: Home | D57: Decor | E57: Hatfield, Baird and Torres | F57: 81.75 | G57: =AVERAGEIF(Table24[Category],"Home",Table24[Stock]) -> 226.05
A58: PROD56 | B58: Premium Blanket Throw | C58: Home | D58: Decor | E58: Hernandez, Kennedy and Porter | F58: 461.47 | G58: 190
A59: PROD57 | B59: Foam Roller | C59: Sports | D59: Fitness | E59: Atkinson, Camacho and Oliver | F59: 30.62 | G59: 138
A60: PROD58 | B60: Womens Cotton Scarf | C60: Clothing | D60: Accessories | E60: Shepherd-Gould | F60: 113.83 | G60: 485
A61: PROD59 | B61: Men's Hair Styling Gel | C61: Beauty | D61: Haircare | E61: Cline-Mccarthy | F61: 17.31 | G61: 399
A62: PROD60 | B62: Luxury Perfume Spray | C62: Beauty | D62: Fragrance | E62: Gibson, Green and Lopez | F62: 482.75 | G62: 444
A63: PROD61 | B63: Tennis Ball 3-Pack | C63: Sports | D63: Equipment | E63: Lopez LLC | F63: 103.45 | G63: 465
A64: PROD62 | B64: Laptop Cooling Pad | C64: Electronics | D64: Computer | E64: Murray, Gould and Ware | F64: 86.42 | G64: 222
A65: PROD63 | B65: Organic Sunscreen Lotion | C65: Beauty | D65: Skincare | E65: Anderson-Riley | F65: 266.86 | G65: 458
A66: PROD64 | B66: Matte Lipstick Set | C66: Beauty | D66: Makeup | E66: Zhang Inc | F66: 299.11 | G66: 118
A67: PROD65 | B67: Adjustable Dumbbells 20kg | C67: Sports | D67: Fitness | E67: Montgomery, Benton and Miller | F67: 240.63 | G67: 423
A68: PROD66 | B68: Women's Hair Dryer Brush | C68: Beauty | D68: Haircare | E68: Torres, Spencer and Potter | F68: 340.39 | G68: 177
A69: PROD67 | B69: Smart LED Light Strip | C69: Electronics | D69: Accessories | E69: Flores-Davis | F69: 349.17 | G69: 476
... A101: PROD99 | B101: Stainless Steel Cookware Set | C101: Home | D101: Kitchen | E101: Campbell Ltd | F101: 201.41 | G101: 146

Sheet Product_Dim
A1: Product_ID | B1: Product_Name | C1: Category | D1: Sub_Category | E1: Brand | F1: Cost | G1: Stock
A2: PROD0 | B2: Brother Laser Printer | C2: Electronics | D2: Computer | E2: Hunt Inc | F2: 112.42 | G2: 416
A3: PROD1 | B3: Men's Graphic T-Shirt | C3: Clothing | D3: Tops | E3: Terry-Moore | F3: 342.56 | G3: 181
A4: PROD2 | B4: Women's Casual Hoodie | C4: Clothing | D4: Outerwear | E4: Sims Inc | G4: 352
A5: PROD3 | B5: Men's Running Jacket | C5: Clothing | D5: Outerwear | E5: Pineda Ltd | F5: 364.67 | G5: 452
A6: PROD4 | B6: Women's Yoga Pants | C6: Clothing | D6: Bottoms | E6: Gonzales-Davis | F6: 306.46 | G6: 487
A7: PROD5 | B7: Men's Leather Belt | C7: Clothing | D7: Accessories | E7: Baldwin, Garza and Gonzalez | F7: 261 | G7: 59
A8: PROD6 | B8: Herbal Face Moisturizer | C8: Beauty | D8: Skincare | E8: Davidson PLC | F8: 312.8 | G8: 350
A9: PROD7 | B9: LED Table Lamp | C9: Home | D9: Lighting | E9: Harrell LLC | F9: 218.86 | G9: 170
A10: PROD8 | B10: Wireless Bluetooth Earbuds | C10: Electronics | D10: Audio | E10: Perez-Johnston | F10: 439.07 | G10: 142
A11: PROD9 | B11: Adjustable Dumbbell Set | C11: Sports | D11: Fitness | E11: Hill PLC | F11: 495.72 | G11: 323
A12: PROD10 | B12: Ceramic Kitchen Bowl Set | C12: Home | D12: Kitchen | E12: Hamilton Group | F12: 298.86 | G12: 308
A13: PROD11 | B13: HD Smart TV Stick | C13: Electronics | D13: Accessories | E13: Gibson, Hobbs and Weaver | F13: 449.4
A14: PROD12 | B14: Hair Strengthening Shampoo | C14: Beauty | D14: Haircare | E14: Rice LLC | F14: 115.82 | G14: 460
A15: PROD13 | B15: USB-C Fast Charger | C15: Electronics | D15: Accessories | E15: Dawson-Perkins | F15: 242.23 | G15: 453
A16: PROD14 | B16: Decorative Wall Mirror | C16: Home | D16: Decor | E16: Luna, Anderson and Bowman | F16: 48.01 | G16: 439
A17: PROD15 | B17: 4K Home Projector | C17: Electronics | D17: Appliances | E17: Thomas LLC | F17: 465.34 | G17: 301
A18: PROD16 | B18: Beard Grooming Kit | C18: Beauty | D18: Grooming | E18: Erickson-Green | F18: 337.42 | G18: 256
A19: PROD17 | B19: Soccer Training Cone Set | C19: Sports | D19: Accessories | E19: Ford, Murphy and Wilson | F19: 144.53 | G19: 367
A20: PROD18 | B20: Women's Denim Jeans | C20: Clothing | D20: Bottoms | E20: Guerra-Hendrix | G20: 343
A21: PROD19 | B21: Knee Support Brace | C21: Sports | D21: Equipment | E21: May-Reese | F21: 21.34 | G21: 65
A22: PROD20 | B22: Outdoor Sports Water Bottle | C22: Sports | D22: Accessories | E22: Soto-Ellis | F22: 131.51
A23: PROD21 | B23: Multi-Purpose Storage Box | C23: Home | D23: Storage | E23: Gardner-Montes | F23: 123.46 | G23: 76
A24: PROD22 | B24: Carbon Fiber Tennis Racket | C24: Sports | D24: Equipment | E24: Flores, Pineda and Rodriguez | F24: 484.62 | G24: 432
A25: PROD23 | B25: Men's Formal Shirt | C25: Clothing | D25: Tops | E25: Moon, Mora and Santos | G25: 360
A26: PROD24 | B26: Foldable Camping Chair | C26: Sports | D26: Outdoor | E26: Cook Ltd | F26: 166.06 | G26: 340
A27: PROD25 | B27: Women's Scarf Set | C27: Clothing | D27: Accessories | E27: Brown and Sons | F27: 174.02 | G27: 268
A28: PROD26 | B28: Wireless Bluetooth Speaker | C28: Electronics | D28: Audio | E28: Reed-Schmidt | F28: 322.41 | G28: 213
A29: PROD27 | B29: Decorative Floor Vase | C29: Home | D29: Decor | E29: Khan, Jones and Paul | G29: 378
A30: PROD28 | B30: Sports Stopwatch Timer | C30: Sports | D30: Accessories | E30: Burns-Hansen | F30: 38.76 | G30: 137
A31: PROD29 | B31: Fabric Sofa Throw Blanket | C31: Home | D31: Decor | E31: Hoffman Group | F31: 218.48 | G31: 276
A32: PROD30 | B32: Stainless Steel Cutlery Set | C32: Home | D32: Kitchen | E32: Stevens, Fernandez and Martin | F32: 19.52 | G32: 57
A33: PROD31 | B33: Basketball | C33: Sports | D33: Team Sports | E33: Nolan-Snow | F33: 204.39 | G33: 281
A34: PROD32 | B34: Vitamin C Face Serum | C34: Beauty | D34: Skincare | E34: Griffin Ltd | F34: 283.83 | G34: 244
A35: PROD33 | B35: Modern Wall Clock | C35: Home | D35: Decor | E35: Weiss-Watson | F35: 179.77 | G35: 305
A36: PROD34 | B36: Gaming Mechanical Keyboard | C36: Electronics | D36: Computer | E36: Lucero LLC | F36: 419.28 | G36: 86
A37: PROD35 | B37: Bedroom Table Lamp | C37: Home | D37: Lighting | E37: Jones LLC | F37: 382.22 | G37: 329
A38: PROD36 | B38: Women's Summer Dress | C38: Clothing | D38: Tops | E38: Smith-Mills | F38: 223.43 | G38: 154
A39: PROD37 | B39: Men's Casual Sneakers | C39: Clothing | D39: Footwear | E39: Hogan-Lee | F39: 353.47 | G39: 214
A40: PROD38 | B40: Sports Water Hydration Pack | C40: Sports | D40: Outdoor | E40: Sims-Smith | F40: 135.61 | G40: 394
A41: PROD39 | B41: Portable Power Bank | C41: Electronics | D41: Mobile | E41: Cummings and Sons | F41: 326.06 | G41: 301
... A48: PROD46 | B48: Men's Winter Jacket | C48: Clothing | D48: Outerwear | E48: Kelly, Smith and Perez | F48: 167.34 | G48: 296
A49: PROD47 | B49: Makeup Brush Set | C49: Beauty | D49: Makeup | E49: Cook Inc | G49: 431
A50: PROD48 | B50: Car Dashboard Phone Holder | C50: Electronics | D50: Accessories | E50: Byrd, Stewart and Valdez | F50: 177.98 | G50: 103
A51: PROD49 | B51: Men's Roll-On Perfume | C51: Beauty | D51: Fragrance | E51: Sullivan and Sons | F51: 43.29 | G51: 267
A52: PROD50 | B52: Boxing Hand Wraps | C52: Sports | D52: Fitness | E52: Smith-King | F52: 190.29 | G52: 260
A53: PROD51 | B53: HDMI Cable – 2m | C53: Electronics | D53: Accessories | E53: Bautista, Green and Hale | F53: 88.49 | G53: 246
A54: PROD52 | B54: Rugby Ball | C54: Sports | D54: Team Sports | E54: Harris Inc | F54: 212.26 | G54: 82
A55: PROD53 | B55: Men's Track Pants | C55: Clothing | D55: Bottoms | E55: Hamilton, Woods and Walker | F55: 386.56 | G55: 125
A56: PROD54 | B56: Sports Stopwatch Pro | C56: Sports | D56: Accessories | E56: Thompson-French | F56: 434.84 | G56: 185
A57: PROD55 | B57: Ceramic Plant Pot | C57: Home | D57: Decor | E57: Hatfield, Baird and Torres | F57: 81.75
A58: PROD56 | B58: Premium Blanket Throw | C58: Home | D58: Decor | E58: Hernandez, Kennedy and Porter | F58: 461.47 | G58: 190
A59: PROD57 | B59: Foam Roller | C59: Sports | D59: Fitness | E59: Atkinson, Camacho and Oliver | F59: 30.62 | G59: 138
A60: PROD58 | B60: Womens Cotton Scarf | C60: Clothing | D60: Accessories | E60: Shepherd-Gould | F60: 113.83 | G60: 485
A61: PROD59 | B61: Men's Hair Styling Gel | C61: Beauty | D61: Haircare | E61: Cline-Mccarthy | F61: 17.31 | G61: 399
A62: PROD60 | B62: Luxury Perfume Spray | C62: Beauty | D62: Fragrance | E62: Gibson, Green and Lopez | F62: 482.75 | G62: 444
A63: PROD61 | B63: Tennis Ball 3-Pack | C63: Sports | D63: Equipment | E63: Lopez LLC | F63: 103.45 | G63: 465
A64: PROD62 | B64: Laptop Cooling Pad | C64: Electronics | D64: Computer | E64: Murray, Gould and Ware | F64: 86.42 | G64: 222
A65: PROD63 | B65: Organic Sunscreen Lotion | C65: Beauty | D65: Skincare | E65: Anderson-Riley | F65: 266.86 | G65: 458
A66: PROD64 | B66: Matte Lipstick Set | C66: Beauty | D66: Makeup | E66: Zhang Inc | F66: 299.11 | G66: 118
A67: PROD65 | B67: Adjustable Dumbbells 20kg | C67: Sports | D67: Fitness | E67: Montgomery, Benton and Miller | F67: 240.63 | G67: 423
A68: PROD66 | B68: Women's Hair Dryer Brush | C68: Beauty | D68: Haircare | E68: Torres, Spencer and Potter | F68: 340.39 | G68: 177
A69: PROD67 | B69: Smart LED Light Strip | C69: Electronics | D69: Accessories | E69: Flores-Davis | F69: 349.17 | G69: 476
... A84: PROD82 | B84: Fitness Resistance Bands | C84: Sports | D84: Fitness | E84: Reese-Watson | F84: 152.92 | G84: 281
A85: PROD83 | B85: Hydrating Face Cleanser | C85: Beauty | D85: Skincare | E85: Butler Group | G85: 159
A86: PROD84 | B86: Wooden Bookshelf | C86: Home | D86: Furniture | E86: Collins-Stephenson | F86: 388.46 | G86: 208
A87: PROD85 | B87: Women's Beanie Hat | C87: Clothing | D87: Accessories | E87: Richardson-Carrillo | F87: 119.57 | G87: 210
A88: PROD86 | B88: Kitchen Cutting Board | C88: Home | D88: Kitchen | E88: Taylor, Dodson and Johnston | F88: 176.07 | G88: 82
A89: PROD87 | B89: LED Bedside Lamp | C89: Home | D89: Lighting | E89: Aguilar, Horton and Lewis | F89: 371.38 | G89: 220
A90: PROD88 | B90: Sports Wrist Sweatbands | C90: Sports | D90: Accessories | E90: Olsen-Daniels | F90: 131.24 | G90: 232
A91: PROD89 | B91: Face Foundation Kit | C91: Beauty | D91: Makeup | E91: Taylor-Elliott | F91: 183.04 | G91: 457
A92: PROD90 | B92: Gaming Mouse Pad XL | C92: Electronics | D92: Accessories | E92: Sharp, Taylor and Rodriguez | F92: 340.14 | G92: 361
A93: PROD91 | B93: Women's High Heels | C93: Clothing | D93: Footwear | E93: Smith-Charles | F93: 438.25 | G93: 496
A94: PROD92 | B94: Microwave Oven | C94: Home | D94: Appliances | E94: Green, Powell and Palmer | F94: 447.43 | G94: 191
A95: PROD93 | B95: USB-C Laptop Charger | C95: Electronics | D95: Computer | E95: Martin LLC | F95: 377.52 | G95: 485
A96: PROD94 | B96: Vitamin E Body Lotion | C96: Beauty | D96: Skincare | E96: Hoffman-Williams | F96: 358.47 | G96: 213
A97: PROD95 | B97: Sports Stopwatch Basic | C97: Sports | D97: Accessories | E97: Wilson Group | F97: 60.65 | G97: 75
... A101: PROD99 | B101: Stainless Steel Cookware Set | C101: Home | D101: Kitchen | E101: Campbell Ltd | F101: 201.41 | G101: 146

Sheet Store_Dim (2)
A1: Store_ID | B1: Store_Name | C1: Region | D1: City | E1: Store_Type
A2: STORE0 | B2: Rivera-Warner | C2: East | D2: Washingtonfurt | E2: Flagship
A3: STORE1 | B3: Martinez, Adkins and Johnson | C3: North | D3: Danielmouth | E3: Flagship
A4: STORE2 | B4: Black-Horn | C4: South | D4: North Nancyview | E4: Outlet
A5: STORE3 | B5: Johnson-Wright | C5: North | D5: Hoodberg | E5: Outlet
A6: STORE4 | B6: Alexander Group | C6: South | D6: Port Sharon | E6: Online
A7: STORE5 | B7: Gray Ltd | C7: North | D7: New Michaelchester | E7: Outlet
A8: STORE6 | B8: Benson-Elliott | C8: East | D8: Port Josephberg | E8: Online
A9: STORE7 | B9: Martinez-Mullins | C9: South | D9: Williamsfurt | E9: Online
A10: STORE8 | B10: Bean, Jones and Park | C10: West | D10: Thompsonborough | E10: Online
A11: STORE9 | B11: Moore, Padilla and Butler | C11: South | D11: East Johnstad | E11: Flagship
A12: STORE10 | B12: Hill, Wagner and Ballard | C12: East | D12: East Davidville | E12: Online
... A21: STORE19 | B21: Mann-Austin | C21: East | D21: Vasquezborough | E21: Online

Sheet Store_Dim
A1: Store_ID | B1: Store_Name | C1: Region | D1: City | E1: Store_Type
A2: STORE0 | B2: Rivera-Warner | C2: East | D2: Washingtonfurt | E2: Flagship
A3: STORE1 | B3: Martinez, Adkins and Johnson | C3: North | D3: Danielmouth | E3: Flagship
A4: STORE2 | B4: Black-Horn | C4: South | D4: North Nancyview | E4: Outlet
A5: STORE3 | B5: Johnson-Wright | C5: North | D5: Hoodberg | E5: Outlet
A6: STORE4 | B6: Alexander Group | C6: South | D6: Port Sharon | E6: Online
A7: STORE5 | B7: Gray Ltd | C7: North | D7: New Michaelchester | E7: Outlet
A8: STORE6 | B8: Benson-Elliott | C8: East | D8: Port Josephberg | E8: Online
A9: STORE7 | B9: Martinez-Mullins | C9: South | D9: Williamsfurt | E9: Online
A10: STORE8 | B10: Bean, Jones and Park | C10: West | D10: Thompsonborough | E10: Online
A11: STORE9 | B11: Moore, Padilla and Butler | C11: South | D11: East Johnstad | E11: Flagship
A12: STORE10 | B12: Hill, Wagner and Ballard | C12: East | D12: East Davidville | E12: Online
... A21: STORE19 | B21: Mann-Austin | C21: East | D21: Vasquezborough | E21: Online

Sheet Sales_Fact
A1: Sales_ID | B1: Order_Date | C1: Customer_ID | D1: Product_ID | E1: Store_ID | F1: Quantity | G1: Unit_Price | H1: Discount | I1: Payment_Type | J1: Total_Amount
A2: SALE0 | B2: 45480 | C2: CUST1409 | D2: PROD97 | E2: STORE3 | F2: 1 | G2: 218.04 | H2: 0.09 | I2: Credit Card | J2: 198.4164
A3: SALE1 | B3: 45285 | C3: CUST1467 | D3: PROD74 | E3: STORE17 | F3: 3 | G3: 104.47 | H3: 0.27 | I3: PayPal | J3: 228.7893
A4: SALE2 | B4: 45446 | C4: CUST1056 | D4: PROD49 | E4: STORE8 | F4: 4 | G4: 914.05 | H4: 0.25 | I4: Credit Card | J4: 2742.15
A5: SALE3 | B5: 45259 | C5: CUST1346 | D5: PROD76 | E5: STORE8 | F5: 1 | G5: 921.51 | H5: 0.16 | I5: COD | J5: 774.0684
A6: SALE4 | B6: 45297 | C6: CUST1493 | D6: PROD59 | E6: STORE5 | F6: 3 | G6: 745.3 | H6: 0.18 | I6: Credit Card | J6: 1833.438
A7: SALE5 | B7: 45499 | C7: CUST1116 | D7: PROD15 | E7: STORE7 | F7: 3 | G7: 147.01 | H7: 0.19 | I7: COD | J7: 357.2343
A8: SALE6 | B8: 45850 | C8: CUST1016 | D8: PROD56 | E8: STORE4 | F8: 2 | G8: 785.31 | H8: 0.15 | I8: PayPal | J8: 1335.027
A9: SALE7 | B9: 45248 | C9: CUST1152 | D9: PROD70 | E9: STORE8 | F9: 4 | G9: 342.39 | H9: 0.23 | I9: PayPal | J9: 1054.5612
A10: SALE8 | B10: 45781 | C10: CUST1187 | D10: PROD99 | E10: STORE5 | G10: 448.25 | H10: 0.07 | I10: PayPal | J10: 1250.6175
A11: SALE9 | B11: 45869 | C11: CUST1464 | D11: PROD33 | E11: STORE0 | F11: 2 | G11: 873.17 | H11: 0.23 | I11: PayPal | J11: 1344.6818
A12: SALE10 | B12: 45335 | C12: CUST1065 | D12: PROD24 | E12: STORE14 | F12: 1 | G12: 278.63 | H12: 0.07 | I12: Credit Card | J12: 259.1259
A13: SALE11 | B13: 45801 | C13: CUST1320 | D13: PROD39 | E13: STORE1 | F13: 4 | G13: 286.92 | H13: 0.17 | I13: Credit Card | J13: 952.5744
A14: SALE12 | B14: 45528 | C14: CUST1237 | D14: PROD88 | E14: STORE4 | F14: 4 | G14: 644.58 | H14: 0.01 | I14: Credit Card | J14: 2552.5368
A15: SALE13 | B15: 45875 | C15: CUST1443 | D15: PROD34 | E15: STORE16 | F15: 2 | G15: 316.9 | H15: 0.3 | I15: PayPal | J15: 443.66
A16: SALE14 | B16: 45829 | C16: CUST1348 | D16: PROD24 | E16: STORE15 | F16: 4 | G16: 403.47 | H16: 0.29 | I16: PayPal | J16: 1145.8548
A17: SALE15 | B17: 45636 | C17: CUST1435 | D17: PROD36 | E17: STORE9 | G17: 871.34 | H17: 0.04 | I17: COD | J17: 2509.4592
A18: SALE16 | B18: 45913 | C18: CUST1276 | D18: PROD65 | E18: STORE19 | F18: 2 | G18: 451.98 | H18: 0.25 | I18: Credit Card | J18: 677.97
A19: SALE17 | B19: 45637 | C19: CUST1079 | D19: PROD27 | E19: STORE4 | F19: 2 | G19: 502.69 | H19: 0.23 | I19: Credit Card | J19: 774.1426
A20: SALE18 | B20: 45517 | C20: CUST1094 | D20: PROD39 | E20: STORE4 | F20: 2 | G20: 559.23 | H20: 0.25 | I20: COD | J20: 838.845
A21: SALE19 | B21: 45369 | C21: CUST1239 | D21: PROD60 | E21: STORE13 | F21: 4 | H21: 0.04 | I21: COD | J21: 1782.4512
A22: SALE20 | B22: 45843 | C22: CUST1144 | D22: PROD72 | E22: STORE17 | F22: 3 | G22: 986.04 | H22: 0.27 | I22: COD | J22: 2159.4276
A23: SALE21 | B23: 45447 | C23: CUST1396 | D23: PROD43 | E23: STORE18 | F23: 1 | G23: 589.56 | H23: 0.22 | I23: Credit Card | J23: 459.8568
A24: SALE22 | B24: 45394 | C24: CUST1476 | D24: PROD69 | E24: STORE10 | F24: 3 | G24: 979.42 | H24: 0.03 | I24: PayPal | J24: 2850.1122
A25: SALE23 | B25: 45466 | C25: CUST1368 | D25: PROD12 | E25: STORE8 | F25: 1 | G25: 719.28 | H25: 0.08 | I25: Credit Card | J25: 661.7376
A26: SALE24 | B26: 45908 | C26: CUST1186 | D26: PROD67 | E26: STORE6 | F26: 3 | G26: 77.6 | H26: 0.07 | I26: Credit Card | J26: 216.504
A27: SALE25 | B27: 45552 | C27: CUST1381 | D27: PROD5 | E27: STORE3 | F27: 4 | G27: 852.71 | H27: 0.14 | I27: PayPal | J27: 2933.3224
A28: SALE26 | B28: 45294 | C28: CUST1213 | D28: PROD98 | E28: STORE8 | F28: 4 | G28: 156.16 | I28: Credit Card | J28: 599.6544
A29: SALE27 | B29: 45710 | C29: CUST1200 | D29: PROD77 | E29: STORE8 | F29: 3 | G29: 815.49 | H29: 0.17 | I29: Credit Card | J29: 2030.5701
A30: SALE28 | B30: 45923 | C30: CUST1148 | D30: PROD13 | E30: STORE2 | F30: 2 | G30: 74.21 | H30: 0.11 | I30: PayPal | J30: 132.0938
A31: SALE29 | B31: 45302 | C31: CUST1348 | D31: PROD99 | E31: STORE3 | G31: 451.67 | H31: 0.15 | I31: Credit Card | J31: 1535.678
A32: SALE30 | B32: 45217 | C32: CUST1028 | D32: PROD5 | E32: STORE19 | F32: 1 | G32: 429.38 | H32: 0.13 | I32: PayPal | J32: 373.5606
A33: SALE31 | B33: 45593 | C33: CUST1412 | D33: PROD53 | E33: STORE12 | F33: 2 | G33: 148.96 | H33: 0.03 | I33: COD | J33: 288.9824
A34: SALE32 | B34: 45597 | C34: CUST1398 | D34: PROD75 | E34: STORE8 | F34: 4 | G34: 313.83 | H34: 0.08 | I34: Credit Card | J34: 1154.8944
A35: SALE33 | B35: 45620 | C35: CUST1453 | D35: PROD12 | E35: STORE6 | F35: 2 | G35: 717.31 | H35: 0.15 | I35: Credit Card | J35: 1219.427
A36: SALE34 | B36: 45215 | C36: CUST1344 | D36: PROD79 | E36: STORE1 | G36: 873.22 | H36: 0.18 | I36: Credit Card | J36: 2148.1212
A37: SALE35 | B37: 45878 | C37: CUST1218 | D37: PROD16 | E37: STORE3 | F37: 4 | G37: 109.36 | H37: 0.19 | I37: COD | J37: 354.3264
A38: SALE36 | B38: 45635 | C38: CUST1086 | D38: PROD5 | E38: STORE7 | F38: 3 | G38: 559.52 | H38: 0.16 | I38: PayPal | J38: 1409.9904
A39: SALE37 | B39: 45329 | C39: CUST1492 | D39: PROD10 | E39: STORE17 | F39: 3 | G39: 121.76 | H39: 0.27 | I39: PayPal | J39: 266.6544
A40: SALE38 | B40: 45378 | C40: CUST1189 | D40: PROD33 | E40: STORE13 | F40: 4 | G40: 735.32 | H40: 0.06 | I40: COD | J40: 2764.8032
A41: SALE39 | B41: 45264 | C41: CUST1431 | D41: PROD94 | E41: STORE3 | F41: 2 | G41: 600.73 | H41: 0.08 | I41: Credit Card | J41: 1105.3432
A42: SALE40 | B42: 45486 | C42: CUST1072 | D42: PROD26 | E42: STORE19 | F42: 2 | G42: 873.86 | H42: 0.07 | I42: COD | J42: 1625.3796
A43: SALE41 | B43: 45241 | C43: CUST1302 | D43: PROD23 | E43: STORE8 | F43: 3 | G43: 342.47 | H43: 0.08 | I43: PayPal | J43: 945.2172
A44: SALE42 | B44: 45649 | C44: CUST1335 | D44: PROD29 | E44: STORE9 | F44: 2 | G44: 915.15 | H44: 0.16 | I44: PayPal | J44: 1537.452
A45: SALE43 | B45: 45677 | C45: CUST1084 | D45: PROD33 | E45: STORE17 | G45: 863.11 | H45: 0.28 | I45: PayPal | J45: 1864.3176
A46: SALE44 | B46: 45538 | C46: CUST1203 | D46: PROD43 | E46: STORE12 | F46: 2 | G46: 209.32 | H46: 0.23 | I46: COD | J46: 322.3528
A47: SALE45 | B47: 45606 | C47: CUST1470 | D47: PROD59 | E47: STORE8 | F47: 4 | G47: 288.6 | H47: 0.09 | I47: PayPal | J47: 1050.504
A48: SALE46 | B48: 45570 | C48: CUST1070 | D48: PROD78 | E48: STORE16 | F48: 1 | G48: 418.69 | H48: 0.06 | I48: PayPal | J48: 393.5686
A49: SALE47 | B49: 45466 | C49: CUST1008 | D49: PROD30 | E49: STORE11 | F49: 1 | G49: 135.78 | H49: 0.14 | I49: PayPal | J49: 116.7708
A50: SALE48 | B50: 45218 | C50: CUST1203 | D50: PROD44 | E50: STORE17 | F50: 1 | G50: 517.13 | H50: 0.28 | I50: Credit Card | J50: 372.3336
A51: SALE49 | B51: 45607 | C51: CUST1420 | D51: PROD21 | E51: STORE16 | F51: 2 | G51: 384.66 | H51: 0.08 | I51: COD | J51: 707.7744
A52: SALE50 | B52: 45291 | C52: CUST1070 | D52: PROD52 | E52: STORE9 | F52: 3 | G52: 83.7 | H52: 0.24 | I52: PayPal | J52: 190.836
A53: SALE51 | B53: 45689 | C53: CUST1142 | D53: PROD69 | E53: STORE7 | F53: 3 | G53: 76.57 | H53: 0.26 | I53: Credit Card | J53: 169.9854
A54: SALE52 | B54: 45894 | C54: CUST1148 | D54: PROD89 | E54: STORE6 | F54: 3 | I54: Credit Card | J54: 486.0633
A55: SALE53 | B55: 45677 | C55: CUST1324 | D55: PROD20 | E55: STORE8 | F55: 1 | G55: 900.35 | H55: 0.13 | I55: COD | J55: 783.3045
A56: SALE54 | B56: 45706 | C56: CUST1095 | D56: PROD40 | E56: STORE10 | F56: 4 | G56: 428.09 | H56: 0.07 | I56: Credit Card | J56: 1592.4948
A57: SALE55 | B57: 45589 | C57: CUST1416 | D57: PROD49 | E57: STORE11 | F57: 2 | G57: 559.71 | H57: 0.3 | I57: COD | J57: 783.594
A58: SALE56 | B58: 45282 | C58: CUST1080 | D58: PROD34 | E58: STORE6 | F58: 2 | G58: 833.7 | H58: 0.06 | I58: PayPal | J58: 1567.356
A59: SALE57 | B59: 45462 | C59: CUST1467 | D59: PROD47 | E59: STORE14 | F59: 2 | G59: 680.16 | H59: 0.28 | I59: Credit Card | J59: 979.4304
A60: SALE58 | B60: 45633 | C60: CUST1404 | D60: PROD15 | E60: STORE7 | F60: 4 | G60: 733.42 | I60: PayPal | J60: 2552.3016
A61: SALE59 | B61: 45257 | C61: CUST1367 | D61: PROD89 | E61: STORE11 | F61: 1 | G61: 996.33 | H61: 0.23 | I61: PayPal | J61: 767.1741
A62: SALE60 | B62: 45854 | C62: CUST1408 | D62: PROD31 | E62: STORE10 | F62: 1 | G62: 198.83 | H62: 0.09 | I62: COD | J62: 180.9353
A63: SALE61 | B63: 45716 | C63: CUST1239 | D63: PROD19 | E63: STORE7 | F63: 1 | G63: 374.92 | H63: 0.18 | I63: PayPal | J63: 307.4344
A64: SALE62 | B64: 45515 | C64: CUST1464 | D64: PROD93 | E64: STORE16 | F64: 1 | G64: 468.94 | H64: 0.12 | I64: Credit Card | J64: 412.6672
A65: SALE63 | B65: 45927 | C65: CUST1126 | D65: PROD89 | E65: STORE12 | F65: 2 | G65: 121.37 | H65: 0.05 | I65: Credit Card | J65: 230.603
A66: SALE64 | B66: 45914 | C66: CUST1255 | D66: PROD53 | E66: STORE10 | F66: 3 | G66: 480.06 | H66: 0.01 | I66: Credit Card
A67: SALE65 | B67: 45290 | C67: CUST1162 | D67: PROD99 | E67: STORE17 | F67: 2 | G67: 856.57 | H67: 0.24 | I67: Credit Card | J67: 1301.9864
A68: SALE66 | B68: 45213 | C68: CUST1269 | D68: PROD77 | E68: STORE2 | F68: 4 | G68: 814.25 | H68: 0.18 | I68: Credit Card | J68: 2670.74
A69: SALE67 | B69: 45255 | C69: CUST1483 | D69: PROD12 | E69: STORE2 | F69: 1 | G69: 989.17 | H69: 0.2 | I69: PayPal | J69: 791.336
A70: SALE68 | B70: 45270 | C70: CUST1372 | D70: PROD72 | E70: STORE10 | F70: 4 | G70: 62.48 | H70: 0.18 | I70: Credit Card | J70: 204.9344
A71: SALE69 | B71: 45897 | C71: CUST1423 | D71: PROD13 | E71: STORE16 | F71: 4 | G71: 561.24 | H71: 0.24 | I71: Credit Card | J71: 1706.1696
A72: SALE70 | B72: 45849 | C72: CUST1058 | D72: PROD60 | E72: STORE5 | F72: 3 | G72: 92.24 | H72: 0.28 | I72: COD
A73: SALE71 | B73: 45889 | C73: CUST1168 | D73: PROD72 | E73: STORE1 | F73: 2 | G73: 668.3 | H73: 0.07 | I73: Credit Card | J73: 1243.038
A74: SALE72 | B74: 45533 | C74: CUST1409 | D74: PROD38 | E74: STORE5 | F74: 1 | G74: 553.82 | H74: 0.09 | I74: Credit Card | J74: 503.9762
A75: SALE73 | B75: 45626 | C75: CUST1037 | D75: PROD45 | E75: STORE11 | F75: 2 | G75: 556.43 | H75: 0.13 | I75: Credit Card | J75: 968.1882
A76: SALE74 | B76: 45942 | C76: CUST1273 | D76: PROD20 | E76: STORE8 | F76: 1 | G76: 184.98 | H76: 0.1 | I76: COD | J76: 166.482
A77: SALE75 | B77: 45500 | C77: CUST1035 | D77: PROD97 | E77: STORE12 | F77: 4 | G77: 700.18 | H77: 0.23 | I77: Credit Card | J77: 2156.5544
A78: SALE76 | B78: 45285 | C78: CUST1019 | D78: PROD76 | E78: STORE10 | F78: 2 | G78: 686.31 | H78: 0.25 | I78: Credit Card | J78: 1029.465
A79: SALE77 | B79: 45800 | C79: CUST1007 | D79: PROD67 | E79: STORE15 | F79: 1 | G79: 687.82 | H79: 0.27 | I79: COD | J79: 502.1086
A80: SALE78 | B80: 45609 | C80: CUST1221 | D80: PROD83 | E80: STORE8 | F80: 2 | G80: 900.55 | H80: 0.16 | I80: Credit Card | J80: 1512.924
A81: SALE79 | B81: 45268 | C81: CUST1115 | D81: PROD21 | E81: STORE2 | F81: 1 | G81: 341.17 | H81: 0.15 | I81: Credit Card | J81: 289.9945
A82: SALE80 | B82: 45885 | C82: CUST1176 | D82: PROD52 | E82: STORE8 | F82: 1 | G82: 442.27 | H82: 0.06 | I82: COD | J82: 415.7338
A83: SALE81 | B83: 45616 | C83: CUST1253 | D83: PROD71 | E83: STORE9 | F83: 1 | G83: 363.73 | H83: 0.25 | I83: PayPal | J83: 272.7975
A84: SALE82 | B84: 45518 | C84: CUST1378 | D84: PROD91 | E84: STORE17 | F84: 2 | G84: 601.33 | H84: 0.16 | I84: PayPal | J84: 1010.2344
A85: SALE83 | B85: 45427 | C85: CUST1403 | D85: PROD17 | E85: STORE18 | F85: 4 | G85: 34.39 | H85: 0.03 | I85: PayPal | J85: 133.4332
A86: SALE84 | B86: 45268 | C86: CUST1423 | D86: PROD46 | E86: STORE17 | F86: 1 | G86: 773.57 | H86: 0.05 | I86: COD
A87: SALE85 | B87: 45282 | C87: CUST1054 | D87: PROD88 | E87: STORE7 | F87: 4 | G87: 127.1 | H87: 0.24 | I87: COD | J87: 386.384
A88: SALE86 | B88: 45545 | C88: CUST1303 | D88: PROD20 | E88: STORE3 | F88: 3 | G88: 899.58 | H88: 0.28 | I88: PayPal | J88: 1943.0928
A89: SALE87 | B89: 45755 | C89: CUST1327 | D89: PROD1 | E89: STORE10 | F89: 3 | G89: 964.39 | H89: 0.04 | I89: Credit Card | J89: 2777.4432
A90: SALE88 | B90: 45588 | C90: CUST1183 | D90: PROD38 | E90: STORE0 | F90: 2 | G90: 217.83 | H90: 0.14 | I90: PayPal | J90: 374.6676
A91: SALE89 | B91: 45848 | C91: CUST1143 | D91: PROD17 | E91: STORE1 | F91: 4 | G91: 187.71 | H91: 0.06 | I91: COD | J91: 705.7896
A92: SALE90 | B92: 45577 | C92: CUST1010 | D92: PROD33 | E92: STORE18 | F92: 2 | G92: 350.12 | H92: 0.12 | I92: COD | J92: 616.2112
A93: SALE91 | B93: 45312 | C93: CUST1406 | D93: PROD16 | E93: STORE1 | F93: 4 | G93: 102.19 | H93: 0.17 | I93: PayPal | J93: 339.2708
A94: SALE92 | B94: 45350 | C94: CUST1007 | D94: PROD86 | E94: STORE4 | F94: 1 | G94: 696.53 | H94: 0.17 | I94: Credit Card | J94: 578.1199
A95: SALE93 | B95: 45657 | C95: CUST1065 | D95: PROD19 | E95: STORE4 | F95: 2 | G95: 327.52 | H95: 0.15 | I95: PayPal | J95: 556.784
A96: SALE94 | B96: 45530 | C96: CUST1298 | D96: PROD97 | E96: STORE19 | F96: 2 | G96: 569.36 | H96: 0.01 | I96: PayPal
A97: SALE95 | B97: 45556 | C97: CUST1321 | D97: PROD99 | E97: STORE6 | F97: 2 | G97: 68.29 | H97: 0.14 | I97: COD | J97: 117.4588
A98: SALE96 | B98: 45523 | C98: CUST1244 | D98: PROD50 | E98: STORE10 | F98: 1 | G98: 842.9 | H98: 0.06 | I98: COD | J98: 792.326
A99: SALE97 | B99: 45587 | C99: CUST1287 | D99: PROD3 | E99: STORE3 | F99: 3 | G99: 751.94 | H99: 0.26 | I99: PayPal | J99: 1669.3068
A100: SALE98 | B100: 45580 | C100: CUST1131 | D100: PROD56 | E100: STORE7 | F100: 4 | G100: 476.28 | H100: 0.17 | I100: Credit Card | J100: 1581.2496
...
